Workbook

Sheet 役員報酬・社保
B2: 💰 役員報酬・社会保険料 計算シート
B3: 月額報酬・賞与・経費枠を入力すると、等級表で社保自動計算＋実質手取りも算出されます。
B5: ■ 保険料率設定（令和8年度 滋賀県）
B6: 項目 | C6: 率 | D6: 備考
B7: 健康保険料率（滋賀県R8） | C7: 0.0988 | D7: 令和8年3月分から。協会けんぽ滋賀支部
B8: 介護保険料率 | C8: 0.0162 | D8: 全国一律。40歳以上64歳以下に適用
B9: 子育て支援金率 | C9: 0.0023 | D9: 全国一律。R8年4月分（5月納付）から
B10: 厚生年金保険料率 | C10: 0.183 | D10: 全国一律（法定）
B11: 子ども・子育て拠出金率 | C11: 0.0036 | D11: 事業主のみ負担（本人負担なし）
B13: データソース: 協会けんぽ R8保険料額表、厚労省（2026年2月時点）
B14: ※ 令和8年4月からは防衛特別法人税（法人税額の4%）も加算。本シートでは未反映
B15: ■ 役員報酬設定（月額・手入力）
B16: 項目 | C16: 坂本 | D16: 櫻井 | E16: 町田 | F16: 備考
B17: 月額報酬（定期同額給与） | C17: 62000 | D17: 62000 | E17: 62000 | F17: 毎月同額。年度途中変更不可
B18: 年齢（40歳以上なら介護保険） | C18: いいえ | D18: いいえ | E18: いいえ | F18: 40〜64歳は介護保険対象
B19: 介護保険 対象？（自動判定） | C19: =IF(C18="はい","〇","×") -> × | D19: =IF(D18="はい","〇","×") -> × | E19: =IF(E18="はい","〇","×") -> × | F19: 自動
B20: flat.で社保加入？ | C20: はい | D20: はい | E20: はい | F20: いいえ=国保+国民年金
B21: 年間賞与（事前確定届出給与） | C21: 0 | D21: 0 | F21: 年1回想定。届出額と1円違うと全額否認
B24: ■ 標準報酬月額 等級表（健康保険1-30等級 / 厚生年金1-27等級）
B25: 健保等級 | C25: 厚年等級 | D25: 標準報酬月額 | E25: 報酬月額 下限 | F25: 報酬月額 上限
B26: 1 | D26: 58000 | E26: 0 | F26: 63000
B27: 2 | D27: 68000 | E27: 63000 | F27: 73000
B28: 3 | D28: 78000 | E28: 73000 | F28: 83000
B29: 4 | C29: 1 | D29: 88000 | E29: 83000 | F29: 93000
B30: 5 | C30: 2 | D30: 98000 | E30: 93000 | F30: 101000
B31: 6 | C31: 3 | D31: 104000 | E31: 101000 | F31: 107000
B32: 7 | C32: 4 | D32: 110000 | E32: 107000 | F32: 114000
B33: 8 | C33: 5 | D33: 118000 | E33: 114000 | F33: 122000
B34: 9 | C34: 6 | D34: 126000 | E34: 122000 | F34: 130000
B35: 10 | C35: 7 | D35: 134000 | E35: 130000 | F35: 138000
B36: 11 | C36: 8 | D36: 142000 | E36: 138000 | F36: 146000
B37: 12 | C37: 9 | D37: 150000 | E37: 146000 | F37: 155000
B38: 13 | C38: 10 | D38: 160000 | E38: 155000 | F38: 165000
B39: 14 | C39: 11 | D39: 170000 | E39: 165000 | F39: 175000
B40: 15 | C40: 12 | D40: 180000 | E40: 175000 | F40: 185000
... B55: 30 | C55: 27 | D55: 500000 | E55: 485000 | F55: 515000
B58: ■ 社会保険料 計算（月次）
B59: 項目 | C59: 坂本 | D59: 櫻井 | E59: 町田 | F59: 合計 | G59: 備考
B60: 標準報酬月額 | C60: =IF(C20="いいえ",0,IFERROR(INDEX($D$26:$D$55,MATCH(C17,$E$26:$E$55,1)),88000)) -> 58000 | D60: =IF(D20="いいえ",0,IFERROR(INDEX($D$26:$D$55,MATCH(D17,$E$26:$E$55,1)),88000)) -> 58000 | E60: =IF(E20="いいえ",0,IFERROR(INDEX($D$26:$D$55,MATCH(E17,$E$26:$E$55,1)),88000)) -> 58000 | F60: =SUM(C60:E60) -> 174000 | G60: 月額報酬から自動判定（加入していない人は0）
B61: 健康保険料（月額、会社+本人） | C61: =C60*($C$7+IF(C19="〇",$C$8,0)) -> 5730.4 | D61: =D60*($C$7+IF(D19="〇",$C$8,0)) -> 5730.4 | E61: =E60*($C$7+IF(E19="〇",$C$8,0)) -> 5730.4 | F61: =SUM(C61:E61) -> 17191.2 | G61: 介護対象者は+1.62%
B62: 子育て支援金（月額、会社+本人） | C62: =C60*$C$9 -> 133.4 | D62: =D60*$C$9 -> 133.4 | E62: =E60*$C$9 -> 133.4 | F62: =SUM(C62:E62) -> 400.2 | G62: R8年4月分（5月納付）から開始
B63: 厚生年金保険料（月額、会社+本人） | C63: =C60*$C$10 -> 10614 | D63: =D60*$C$10 -> 10614 | E63: =E60*$C$10 -> 10614 | F63: =SUM(C63:E63) -> 31842 | G63: 法定率18.3%
B64: 子ども・子育て拠出金（会社のみ） | C64: =C60*$C$11 -> 208.8 | D64: =D60*$C$11 -> 208.8 | E64: =E60*$C$11 -> 208.8 | F64: =SUM(C64:E64) -> 626.4 | G64: 全額会社負担（本人負担なし）
B65: 【月額】社会保険料 合計（会社+本人） | C65: =SUM(C61:C64) -> 16686.6 | D65: =SUM(D61:D64) -> 16686.6 | E65: =SUM(E61:E64) -> 16686.6 | F65: =SUM(C65:E65) -> 50059.8
B67: ── 本人負担（給与から天引き）
B68: 本人負担（月額） | C68: =(C61+C62+C63)/2 -> 8238.9 | D68: =(D61+D62+D63)/2 -> 8238.9 | E68: =(E61+E62+E63)/2 -> 8238.9 | F68: =SUM(C68:E68) -> 24716.7
B70: ── 会社負担（経費計上）
B71: 会社負担（月額） | C71: =(C61+C62+C63)/2+C64 -> 8447.7 | D71: =(D61+D62+D63)/2+D64 -> 8447.7 | E71: =(E61+E62+E63)/2+E64 -> 8447.7 | F71: =SUM(C71:E71) -> 25343.1
B74: ■ 賞与の社会保険料（年1回想定）
B75: 項目 | C75: 坂本 | D75: 櫻井 | E75: 町田 | F75: 合計 | G75: 備考
B76: 標準賞与額（1000円未満切捨） | C76: =IF(C20="いいえ",0,ROUNDDOWN(C21,-3)) -> 0 | D76: =IF(D20="いいえ",0,ROUNDDOWN(D21,-3)) -> 0 | E76: =IF(E20="いいえ",0,ROUNDDOWN(E21,-3)) -> 0 | F76: =SUM(C76:E76) -> 0 | G76: 上限: 年累計573万円（健保）、1回150万円（厚年）
B77: 賞与 社保料（会社+本人） | C77: =C76*($C$7+IF(C19="〇",$C$8,0)+$C$9+$C$10+$C$11) -> 0 | D77: =D76*($C$7+IF(D19="〇",$C$8,0)+$C$9+$C$10+$C$11) -> 0 | E77: =E76*($C$7+IF(E19="〇",$C$8,0)+$C$9+$C$10+$C$11) -> 0 | F77: =SUM(C77:E77) -> 0
B78: うち会社負担（経費） | C78: =C76*(($C$7+IF(C19="〇",$C$8,0)+$C$9+$C$10)/2+$C$11) -> 0 | D78: =D76*(($C$7+IF(D19="〇",$C$8,0)+$C$9+$C$10)/2+$C$11) -> 0 | E78: =E76*(($C$7+IF(E19="〇",$C$8,0)+$C$9+$C$10)/2+$C$11) -> 0 | F78: =SUM(C78:E78) -> 0
B81: ■ 年間サマリー（会社の総コスト）
B82: 項目 | C82: 坂本 | D82: 櫻井 | E82: 町田 | F82: 合計
B83: 年間 役員報酬（月額×12） | C83: =C17*12 -> 744000 | D83: =D17*12 -> 744000 | E83: =E17*12 -> 744000 | F83: =SUM(C83:E83) -> 2232000
B84: 年間 賞与 | C84: =C21 -> 0 | D84: =D21 -> 0 | E84: =E21 | F84: =SUM(C84:E84) -> 0
B85: 年間 社保 会社負担（月×12 + 賞与分） | C85: =C71*12+C78 -> 101372.4 | D85: =D71*12+D78 -> 101372.4 | E85: =E71*12+E78 -> 101372.4 | F85: =SUM(C85:E85) -> 304117.2
B86: 【年間】会社の総人件費コスト | C86: =C83+C84+C85 -> 845372.4 | D86: =D83+D84+D85 -> 845372.4 | E86: =E83+E84+E85 -> 845372.4 | F86: =SUM(C86:E86) -> 2536117.2
B88: 【年間】本人手取り（ざっくり：報酬+賞与 − 社保本人負担 − 所得税住民税10%想定） | C88: =(C83+C84)-(C68*12+(C77-C78))-(C83+C84)*0.1 -> 570733.2 | D88: =(D83+D84)-(D68*12+(D77-D78))-(D83+D84)*0.1 -> 570733.2 | E88: =(E83+E84)-(E68*12+(E77-E78))-(E83+E84)*0.1 -> 570733.2 | F88: =SUM(C88:E88) -> 1712199.6
B91: ■ 経費（カテゴリ別 月間予算）
B92: 役員が実際に使う経費の月額予算。実費精算ベース。
B93: ※ 領収書必須。日当のみ出張旅費規程で定額OK。社保・所得税の対象外。
B95: カテゴリ | C95: 坂本 | D95: 櫻井 | E95: 町田 | F95: 合計 | G95: 備考
B96: 交通費（実費） | C96: 0 | D96: 0 | E96: 0 | F96: =SUM(C96:E96) -> 0 | G96: 電車・バス・ガソリン代の実費
B97: 出張旅費（実費・遠方） | C97: 0 | D97: 0 | E97: 0 | F97: =SUM(C97:E97) -> 0 | G97: 宿泊・遠方移動。櫻井は東京⇔彦根想定
B98: 日当（出張旅費規程） | C98: 0 | D98: 0 | E98: 0 | F98: =SUM(C98:E98) -> 0 | G98: 規程で定額。所得税・社保非課税
B99: 交際費（接待・取引先） | C99: 0 | D99: 0 | E99: 0 | F99: =SUM(C99:E99) -> 0 | G99: 取引先・関係者との会食
B100: 会議費（社内） | C100: 0 | D100: 0 | E100: 0 | F100: =SUM(C100:E100) -> 0 | G100: 1人5千円以下なら全額損金OK
B101: 通信費（業務用） | C101: 0 | D101: 0 | E101: 0 | F101: =SUM(C101:E101) -> 0 | G101: スマホ業務利用分
B102: 図書費・研修費 | C102: 0 | D102: 0 | E102: 0 | F102: =SUM(C102:E102) -> 0 | G102: 書籍・セミナー・視察
B103: 月間 経費 合計 | C103: =SUM(C96:C102) -> 0 | D103: =SUM(D96:D102) -> 0 | E103: =SUM(E96:E102) -> 0 | F103: =SUM(C103:E103) -> 0
B104: 年間 経費 合計（×8ヶ月、8月開業想定） | C104: =C103*8 -> 0 | D104: =D103*8 -> 0 | E104: =E103*8 -> 0 | F104: =SUM(C104:E104) -> 0
B107: ■ 1人あたり 月の実質手取り（参考）
B108: ※ 所得税・住民税はざっくり10%想定。税理士相談時に精緻化
B110: 項目 | C110: 坂本 | D110: 櫻井 | E110: 町田 | F110: 合計
B111: 月額役員報酬 | C111: =C17 -> 62000 | D111: =D17 -> 62000 | E111: =E17 -> 62000 | F111: =SUM(C111:E111) -> 186000
B112: ＋ 月間経費 | C112: =C103 -> 0 | D112: =D103 -> 0 | E112: =E103 -> 0 | F112: =SUM(C112:E112) -> 0
B113: − 月額 社保 本人負担 | C113: =C68 -> 8238.9 | D113: =D68 -> 8238.9 | E113: =E68 -> 8238.9 | F113: =SUM(C113:E113) -> 24716.7
B114: − 月額 所得税住民税（報酬の10%想定） | C114: =C17*0.1 -> 6200 | D114: =D17*0.1 -> 6200 | E114: =E17*0.1 -> 6200 | F114: =SUM(C114:E114) -> 18600
B115: 【月】実質手取り相当額 | C115: =C111+C112-C113-C114 -> 47561.1 | D115: =D111+D112-D113-D114 -> 47561.1 | E115: =E111+E112-E113-E114 -> 47561.1 | F115: =SUM(C115:E115) -> 142683.3
B118: ■ 月別労働時間 実績記録（1年目）
B119: 毎月の労働時間を実績で記入。翌年度の役員報酬上乗せ枠の算出に使用。
B120: ※ 1,080円/h で評価。労働対価は1年目の口座流出にはカウントしない（記録のみ）
B122: 月 | C122: 8月 | D122: 9月 | E122: 10月 | F122: 11月 | G122: 12月 | H122: 1月 | I122: 2月 | J122: 3月 | K122: 年間合計 | L122: 評価額(×1,080)
B123: 坂本 労働時間/月 | C123: 0 | D123: 0 | E123: 0 | F123: 0 | G123: 0 | H123: 0 | I123: 0 | J123: 0 | K123: =SUM(C123:J123) -> 0 | L123: =K123*1080 -> 0
B124: 櫻井 労働時間/月 | C124: 0 | D124: 0 | E124: 0 | F124: 0 | G124: 0 | H124: 0 | I124: 0 | J124: 0 | K124: =SUM(C124:J124) -> 0 | L124: =K124*1080 -> 0
B125: 町田 労働時間/月 | C125: 0 | D125: 0 | E125: 0 | F125: 0 | G125: 0 | H125: 0 | I125: 0 | J125: 0 | K125: =SUM(C125:J125) -> 0 | L125: =K125*1080 -> 0
B128: ■ 翌年精算枠（翌年度の役員報酬上乗せ計算）
B129: 1年目の労働評価額 − 1年目に使った経費 = 翌年度に上乗せできる枠
B130: ※ この枠を12分割して翌年の月額役員報酬に上乗せ（定期同額給与のルールを守れる）
B132: 項目 | C132: 坂本 | D132: 櫻井 | E132: 町田 | F132: 合計
B133: ① 1年目 労働評価額 | C133: =L123 -> 0 | D133: =L124 -> 0 | E133: =L125 -> 0 | F133: =SUM(C133:E133) -> 0
B134: ② 1年目 使用経費（年間合計） | C134: =C104 -> 0 | D134: =D104 -> 0 | E134: =E104 -> 0 | F134: =SUM(C134:E134) -> 0
B135: ③ 翌年精算枠（① − ②） | C135: =MAX(0,C133-C134) -> 0 | D135: =MAX(0,D133-D134) -> 0 | E135: =MAX(0,E133-E134) -> 0 | F135: =SUM(C135:E135) -> 0
B136: ④ 翌年 月額上乗せ（③ ÷ 12ヶ月） | C136: =C135/12 -> 0 | D136: =D135/12 -> 0 | E136: =E135/12 -> 0 | F136: =SUM(C136:E136) -> 0
B137: ⑤ 翌年 月額役員報酬目安（62,000 + ④） | C137: =62000+C136 -> 62000 | D137: =62000+D136 -> 62000 | E137: =62000+E136 -> 62000 | F137: =SUM(C137:E137) -> 186000
B140: ■ 使い方
B141: ① 月の役員報酬（C17-E17）は全員62,000円固定
B142: ② 経費カテゴリ別の月間予算（C列-E列）に実費の見込み額を入力
...

Sheet freee実績
A1: 日付 | B1: 年月 | C1: 勘定科目 | D1: 品目 | E1: 金額 | F1: 取引ID | H1: ※このタブはfreee取込専用。B列「年月」はYYYY-MM形式の文字列で入れること（例: 2026-08）。月次シートのSUMIFSがこの値で集計する。

Sheet 4月
B1: ☕ カフェ経営管理 ─ 4月 | U1: ■ 計画値（売上計画シートから自動取得）
B2: 月末口座（人件費なし） | C2: =I75 -> 0 | E2: 今月出ていくお金 | F2: =C16+SUM(C20:C23)+SUM(C25:C28)+M36+D54+M41 -> 0 | H2: 今月の利益 | I2: =I39 -> 0 | L2: 来月必要なお金 | M2: ='5月'!C20+'5月'!C21+'5月'!C22+'5月'!C23+'5月'!C25 -> 0 | U2: 実績の入力時に参考にしてください。差額・達成率も自動表示。
B3: ■ 資金（期首残高） | G3: ■ 売上（定期収入） | L3: ■ 人件費計算
B4: 科目 | C4: 金額 | D4: 詳細 | E4: メモ | G4: カテゴリ | H4: 金額 | I4: 詳細 | J4: メモ | L4: スタッフ名 | M4: 時給 | N4: 日数 | O4: 時間/日 | P4: 交通費/日 | Q4: 小計（給与） | R4: 小計（交通費） | U4: ■ 売上
B5: 自己資金（資本金） | G5: ドリンク（コーヒー） | H5: ='4月日次売上'!C34 -> 0 | Q5: =M5*N5*O5 -> 0 | R5: =P5*N5 -> 0 | U5: 項目 | V5: 計画 | W5: 実績 | X5: 差額 | Y5: 達成率
B6: 追加資金（借入等） | G6: ドリンク（紅茶・その他） | H6: ='4月日次売上'!D34 -> 0 | Q6: =M6*N6*O6 -> 0 | R6: =P6*N6 -> 0 | U6: 昼 来客数（季節調整後）/日 | V6: ='売上計画'!C38 -> 0 | W6: =IF(H26=0,"",H24/H26/2) | X6: =IF(W6="",0,W6-V6) -> 0 | Y6: =IF(OR(W6="",V6=0),0,W6/V6) -> 0
B7: 期首資金 合計 | C7: =SUM(C5:C6) -> 0 | G7: フード（軽食） | H7: ='4月日次売上'!E34 -> 0 | Q7: =M7*N7*O7 -> 0 | R7: =P7*N7 -> 0 | U7: 夜 来客数（季節調整後）/日 | V7: ='売上計画'!C39 -> 0 | W7: =IF(H26=0,"",H24/H26/2) | X7: =IF(W7="",0,W7-V7) -> 0 | Y7: =IF(OR(W7="",V7=0),0,W7/V7) -> 0
G8: フード（スイーツ） | H8: ='4月日次売上'!F34 -> 0 | Q8: =M8*N8*O8 -> 0 | R8: =P8*N8 -> 0 | U8: 売上合計（月間） | V8: ='売上計画'!C45 -> 0 | W8: =H20 -> 0 | X8: =W8-V8 -> 0 | Y8: =IF(V8=0,0,W8/V8) -> 0
B9: ■ 原価（売上原価） | G9: 物販（コーヒー豆・グッズ） | H9: ='4月日次売上'!G34 -> 0 | Q9: =M9*N9*O9 -> 0 | R9: =P9*N9 -> 0 | U9: 客単価 | V9: =IF((V6*'売上計画'!$C$7+V7*'売上計画'!$C$8)=0,0,V8/(V6*'売上計画'!$C$7+V7*'売上計画'!$C$8)) -> 0 | W9: =H25 -> 0 | X9: =W9-V9 -> 0 | Y9: =IF(V9=0,0,W9/V9) -> 0
B10: 科目 | C10: 金額 | D10: 詳細 | E10: メモ | G10: テイクアウト | H10: ='4月日次売上'!H34 -> 0 | Q10: =M10*N10*O10 -> 0 | R10: =P10*N10 -> 0
B11: コーヒー豆・茶葉 | C11: =SUMIFS('freee実績'!$E:$E,'freee実績'!$B:$B,"2026-04",'freee実績'!$C:$C,"仕入高",'freee実績'!$D:$D,"コーヒー豆・茶葉") -> 0 | G11: 売上 合計 | H11: =SUM(H5:H10) -> 0 | Q11: =M11*N11*O11 -> 0 | R11: =P11*N11 -> 0 | U11: ■ 原価・粗利
B12: 牛乳・シロップ等 | C12: =SUMIFS('freee実績'!$E:$E,'freee実績'!$B:$B,"2026-04",'freee実績'!$C:$C,"仕入高",'freee実績'!$D:$D,"牛乳・シロップ等") -> 0 | Q12: =M12*N12*O12 -> 0 | R12: =P12*N12 -> 0 | U12: 項目 | V12: 計画 | W12: 実績 | X12: 差額 | Y12: 原価率
B13: フード材料費 | C13: =SUMIFS('freee実績'!$E:$E,'freee実績'!$B:$B,"2026-04",'freee実績'!$C:$C,"仕入高",'freee実績'!$D:$D,"フード材料費") -> 0 | G13: ■ その他収入（不定期） | L13: アルバイト給与 合計 | Q13: =SUM(Q5:Q12) -> 0 | R13: =SUM(R5:R12) -> 0 | U13: 原価合計 | V13: ='売上計画'!C46 -> 0 | W13: =C16 -> 0 | X13: =W13-V13 -> 0 | Y13: =IF(W8=0,0,W13/W8) -> 0
B14: 包装資材・消耗品 | C14: =SUMIFS('freee実績'!$E:$E,'freee実績'!$B:$B,"2026-04",'freee実績'!$C:$C,"仕入高",'freee実績'!$D:$D,"包装資材・消耗品") -> 0 | G14: カテゴリ | H14: 金額 | I14: 詳細 | J14: メモ | U14: 粗利益 | V14: ='売上計画'!C47 -> 0 | W14: =H20-C16 -> 0 | X14: =W14-V14 -> 0 | Y14: =IF(W8=0,0,W14/W8) -> 0
B15: その他原価 | C15: =SUMIFS('freee実績'!$E:$E,'freee実績'!$B:$B,"2026-04",'freee実績'!$C:$C,"仕入高",'freee実績'!$D:$D,"その他原価") -> 0 | G15: イベント・貸切 | H15: ='4月日次売上'!I34 -> 0 | L15: ■ 固定人件費（役員報酬・社員給与等）
B16: 原価 合計 | C16: =SUM(C11:C15) -> 0 | G16: その他収入② | L16: 項目 | M16: 月額 | R16: 備考 | U16: ■ 経費
G17: その他収入 | L17: 役員報酬 | U17: 項目 | V17: 計画 | W17: 実績 | X17: 差額
B18: ■ 経費（販管費） | G18: その他収入 合計 | H18: =SUM(H15:H17) -> 0 | L18: 社員給与 | U18: 人件費（バイト+固定） | V18: ='売上計画'!C54 -> 0 | W18: =C24 -> 0 | X18: =W18-V18 -> 0
B19: 科目 | C19: 金額 | D19: 詳細 | E19: メモ | L19: 社会保険料（会社負担） | U19: 固定費（家賃+光熱+通信+保険） | V19: ='売上計画'!C57 -> 0 | W19: =C20+C21+C22+C23 -> 0 | X19: =W19-V19 -> 0
B20: 家賃 | C20: =SUMIFS('freee実績'!$E:$E,'freee実績'!$B:$B,"2026-04",'freee実績'!$C:$C,"地代家賃") -> 0 | D20: 固定費 | G20: 売上合計（定期＋不定期） | H20: =H11+H18 -> 0 | L20: その他人件費 | U20: 消耗品 | V20: ='売上計画'!C58 -> 0 | W20: =C25 -> 0 | X20: =W20-V20 -> 0
B21: 水道光熱費 | C21: =SUMIFS('freee実績'!$E:$E,'freee実績'!$B:$B,"2026-04",'freee実績'!$C:$C,"水道光熱費") -> 0 | D21: 固定費 | L21: 固定人件費 合計 | M21: =SUM(M17:M20) -> 0 | U21: 経費合計 | V21: ='売上計画'!C59 -> 0 | W21: =C30 -> 0 | X21: =W21-V21 -> 0
B22: 通信費 | C22: =SUMIFS('freee実績'!$E:$E,'freee実績'!$B:$B,"2026-04",'freee実績'!$C:$C,"通信費") -> 0 | D22: 固定費 | G22: ■ 売上KPI
B23: 保険料 | C23: =SUMIFS('freee実績'!$E:$E,'freee実績'!$B:$B,"2026-04",'freee実績'!$C:$C,"保険料") -> 0 | D23: 固定費 | G23: 指標 | H23: 数値 | J23: 算出方法 | L23: 人件費 総合計 | M23: =Q13+R13+M21 -> 0 | U23: ■ 営業利益
B24: 人件費（給与・社保） | C24: =M23 -> 0 | D24: 変動費 | G24: 来客数（人） | H24: ='4月日次売上'!J34 -> 0 | U24: 項目 | V24: 計画 | W24: 実績 | X24: 差額 | Y24: 達成率
B25: 消耗品費 | C25: =SUMIFS('freee実績'!$E:$E,'freee実績'!$B:$B,"2026-04",'freee実績'!$C:$C,"消耗品費") -> 0 | D25: 変動費 | G25: 客単価 | H25: =IF(H24=0,0,H20/H24) -> 0 | J25: 売上÷来客数 | L25: ↑ この金額を左側「人件費（給与・社保）」に転記 | U25: 営業利益 | V25: ='売上計画'!C61 | W25: =I39 -> 0 | X25: =W25-V25 -> 0 | Y25: =IF(V25=0,0,W25/V25) -> 0
B26: 広告宣伝費 | C26: =SUMIFS('freee実績'!$E:$E,'freee実績'!$B:$B,"2026-04",'freee実績'!$C:$C,"広告宣伝費") -> 0 | D26: 変動費 | G26: 営業日数 | H26: 0 | U26: 営業利益率 | V26: ='売上計画'!C62 -> 0 | W26: =IF(W8=0,0,W25/W8) -> 0 | X26: =W26-V26 -> 0
B27: 修繕費 | C27: =SUMIFS('freee実績'!$E:$E,'freee実績'!$B:$B,"2026-04",'freee実績'!$C:$C,"修繕費") -> 0 | D27: 変動費 | G27: 日商（1日平均売上） | H27: =IF(H26=0,0,H20/H26) -> 0 | J27: 売上÷営業日数 | L27: ■ 人件費KPI
B28: その他経費 | C28: =SUMIFS('freee実績'!$E:$E,'freee実績'!$B:$B,"2026-04",'freee実績'!$C:$C,"雑費") -> 0 | D28: 変動費 | G28: 原価率 | H28: =IF(H20=0,0,C16/H20) -> 0 | J28: 原価÷売上 | L28: 指標 | M28: 数値 | R28: 算出方法
B29: 減価償却費 | C29: ='固定資産台帳'!L26 -> 0 | D29: 帳簿上のみ | L29: 人件費率 | M29: =IF(H20=0,0,M23/H20) -> 0 | R29: 人件費÷売上
B30: 経費 合計 | C30: =SUM(C20:C29) -> 0 | L30: 人時売上高 | M30: =IF((SUM(N5:N12)*SUM(O5:O12))=0,0,H20/(SUM(N5:N12)*SUM(O5:O12))) -> 0 | R30: 売上÷総労働時間
B32: ■ 一括経費（設備投資等） | G32: ■ 月次損益計算 | L32: ■ オーナー人件費 未払い管理
B33: 科目 | C33: 予算 | D33: 実績 | E33: 差額（残） | F33: メモ | H33: 項目 | I33: 金額 | L33: 帳簿上は計上、実際の支払いは利益が出てから
H34: 売上高 | I34: =H20 -> 0 | L34: 今月の人件費 支払い？ | M34: 未払い | N34: ← 「支払い」か「未払い」を入力
E35: =C35-D35 -> 0 | H35: 原価合計 | I35: =C16 -> 0 | L35: 人件費（帳簿計上額） | M35: =M23 -> 0 | N35: P/Lに反映
E36: =C36-D36 -> 0 | H36: 粗利益 | I36: =I34-I35 -> 0 | L36: 実際の支払い額 | M36: =IF(M34="支払い",M35,0) -> 0 | N36: 口座から出るお金
E37: =C37-D37 -> 0 | H37: 粗利率 | I37: =IF(I34=0,0,I36/I34) -> 0 | L37: 今月の未払い額 | M37: =M35-M36 -> 0 | N37: 帳簿上は経費だが現金は出ない
E38: =C38-D38 -> 0 | H38: 経費合計 | I38: =C30 -> 0 | L38: 前月までの未払い累計 | M38: 0
E39: =C39-D39 -> 0 | H39: 営業利益 | I39: =I36-I38 -> 0 | L39: 未払い累計（今月末時点） | M39: =M38+M37 -> 0 | N39: 将来支払う必要のある額
E40: =C40-D40 -> 0
E41: =C41-D41 -> 0 | L41: 過去の未払い分 今月支払額 | N41: 未払い累計から取り崩す場合に入力
E42: =C42-D42 -> 0
E43: =C43-D43 -> 0
E44: =C44-D44 -> 0
E45: =C45-D45 -> 0
E46: =C46-D46 -> 0
E47: =C47-D47 -> 0
E48: =C48-D48 -> 0
E49: =C49-D49 -> 0
E50: =C50-D50 -> 0
E51: =C51-D51 -> 0
E52: =C52-D52 -> 0
E53: =C53-D53 -> 0
B54: 一括経費 合計 | C54: =SUM(C34:C53) -> 0 | D54: =SUM(D34:D53) -> 0 | E54: =C54-D54 -> 0
B56: コスト合計（原価＋経費＋一括） | C56: =C16+C30+D54 -> 0
G58: ■ キャッシュフロー（実際のお金の動き）
H59: 項目 | I59: 金額
H60: 営業利益 | I60: =I39 -> 0
H61: ＋ 減価償却費（現金支出なし） | I61: =C29 -> 0 | J61: 損益上の経費だが現金は出ない
H62: 営業CF | I62: =I60+I61+M37-M41 -> 0 | J62: 実際に営業で増えた現金
H64: − 設備投資（一括経費） | I64: =D54 -> 0 | J64: 実際に出ていった現金
H65: 投資CF | I65: =-I64 -> 0 | J65: 設備購入で減った現金
H67: 追加資金（借入・増資等） | I67: =C6
H68: 財務CF | I68: =I67
G70: ■ 口座残高
H71: 前月末 口座残高 | I71: =C5
H72: ＋ 営業CF | I72: =I62 -> 0
H73: ＋ 投資CF | I73: =I65 -> 0
H74: ＋ 財務CF | I74: =I68
H75: 期末 口座残高 | I75: =I71+I72+I73+I74 -> 0 | J75: 翌月に繰越
H77: 【参考】損益と現金の差
H78: 帳簿上の利益（営業利益） | I78: =I39 -> 0
H79: 実際の現金増減（CF合計） | I79: =I72+I73+I74 -> 0
H80: 差額（減価償却＋設備投資） | I80: =I79-I78 -> 0 | J80: ＋なら利益より現金が多い
H82: 期末口座（人件費なし） | I82: =I75 -> 0 | J82: 3人の給与を払わない場合
H83: 期末口座（人件費あり） | I83: =I75-M37 -> 0 | J83: 3人に給与を払った場合

Sheet 5月
B1: ☕ カフェ経営管理 ─ 5月 | U1: ■ 計画値（売上計画シートから自動取得）
B2: 月末口座（人件費なし） | C2: =I75 -> 2886000 | E2: 今月出ていくお金 | F2: =C16+SUM(C20:C23)+SUM(C25:C28)+M36+D54+M41 -> 114000 | H2: 今月の利益 | I2: =I39 -> 0 | L2: 来月必要なお金 | M2: ='6月'!C20+'6月'!C21+'6月'!C22+'6月'!C23+'6月'!C25 -> 0 | U2: 実績の入力時に参考にしてください。差額・達成率も自動表示。
B3: ■ 資金（期首残高） | G3: ■ 売上（定期収入） | L3: ■ 人件費計算
B4: 科目 | C4: 金額 | D4: 詳細 | E4: メモ | G4: カテゴリ | H4: 金額 | I4: 詳細 | J4: メモ | L4: スタッフ名 | M4: 時給 | N4: 日数 | O4: 時間/日 | P4: 交通費/日 | Q4: 小計（給与） | R4: 小計（交通費） | U4: ■ 売上
B5: 前月繰越金 | C5: 3000000 | E5: 出資金合計300万円(創業メンバー4名による出資) | G5: ドリンク（コーヒー） | H5: ='5月日次売上'!C35 -> 0 | Q5: =M5*N5*O5 -> 0 | R5: =P5*N5 -> 0 | U5: 項目 | V5: 計画 | W5: 実績 | X5: 差額 | Y5: 達成率
B6: 追加資金（借入等） | G6: ドリンク（紅茶・その他） | H6: ='5月日次売上'!D35 -> 0 | Q6: =M6*N6*O6 -> 0 | R6: =P6*N6 -> 0 | U6: 昼 来客数（季節調整後）/日 | V6: ='売上計画'!D38 -> 0 | W6: =IF(H26=0,"",H24/H26/2) | X6: =IF(W6="",0,W6-V6) -> 0 | Y6: =IF(OR(W6="",V6=0),0,W6/V6) -> 0
B7: 期首資金 合計 | C7: =SUM(C5:C6) -> 3000000 | G7: フード（軽食） | H7: ='5月日次売上'!E35 -> 0 | Q7: =M7*N7*O7 -> 0 | R7: =P7*N7 -> 0 | U7: 夜 来客数（季節調整後）/日 | V7: ='売上計画'!D39 -> 0 | W7: =IF(H26=0,"",H24/H26/2) | X7: =IF(W7="",0,W7-V7) -> 0 | Y7: =IF(OR(W7="",V7=0),0,W7/V7) -> 0
G8: フード（スイーツ） | H8: ='5月日次売上'!F35 -> 0 | Q8: =M8*N8*O8 -> 0 | R8: =P8*N8 -> 0 | U8: 売上合計（月間） | V8: ='売上計画'!D45 -> 0 | W8: =H20 -> 0 | X8: =W8-V8 -> 0 | Y8: =IF(V8=0,0,W8/V8) -> 0
B9: ■ 原価（売上原価） | G9: 物販（コーヒー豆・グッズ） | H9: ='5月日次売上'!G35 -> 0 | Q9: =M9*N9*O9 -> 0 | R9: =P9*N9 -> 0 | U9: 客単価 | V9: =IF((V6*'売上計画'!$C$7+V7*'売上計画'!$C$8)=0,0,V8/(V6*'売上計画'!$C$7+V7*'売上計画'!$C$8)) -> 0 | W9: =H25 -> 0 | X9: =W9-V9 -> 0 | Y9: =IF(V9=0,0,W9/V9) -> 0
B10: 科目 | C10: 金額 | D10: 詳細 | E10: メモ | G10: テイクアウト | H10: ='5月日次売上'!H35 -> 0 | Q10: =M10*N10*O10 -> 0 | R10: =P10*N10 -> 0
B11: コーヒー豆・茶葉 | C11: =SUMIFS('freee実績'!$E:$E,'freee実績'!$B:$B,"2026-05",'freee実績'!$C:$C,"仕入高",'freee実績'!$D:$D,"コーヒー豆・茶葉") -> 0 | G11: 売上 合計 | H11: =SUM(H5:H10) -> 0 | Q11: =M11*N11*O11 -> 0 | R11: =P11*N11 -> 0 | U11: ■ 原価・粗利
B12: 牛乳・シロップ等 | C12: =SUMIFS('freee実績'!$E:$E,'freee実績'!$B:$B,"2026-05",'freee実績'!$C:$C,"仕入高",'freee実績'!$D:$D,"牛乳・シロップ等") -> 0 | Q12: =M12*N12*O12 -> 0 | R12: =P12*N12 -> 0 | U12: 項目 | V12: 計画 | W12: 実績 | X12: 差額 | Y12: 原価率
B13: フード材料費 | C13: =SUMIFS('freee実績'!$E:$E,'freee実績'!$B:$B,"2026-05",'freee実績'!$C:$C,"仕入高",'freee実績'!$D:$D,"フード材料費") -> 0 | G13: ■ その他収入（不定期） | L13: アルバイト給与 合計 | Q13: =SUM(Q5:Q12) -> 0 | R13: =SUM(R5:R12) -> 0 | U13: 原価合計 | V13: ='売上計画'!D46 -> 0 | W13: =C16 -> 0 | X13: =W13-V13 -> 0 | Y13: =IF(W8=0,0,W13/W8) -> 0
B14: 包装資材・消耗品 | C14: =SUMIFS('freee実績'!$E:$E,'freee実績'!$B:$B,"2026-05",'freee実績'!$C:$C,"仕入高",'freee実績'!$D:$D,"包装資材・消耗品") -> 0 | G14: カテゴリ | H14: 金額 | I14: 詳細 | J14: メモ | U14: 粗利益 | V14: ='売上計画'!D47 -> 0 | W14: =H20-C16 -> 0 | X14: =W14-V14 -> 0 | Y14: =IF(W8=0,0,W14/W8) -> 0
B15: その他原価 | C15: =SUMIFS('freee実績'!$E:$E,'freee実績'!$B:$B,"2026-05",'freee実績'!$C:$C,"仕入高",'freee実績'!$D:$D,"その他原価") -> 0 | G15: イベント・貸切 | H15: ='5月日次売上'!I35 -> 0 | L15: ■ 固定人件費（役員報酬・社員給与等）
B16: 原価 合計 | C16: =SUM(C11:C15) -> 0 | G16: その他収入② | L16: 項目 | M16: 月額 | R16: 備考 | U16: ■ 経費
G17: その他収入 | L17: 役員報酬 | U17: 項目 | V17: 計画 | W17: 実績 | X17: 差額
B18: ■ 経費（販管費） | G18: その他収入 合計 | H18: =SUM(H15:H17) -> 0 | L18: 社員給与 | U18: 人件費（バイト+固定） | V18: ='売上計画'!D54 -> 0 | W18: =C24 -> 0 | X18: =W18-V18 -> 0
B19: 科目 | C19: 金額 | D19: 詳細 | E19: メモ | L19: 社会保険料（会社負担） | U19: 固定費（家賃+光熱+通信+保険） | V19: ='売上計画'!D57 -> 0 | W19: =C20+C21+C22+C23 -> 0 | X19: =W19-V19 -> 0
B20: 家賃 | C20: =SUMIFS('freee実績'!$E:$E,'freee実績'!$B:$B,"2026-05",'freee実績'!$C:$C,"地代家賃") -> 0 | D20: 固定費 | G20: 売上合計（定期＋不定期） | H20: =H11+H18 -> 0 | L20: その他人件費 | U20: 消耗品 | V20: ='売上計画'!D58 -> 0 | W20: =C25 -> 0 | X20: =W20-V20 -> 0
B21: 水道光熱費 | C21: =SUMIFS('freee実績'!$E:$E,'freee実績'!$B:$B,"2026-05",'freee実績'!$C:$C,"水道光熱費") -> 0 | D21: 固定費 | L21: 固定人件費 合計 | M21: =SUM(M17:M20) -> 0 | U21: 経費合計 | V21: ='売上計画'!D59 -> 0 | W21: =C30 -> 0 | X21: =W21-V21 -> 0
B22: 通信費 | C22: =SUMIFS('freee実績'!$E:$E,'freee実績'!$B:$B,"2026-05",'freee実績'!$C:$C,"通信費") -> 0 | D22: 固定費 | G22: ■ 売上KPI
B23: 保険料 | C23: =SUMIFS('freee実績'!$E:$E,'freee実績'!$B:$B,"2026-05",'freee実績'!$C:$C,"保険料") -> 0 | D23: 固定費 | G23: 指標 | H23: 数値 | J23: 算出方法 | L23: 人件費 総合計 | M23: =Q13+R13+M21 -> 0 | U23: ■ 営業利益
B24: 人件費（給与・社保） | C24: =M23 -> 0 | D24: 変動費 | G24: 来客数（人） | H24: ='5月日次売上'!J35 -> 0 | U24: 項目 | V24: 計画 | W24: 実績 | X24: 差額 | Y24: 達成率
B25: 消耗品費 | C25: =SUMIFS('freee実績'!$E:$E,'freee実績'!$B:$B,"2026-05",'freee実績'!$C:$C,"消耗品費") -> 0 | D25: 変動費 | G25: 客単価 | H25: =IF(H24=0,0,H20/H24) -> 0 | J25: 売上÷来客数 | L25: ↑ この金額を左側「人件費（給与・社保）」に転記 | U25: 営業利益 | V25: ='売上計画'!D61 | W25: =I39 -> 0 | X25: =W25-V25 -> 0 | Y25: =IF(V25=0,0,W25/V25) -> 0
B26: 広告宣伝費 | C26: =SUMIFS('freee実績'!$E:$E,'freee実績'!$B:$B,"2026-05",'freee実績'!$C:$C,"広告宣伝費") -> 0 | D26: 変動費 | G26: 営業日数 | H26: 0 | U26: 営業利益率 | V26: ='売上計画'!D62 -> 0 | W26: =IF(W8=0,0,W25/W8) -> 0 | X26: =W26-V26 -> 0
B27: 修繕費 | C27: =SUMIFS('freee実績'!$E:$E,'freee実績'!$B:$B,"2026-05",'freee実績'!$C:$C,"修繕費") -> 0 | D27: 変動費 | G27: 日商（1日平均売上） | H27: =IF(H26=0,0,H20/H26) -> 0 | J27: 売上÷営業日数 | L27: ■ 人件費KPI
B28: その他経費 | C28: =SUMIFS('freee実績'!$E:$E,'freee実績'!$B:$B,"2026-05",'freee実績'!$C:$C,"雑費") -> 0 | D28: 変動費 | G28: 原価率 | H28: =IF(H20=0,0,C16/H20) -> 0 | J28: 原価÷売上 | L28: 指標 | M28: 数値 | R28: 算出方法
B29: 減価償却費 | C29: ='固定資産台帳'!M26 -> 0 | D29: 帳簿上のみ | L29: 人件費率 | M29: =IF(H20=0,0,M23/H20) -> 0 | R29: 人件費÷売上
B30: 経費 合計 | C30: =SUM(C20:C29) -> 0 | L30: 人時売上高 | M30: =IF((SUM(N5:N12)*SUM(O5:O12))=0,0,H20/(SUM(N5:N12)*SUM(O5:O12))) -> 0 | R30: 売上÷総労働時間
B32: ■ 一括経費（設備投資等） | G32: ■ 月次損益計算 | L32: ■ オーナー人件費 未払い管理
B33: 科目 | C33: 予算 | D33: 実績 | E33: 差額（残） | F33: メモ | H33: 項目 | I33: 金額 | L33: 帳簿上は計上、実際の支払いは利益が出てから
B34: 設備購入 | E34: =C34-D34 -> 0 | H34: 売上高 | I34: =H20 -> 0 | L34: 今月の人件費 支払い？ | M34: 未払い | N34: ← 「支払い」か「未払い」を入力
B35: 内装工事 | E35: =C35-D35 -> 0 | H35: 原価合計 | I35: =C16 -> 0 | L35: 人件費（帳簿計上額） | M35: =M23 -> 0 | N35: P/Lに反映
B36: その他一括経費 | E36: =C36-D36 -> 0 | H36: 粗利益 | I36: =I34-I35 -> 0 | L36: 実際の支払い額 | M36: =IF(M34="支払い",M35,0) -> 0 | N36: 口座から出るお金
H37: 粗利率 | I37: =IF(I34=0,0,I36/I34) -> 0 | L37: 今月の未払い額 | M37: =M35-M36 -> 0 | N37: 帳簿上は経費だが現金は出ない
H38: 経費合計 | I38: =C30 -> 0 | L38: 前月までの未払い累計 | M38: ='4月'!M39 -> 0
H39: 営業利益 | I39: =I36-I38 -> 0 | L39: 未払い累計（今月末時点） | M39: =M38+M37 -> 0 | N39: 将来支払う必要のある額
B40: 許認可・法人設立費 | C40: 114000 | D40: 114000 | E40: =C40-D40 -> 0 | F40: 設立6万+印鑑1万+飲食1.8万+菓子1.6万+衛生1万
E41: =C41-D41 -> 0 | L41: 過去の未払い分 今月支払額 | N41: 未払い累計から取り崩す場合に入力
E42: =C42-D42 -> 0
E43: =C43-D43 -> 0
E44: =C44-D44 -> 0
E45: =C45-D45 -> 0
E46: =C46-D46 -> 0
E47: =C47-D47 -> 0
E48: =C48-D48 -> 0
E49: =C49-D49 -> 0
E50: =C50-D50 -> 0
E51: =C51-D51 -> 0
E52: =C52-D52 -> 0
E53: =C53-D53 -> 0
B54: 一括経費 合計 | C54: =SUM(C34:C53) -> 114000 | D54: =SUM(D34:D53) -> 114000 | E54: =C54-D54 -> 0
B56: コスト合計（原価＋経費＋一括） | C56: =C16+C30+D54 -> 114000
G58: ■ キャッシュフロー（実際のお金の動き）
H59: 項目 | I59: 金額
H60: 営業利益 | I60: =I39 -> 0
H61: ＋ 減価償却費（現金支出なし） | I61: =C29 -> 0 | J61: 損益上の経費だが現金は出ない
H62: 営業CF | I62: =I60+I61+M37-M41 -> 0 | J62: 実際に営業で増えた現金
H64: − 設備投資（一括経費） | I64: =D54 -> 114000 | J64: 実際に出ていった現金
H65: 投資CF | I65: =-I64 -> -114000 | J65: 設備購入で減った現金
H67: 追加資金（借入・増資等） | I67: =C6
H68: 財務CF | I68: =I67
G70: ■ 口座残高
H71: 前月末 口座残高 | I71: =C5 -> 3000000
H72: ＋ 営業CF | I72: =I62 -> 0
H73: ＋ 投資CF | I73: =I65 -> -114000
H74: ＋ 財務CF | I74: =I68
H75: 期末 口座残高 | I75: =I71+I72+I73+I74 -> 2886000 | J75: 翌月に繰越
H77: 【参考】損益と現金の差
H78: 帳簿上の利益（営業利益） | I78: =I39 -> 0
H79: 実際の現金増減（CF合計） | I79: =I72+I73+I74 -> -114000
H80: 差額（減価償却＋設備投資） | I80: =I79-I78 -> -114000 | J80: ＋なら利益より現金が多い
H82: 期末口座（人件費なし） | I82: =I75 -> 2886000 | J82: 3人の給与を払わない場合
H83: 期末口座（人件費あり） | I83: =I75-M37 -> 2886000 | J83: 3人に給与を払った場合

Sheet 6月
B1: ☕ カフェ経営管理 ─ 6月 | U1: ■ 計画値（売上計画シートから自動取得）
B2: 月末口座（人件費なし） | C2: =I75 -> 939612 | E2: 今月出ていくお金 | F2: =C16+SUM(C20:C23)+SUM(C25:C28)+M36+D54+M41 -> 1946388 | H2: 今月の利益 | I2: =I39 -> -14433.833 | L2: 来月必要なお金 | M2: ='7月'!C20+'7月'!C21+'7月'!C22+'7月'!C23+'7月'!C25 -> 0 | U2: 実績の入力時に参考にしてください。差額・達成率も自動表示。
B3: ■ 資金（期首残高） | G3: ■ 売上（定期収入） | L3: ■ 人件費計算
B4: 科目 | C4: 金額 | D4: 詳細 | E4: メモ | G4: カテゴリ | H4: 金額 | I4: 詳細 | J4: メモ | L4: スタッフ名 | M4: 時給 | N4: 日数 | O4: 時間/日 | P4: 交通費/日 | Q4: 小計（給与） | R4: 小計（交通費） | U4: ■ 売上
B5: 前月繰越金 | C5: ='5月'!I75 -> 2886000 | G5: ドリンク（コーヒー） | H5: ='6月日次売上'!C34 -> 0 | Q5: =M5*N5*O5 -> 0 | R5: =P5*N5 -> 0 | U5: 項目 | V5: 計画 | W5: 実績 | X5: 差額 | Y5: 達成率
B6: 追加資金（借入等） | G6: ドリンク（紅茶・その他） | H6: ='6月日次売上'!D34 -> 0 | Q6: =M6*N6*O6 -> 0 | R6: =P6*N6 -> 0 | U6: 昼 来客数（季節調整後）/日 | V6: ='売上計画'!E38 -> 0 | W6: =IF(H26=0,"",H24/H26/2) | X6: =IF(W6="",0,W6-V6) -> 0 | Y6: =IF(OR(W6="",V6=0),0,W6/V6) -> 0
B7: 期首資金 合計 | C7: =SUM(C5:C6) -> 2886000 | G7: フード（軽食） | H7: ='6月日次売上'!E34 -> 0 | Q7: =M7*N7*O7 -> 0 | R7: =P7*N7 -> 0 | U7: 夜 来客数（季節調整後）/日 | V7: ='売上計画'!E39 -> 0 | W7: =IF(H26=0,"",H24/H26/2) | X7: =IF(W7="",0,W7-V7) -> 0 | Y7: =IF(OR(W7="",V7=0),0,W7/V7) -> 0
G8: フード（スイーツ） | H8: ='6月日次売上'!F34 -> 0 | Q8: =M8*N8*O8 -> 0 | R8: =P8*N8 -> 0 | U8: 売上合計（月間） | V8: ='売上計画'!E45 -> 0 | W8: =H20 -> 0 | X8: =W8-V8 -> 0 | Y8: =IF(V8=0,0,W8/V8) -> 0
B9: ■ 原価（売上原価） | G9: 物販（コーヒー豆・グッズ） | H9: ='6月日次売上'!G34 -> 0 | Q9: =M9*N9*O9 -> 0 | R9: =P9*N9 -> 0 | U9: 客単価 | V9: =IF((V6*'売上計画'!$C$7+V7*'売上計画'!$C$8)=0,0,V8/(V6*'売上計画'!$C$7+V7*'売上計画'!$C$8)) -> 0 | W9: =H25 -> 0 | X9: =W9-V9 -> 0 | Y9: =IF(V9=0,0,W9/V9) -> 0
B10: 科目 | C10: 金額 | D10: 詳細 | E10: メモ | G10: テイクアウト | H10: ='6月日次売上'!H34 -> 0 | Q10: =M10*N10*O10 -> 0 | R10: =P10*N10 -> 0
B11: コーヒー豆・茶葉 | C11: =SUMIFS('freee実績'!$E:$E,'freee実績'!$B:$B,"2026-06",'freee実績'!$C:$C,"仕入高",'freee実績'!$D:$D,"コーヒー豆・茶葉") -> 0 | G11: 売上 合計 | H11: =SUM(H5:H10) -> 0 | Q11: =M11*N11*O11 -> 0 | R11: =P11*N11 -> 0 | U11: ■ 原価・粗利
B12: 牛乳・シロップ等 | C12: =SUMIFS('freee実績'!$E:$E,'freee実績'!$B:$B,"2026-06",'freee実績'!$C:$C,"仕入高",'freee実績'!$D:$D,"牛乳・シロップ等") -> 0 | Q12: =M12*N12*O12 -> 0 | R12: =P12*N12 -> 0 | U12: 項目 | V12: 計画 | W12: 実績 | X12: 差額 | Y12: 原価率
B13: フード材料費 | C13: =SUMIFS('freee実績'!$E:$E,'freee実績'!$B:$B,"2026-06",'freee実績'!$C:$C,"仕入高",'freee実績'!$D:$D,"フード材料費") -> 0 | G13: ■ その他収入（不定期） | L13: アルバイト給与 合計 | Q13: =SUM(Q5:Q12) -> 0 | R13: =SUM(R5:R12) -> 0 | U13: 原価合計 | V13: ='売上計画'!E46 -> 0 | W13: =C16 -> 0 | X13: =W13-V13 -> 0 | Y13: =IF(W8=0,0,W13/W8) -> 0
B14: 包装資材・消耗品 | C14: =SUMIFS('freee実績'!$E:$E,'freee実績'!$B:$B,"2026-06",'freee実績'!$C:$C,"仕入高",'freee実績'!$D:$D,"包装資材・消耗品") -> 0 | G14: カテゴリ | H14: 金額 | I14: 詳細 | J14: メモ | U14: 粗利益 | V14: ='売上計画'!E47 -> 0 | W14: =H20-C16 -> 0 | X14: =W14-V14 -> 0 | Y14: =IF(W8=0,0,W14/W8) -> 0
B15: その他原価 | C15: =SUMIFS('freee実績'!$E:$E,'freee実績'!$B:$B,"2026-06",'freee実績'!$C:$C,"仕入高",'freee実績'!$D:$D,"その他原価") -> 0 | G15: イベント・貸切 | H15: ='6月日次売上'!I34 -> 0 | L15: ■ 固定人件費（役員報酬・社員給与等）
B16: 原価 合計 | C16: =SUM(C11:C15) -> 0 | G16: その他収入② | L16: 項目 | M16: 月額 | R16: 備考 | U16: ■ 経費
G17: その他収入 | L17: 役員報酬 | U17: 項目 | V17: 計画 | W17: 実績 | X17: 差額
B18: ■ 経費（販管費） | G18: その他収入 合計 | H18: =SUM(H15:H17) -> 0 | L18: 社員給与 | U18: 人件費（バイト+固定） | V18: ='売上計画'!E54 -> 0 | W18: =C24 -> 0 | X18: =W18-V18 -> 0
B19: 科目 | C19: 金額 | D19: 詳細 | E19: メモ | L19: 社会保険料（会社負担） | U19: 固定費（家賃+光熱+通信+保険） | V19: ='売上計画'!E57 -> 0 | W19: =C20+C21+C22+C23 -> 0 | X19: =W19-V19 -> 0
B20: 家賃 | C20: =SUMIFS('freee実績'!$E:$E,'freee実績'!$B:$B,"2026-06",'freee実績'!$C:$C,"地代家賃") -> 0 | D20: 固定費 | G20: 売上合計（定期＋不定期） | H20: =H11+H18 -> 0 | L20: その他人件費 | U20: 消耗品 | V20: ='売上計画'!E58 -> 0 | W20: =C25 -> 0 | X20: =W20-V20 -> 0
B21: 水道光熱費 | C21: =SUMIFS('freee実績'!$E:$E,'freee実績'!$B:$B,"2026-06",'freee実績'!$C:$C,"水道光熱費") -> 0 | D21: 固定費 | L21: 固定人件費 合計 | M21: =SUM(M17:M20) -> 0 | U21: 経費合計 | V21: ='売上計画'!E59 -> 0 | W21: =C30 -> 14433.833 | X21: =W21-V21 -> 14433.833
B22: 通信費 | C22: =SUMIFS('freee実績'!$E:$E,'freee実績'!$B:$B,"2026-06",'freee実績'!$C:$C,"通信費") -> 0 | D22: 固定費 | G22: ■ 売上KPI
B23: 保険料 | C23: =SUMIFS('freee実績'!$E:$E,'freee実績'!$B:$B,"2026-06",'freee実績'!$C:$C,"保険料") -> 0 | D23: 固定費 | G23: 指標 | H23: 数値 | J23: 算出方法 | L23: 人件費 総合計 | M23: =Q13+R13+M21 -> 0 | U23: ■ 営業利益
B24: 人件費（給与・社保） | C24: =M23 -> 0 | D24: 変動費 | G24: 来客数（人） | H24: ='6月日次売上'!J34 -> 0 | U24: 項目 | V24: 計画 | W24: 実績 | X24: 差額 | Y24: 達成率
B25: 消耗品費 | C25: =SUMIFS('freee実績'!$E:$E,'freee実績'!$B:$B,"2026-06",'freee実績'!$C:$C,"消耗品費") -> 0 | D25: 変動費 | G25: 客単価 | H25: =IF(H24=0,0,H20/H24) -> 0 | J25: 売上÷来客数 | L25: ↑ この金額を左側「人件費（給与・社保）」に転記 | U25: 営業利益 | V25: ='売上計画'!E61 | W25: =I39 -> -14433.833 | X25: =W25-V25 -> -14433.833 | Y25: =IF(V25=0,0,W25/V25) -> 0
B26: 広告宣伝費 | C26: =SUMIFS('freee実績'!$E:$E,'freee実績'!$B:$B,"2026-06",'freee実績'!$C:$C,"広告宣伝費") -> 0 | D26: 変動費 | G26: 営業日数 | H26: 0 | U26: 営業利益率 | V26: ='売上計画'!E62 -> 0 | W26: =IF(W8=0,0,W25/W8) -> 0 | X26: =W26-V26 -> 0
B27: 修繕費 | C27: =SUMIFS('freee実績'!$E:$E,'freee実績'!$B:$B,"2026-06",'freee実績'!$C:$C,"修繕費") -> 0 | D27: 変動費 | G27: 日商（1日平均売上） | H27: =IF(H26=0,0,H20/H26) -> 0 | J27: 売上÷営業日数 | L27: ■ 人件費KPI
B28: その他経費 | C28: =SUMIFS('freee実績'!$E:$E,'freee実績'!$B:$B,"2026-06",'freee実績'!$C:$C,"雑費") -> 0 | D28: 変動費 | G28: 原価率 | H28: =IF(H20=0,0,C16/H20) -> 0 | J28: 原価÷売上 | L28: 指標 | M28: 数値 | R28: 算出方法
B29: 減価償却費 | C29: ='固定資産台帳'!N26 -> 14433.833 | D29: 帳簿上のみ | L29: 人件費率 | M29: =IF(H20=0,0,M23/H20) -> 0 | R29: 人件費÷売上
B30: 経費 合計 | C30: =SUM(C20:C29) -> 14433.833 | L30: 人時売上高 | M30: =IF((SUM(N5:N12)*SUM(O5:O12))=0,0,H20/(SUM(N5:N12)*SUM(O5:O12))) -> 0 | R30: 売上÷総労働時間
B32: ■ 一括経費（設備投資等） | G32: ■ 月次損益計算 | L32: ■ オーナー人件費 未払い管理
B33: 科目 | C33: 予算 | D33: 実績 | E33: 差額（残） | F33: メモ | H33: 項目 | I33: 金額 | L33: 帳簿上は計上、実際の支払いは利益が出てから
B34: 敷金（5ヶ月分） | D34: 500000 | E34: =C34-D34 -> -500000 | F34: 北棟 | H34: 売上高 | I34: =H20 -> 0 | L34: 今月の人件費 支払い？ | M34: 未払い | N34: ← 「支払い」か「未払い」を入力
B35: 礼金（2ヶ月分） | D35: 200000 | E35: =C35-D35 -> -200000 | F35: 北棟 | H35: 原価合計 | I35: =C16 -> 0 | L35: 人件費（帳簿計上額） | M35: =M23 -> 0 | N35: P/Lに反映
B36: 仲介手数料 | D36: 100000 | E36: =C36-D36 -> -100000 | F36: 1ヶ月分 | H36: 粗利益 | I36: =I34-I35 -> 0 | L36: 実際の支払い額 | M36: =IF(M34="支払い",M35,0) -> 0 | N36: 口座から出るお金
B37: エスプレッソマシン① | C37: 250000 | D37: 250000 | E37: =C37-D37 -> 0 | F37: La Marzocco Linea Classic S-2（中古） | H37: 粗利率 | I37: =IF(I34=0,0,I36/I34) -> 0 | L37: 今月の未払い額 | M37: =M35-M36 -> 0 | N37: 帳簿上は経費だが現金は出ない
B38: 保険（火災・施設賠償・PL） | D38: 45000 | E38: =C38-D38 -> -45000 | F38: 3種 各15,000円/年 | H38: 経費合計 | I38: =C30 -> 14433.833 | L38: 前月までの未払い累計 | M38: ='5月'!M39 -> 0
B39: 製氷機 | D39: 82500 | E39: =C39-D39 -> -82500 | F39: ダイワ DRI-25LME1（中古） | H39: 営業利益 | I39: =I36-I38 -> -14433.833 | L39: 未払い累計（今月末時点） | M39: =M38+M37 -> 0 | N39: 将来支払う必要のある額
B41: コーヒーグラインダー | C41: 68888 | D41: 68888 | E41: =C41-D41 -> 0 | F41: Mazzer Super Jolly（中古） | L41: 過去の未払い分 今月支払額 | N41: 未払い累計から取り崩す場合に入力
B42: 内装工事着工 | D42: 700000
E53: =C53-D53 -> 0
B54: 一括経費 合計 | C54: =SUM(C34:C53) -> 318888 | D54: =SUM(D34:D53) -> 1946388 | E54: =C54-D54 -> -1627500
B56: コスト合計（原価＋経費＋一括） | C56: =C16+C30+D54 -> 1960821.8
G58: ■ キャッシュフロー（実際のお金の動き）
H59: 項目 | I59: 金額
H60: 営業利益 | I60: =I39 -> -14433.833
H61: ＋ 減価償却費（現金支出なし） | I61: =C29 -> 14433.833 | J61: 損益上の経費だが現金は出ない
H62: 営業CF | I62: =I60+I61+M37-M41 -> 0 | J62: 実際に営業で増えた現金
H64: − 設備投資（一括経費） | I64: =D54 -> 1946388 | J64: 実際に出ていった現金
H65: 投資CF | I65: =-I64 -> -1946388 | J65: 設備購入で減った現金
H67: 追加資金（借入・増資等） | I67: =C6
H68: 財務CF | I68: =I67
G70: ■ 口座残高
H71: 前月末 口座残高 | I71: =C5 -> 2886000
H72: ＋ 営業CF | I72: =I62 -> 0
H73: ＋ 投資CF | I73: =I65 -> -1946388
H74: ＋ 財務CF | I74: =I68
H75: 期末 口座残高 | I75: =I71+I72+I73+I74 -> 939612 | J75: 翌月に繰越
H77: 【参考】損益と現金の差
H78: 帳簿上の利益（営業利益） | I78: =I39 -> -14433.833
H79: 実際の現金増減（CF合計） | I79: =I72+I73+I74 -> -1946388
H80: 差額（減価償却＋設備投資） | I80: =I79-I78 -> -1931954.2 | J80: ＋なら利益より現金が多い
H82: 期末口座（人件費なし） | I82: =I75 -> 939612 | J82: 3人の給与を払わない場合
H83: 期末口座（人件費あり） | I83: =I75-M37 -> 939612 | J83: 3人に給与を払った場合

Sheet 7月
B1: ☕ カフェ経営管理 ─ 7月 | U1: ■ 計画値（売上計画シートから自動取得）
B2: 月末口座（人件費なし） | C2: =I75 -> 3983694 | E2: 今月出ていくお金 | F2: =C16+SUM(C20:C23)+SUM(C25:C28)+M36+D54+M41 -> 455918 | H2: 今月の利益 | I2: =I39 -> -14433.833 | L2: 来月必要なお金 | M2: ='8月'!C20+'8月'!C21+'8月'!C22+'8月'!C23+'8月'!C25 -> 0 | U2: 実績の入力時に参考にしてください。差額・達成率も自動表示。
B3: ■ 資金（期首残高） | G3: ■ 売上（定期収入） | L3: ■ 人件費計算
B4: 科目 | C4: 金額 | D4: 詳細 | E4: メモ | G4: カテゴリ | H4: 金額 | I4: 詳細 | J4: メモ | L4: スタッフ名 | M4: 時給 | N4: 日数 | O4: 時間/日 | P4: 交通費/日 | Q4: 小計（給与） | R4: 小計（交通費） | U4: ■ 売上
B5: 前月繰越金 | C5: ='6月'!I75 -> 939612 | G5: ドリンク（コーヒー） | H5: ='7月日次売上'!C35 -> 0 | Q5: =M5*N5*O5 -> 0 | R5: =P5*N5 -> 0 | U5: 項目 | V5: 計画 | W5: 実績 | X5: 差額 | Y5: 達成率
B6: 追加資金（借入等） | C6: 3500000 | E6: 日本政策金融公庫（300万） | G6: ドリンク（紅茶・その他） | H6: ='7月日次売上'!D35 -> 0 | Q6: =M6*N6*O6 -> 0 | R6: =P6*N6 -> 0 | U6: 昼 来客数（季節調整後）/日 | V6: ='売上計画'!F38 -> 0 | W6: =IF(H26=0,"",H24/H26/2) | X6: =IF(W6="",0,W6-V6) -> 0 | Y6: =IF(OR(W6="",V6=0),0,W6/V6) -> 0
B7: 期首資金 合計 | C7: =SUM(C5:C6) -> 4439612 | G7: フード（軽食） | H7: ='7月日次売上'!E35 -> 0 | Q7: =M7*N7*O7 -> 0 | R7: =P7*N7 -> 0 | U7: 夜 来客数（季節調整後）/日 | V7: ='売上計画'!F39 -> 0 | W7: =IF(H26=0,"",H24/H26/2) | X7: =IF(W7="",0,W7-V7) -> 0 | Y7: =IF(OR(W7="",V7=0),0,W7/V7) -> 0
G8: フード（スイーツ） | H8: ='7月日次売上'!F35 -> 0 | Q8: =M8*N8*O8 -> 0 | R8: =P8*N8 -> 0 | U8: 売上合計（月間） | V8: ='売上計画'!F45 -> 0 | W8: =H20 -> 0 | X8: =W8-V8 -> 0 | Y8: =IF(V8=0,0,W8/V8) -> 0
B9: ■ 原価（売上原価） | G9: 物販（コーヒー豆・グッズ） | H9: ='7月日次売上'!G35 -> 0 | Q9: =M9*N9*O9 -> 0 | R9: =P9*N9 -> 0 | U9: 客単価 | V9: =IF((V6*'売上計画'!$C$7+V7*'売上計画'!$C$8)=0,0,V8/(V6*'売上計画'!$C$7+V7*'売上計画'!$C$8)) -> 0 | W9: =H25 -> 0 | X9: =W9-V9 -> 0 | Y9: =IF(V9=0,0,W9/V9) -> 0
B10: 科目 | C10: 金額 | D10: 詳細 | E10: メモ | G10: テイクアウト | H10: ='7月日次売上'!H35 -> 0 | Q10: =M10*N10*O10 -> 0 | R10: =P10*N10 -> 0
B11: コーヒー豆・茶葉 | C11: =SUMIFS('freee実績'!$E:$E,'freee実績'!$B:$B,"2026-07",'freee実績'!$C:$C,"仕入高",'freee実績'!$D:$D,"コーヒー豆・茶葉") -> 0 | G11: 売上 合計 | H11: =SUM(H5:H10) -> 0 | Q11: =M11*N11*O11 -> 0 | R11: =P11*N11 -> 0 | U11: ■ 原価・粗利
B12: 牛乳・シロップ等 | C12: =SUMIFS('freee実績'!$E:$E,'freee実績'!$B:$B,"2026-07",'freee実績'!$C:$C,"仕入高",'freee実績'!$D:$D,"牛乳・シロップ等") -> 0 | Q12: =M12*N12*O12 -> 0 | R12: =P12*N12 -> 0 | U12: 項目 | V12: 計画 | W12: 実績 | X12: 差額 | Y12: 原価率
B13: フード材料費 | C13: =SUMIFS('freee実績'!$E:$E,'freee実績'!$B:$B,"2026-07",'freee実績'!$C:$C,"仕入高",'freee実績'!$D:$D,"フード材料費") -> 0 | G13: ■ その他収入（不定期） | L13: アルバイト給与 合計 | Q13: =SUM(Q5:Q12) -> 0 | R13: =SUM(R5:R12) -> 0 | U13: 原価合計 | V13: ='売上計画'!F46 -> 0 | W13: =C16 -> 0 | X13: =W13-V13 -> 0 | Y13: =IF(W8=0,0,W13/W8) -> 0
B14: 包装資材・消耗品 | C14: =SUMIFS('freee実績'!$E:$E,'freee実績'!$B:$B,"2026-07",'freee実績'!$C:$C,"仕入高",'freee実績'!$D:$D,"包装資材・消耗品") -> 0 | G14: カテゴリ | H14: 金額 | I14: 詳細 | J14: メモ | U14: 粗利益 | V14: ='売上計画'!F47 -> 0 | W14: =H20-C16 -> 0 | X14: =W14-V14 -> 0 | Y14: =IF(W8=0,0,W14/W8) -> 0
B15: その他原価 | C15: =SUMIFS('freee実績'!$E:$E,'freee実績'!$B:$B,"2026-07",'freee実績'!$C:$C,"仕入高",'freee実績'!$D:$D,"その他原価") -> 0 | G15: イベント・貸切 | H15: ='7月日次売上'!I35 -> 0 | L15: ■ 固定人件費（役員報酬・社員給与等）
B16: 原価 合計 | C16: =SUM(C11:C15) -> 0 | G16: その他収入② | L16: 項目 | M16: 月額 | R16: 備考 | U16: ■ 経費
G17: その他収入 | L17: 役員報酬 | U17: 項目 | V17: 計画 | W17: 実績 | X17: 差額
B18: ■ 経費（販管費） | G18: その他収入 合計 | H18: =SUM(H15:H17) -> 0 | L18: 社員給与 | U18: 人件費（バイト+固定） | V18: ='売上計画'!F54 -> 0 | W18: =C24 | X18: =W18-V18 -> 0
B19: 科目 | C19: 金額 | D19: 詳細 | E19: メモ | L19: 社会保険料（会社負担） | U19: 固定費（家賃+光熱+通信+保険） | V19: ='売上計画'!F57 -> 0 | W19: =C20+C21+C22+C23 -> 0 | X19: =W19-V19 -> 0
B20: 家賃 | C20: =SUMIFS('freee実績'!$E:$E,'freee実績'!$B:$B,"2026-07",'freee実績'!$C:$C,"地代家賃") -> 0 | D20: 固定費 | G20: 売上合計（定期＋不定期） | H20: =H11+H18 -> 0 | L20: その他人件費 | U20: 消耗品 | V20: ='売上計画'!F58 -> 0 | W20: =C25 -> 0 | X20: =W20-V20 -> 0
B21: 水道光熱費 | C21: =SUMIFS('freee実績'!$E:$E,'freee実績'!$B:$B,"2026-07",'freee実績'!$C:$C,"水道光熱費") -> 0 | D21: 固定費 | L21: 固定人件費 合計 | M21: =SUM(M17:M20) -> 0 | U21: 経費合計 | V21: ='売上計画'!F59 -> 0 | W21: =C30 -> 14433.833 | X21: =W21-V21 -> 14433.833
B22: 通信費 | C22: =SUMIFS('freee実績'!$E:$E,'freee実績'!$B:$B,"2026-07",'freee実績'!$C:$C,"通信費") -> 0 | D22: 固定費 | G22: ■ 売上KPI
B23: 保険料 | C23: =SUMIFS('freee実績'!$E:$E,'freee実績'!$B:$B,"2026-07",'freee実績'!$C:$C,"保険料") -> 0 | D23: 固定費 | G23: 指標 | H23: 数値 | J23: 算出方法 | L23: 人件費 総合計 | M23: =Q13+R13+M21 -> 0 | U23: ■ 営業利益
B24: 人件費（給与・社保） | D24: 変動費 | G24: 来客数（人） | H24: ='7月日次売上'!J35 -> 0 | U24: 項目 | V24: 計画 | W24: 実績 | X24: 差額 | Y24: 達成率
B25: 消耗品費 | C25: =SUMIFS('freee実績'!$E:$E,'freee実績'!$B:$B,"2026-07",'freee実績'!$C:$C,"消耗品費") -> 0 | D25: 変動費 | G25: 客単価 | H25: =IF(H24=0,0,H20/H24) -> 0 | J25: 売上÷来客数 | L25: ↑ この金額を左側「人件費（給与・社保）」に転記 | U25: 営業利益 | V25: ='売上計画'!F61 | W25: =I39 -> -14433.833 | X25: =W25-V25 -> -14433.833 | Y25: =IF(V25=0,0,W25/V25) -> 0
B26: 広告宣伝費 | C26: =SUMIFS('freee実績'!$E:$E,'freee実績'!$B:$B,"2026-07",'freee実績'!$C:$C,"広告宣伝費") -> 0 | D26: 変動費 | G26: 営業日数 | H26: 0 | U26: 営業利益率 | V26: ='売上計画'!F62 -> 0 | W26: =IF(W8=0,0,W25/W8) -> 0 | X26: =W26-V26 -> 0
B27: 修繕費 | C27: =SUMIFS('freee実績'!$E:$E,'freee実績'!$B:$B,"2026-07",'freee実績'!$C:$C,"修繕費") -> 0 | D27: 変動費 | G27: 日商（1日平均売上） | H27: =IF(H26=0,0,H20/H26) -> 0 | J27: 売上÷営業日数 | L27: ■ 人件費KPI
B28: その他経費 | C28: =SUMIFS('freee実績'!$E:$E,'freee実績'!$B:$B,"2026-07",'freee実績'!$C:$C,"雑費") -> 0 | D28: 変動費 | G28: 原価率 | H28: =IF(H20=0,0,C16/H20) -> 0 | J28: 原価÷売上 | L28: 指標 | M28: 数値 | R28: 算出方法
B29: 減価償却費 | C29: ='固定資産台帳'!O26 -> 14433.833 | D29: 帳簿上のみ | L29: 人件費率 | M29: =IF(H20=0,0,M23/H20) -> 0 | R29: 人件費÷売上
B30: 経費 合計 | C30: =SUM(C20:C29) -> 14433.833 | L30: 人時売上高 | M30: =IF((SUM(N5:N12)*SUM(O5:O12))=0,0,H20/(SUM(N5:N12)*SUM(O5:O12))) -> 0 | R30: 売上÷総労働時間
B32: ■ 一括経費（設備投資等） | G32: ■ 月次損益計算 | L32: ■ オーナー人件費 未払い管理
B33: 科目 | C33: 予算 | D33: 実績 | E33: 差額（残） | F33: メモ | H33: 項目 | I33: 金額 | L33: 帳簿上は計上、実際の支払いは利益が出てから
B34: トイレ | C34: 63900 | D34: 63900 | H34: 売上高 | I34: =H20 -> 0 | L34: 今月の人件費 支払い？ | M34: 未払い | N34: ← 「支払い」か「未払い」を入力
B35: 業務用冷蔵庫 | C35: 21890 | D35: 21890 | E35: =C35-D35 -> 0 | F35: セカスト | H35: 原価合計 | I35: =C16 -> 0 | L35: 人件費（帳簿計上額） | M35: =M23 -> 0 | N35: P/Lに反映
B36: 冷凍ストッカー | D36: 15000 | F36: セカスト | H36: 粗利益 | I36: =I34-I35 -> 0 | L36: 実際の支払い額 | M36: =IF(M34="支払い",M35,0) -> 0 | N36: 口座から出るお金
H37: 粗利率 | I37: =IF(I34=0,0,I36/I34) -> 0 | L37: 今月の未払い額 | M37: =M35-M36 -> 0 | N37: 帳簿上は経費だが現金は出ない
H38: 経費合計 | I38: =C30 -> 14433.833 | L38: 前月までの未払い累計 | M38: ='6月'!M39 -> 0
H39: 営業利益 | I39: =I36-I38 -> -14433.833 | L39: 未払い累計（今月末時点） | M39: =M38+M37 -> 0 | N39: 将来支払う必要のある額
B41: 浄水器 | D41: 45628 | E41: =C41-D41 -> -45628 | F41: EVERPURE QL3+ESO7 | L41: 過去の未払い分 今月支払額 | N41: 未払い累計から取り崩す場合に入力
B42: 2槽シンク＋手洗いシンク | D42: 50000 | E42: =C42-D42 -> -50000 | F42: 保健所要件
B46: 家具一式（テーブル・椅子・ソファ・照明等） | D46: 204500 | E46: =C46-D46 -> -204500
B49: デジタルスケール | D49: 5000
B50: 釣銭＋消耗品 | D50: 50000 | E50: =C50-D50 -> -50000 | F50: 釣銭3万+洗剤・ペーパー等2万
E51: =C51-D51 -> 0
E52: =C52-D52 -> 0
E53: =C53-D53 -> 0
B54: 一括経費 合計 | C54: =SUM(C34:C53) -> 85790 | D54: =SUM(D34:D53) -> 455918 | E54: =C54-D54 -> -370128
B56: コスト合計（原価＋経費＋一括） | C56: =C16+C30+D54 -> 470351.83
G58: ■ キャッシュフロー（実際のお金の動き）
H59: 項目 | I59: 金額
H60: 営業利益 | I60: =I39 -> -14433.833
H61: ＋ 減価償却費（現金支出なし） | I61: =C29 -> 14433.833 | J61: 損益上の経費だが現金は出ない
H62: 営業CF | I62: =I60+I61+M37-M41 -> 0 | J62: 実際に営業で増えた現金
H64: − 設備投資（一括経費） | I64: =D54 -> 455918 | J64: 実際に出ていった現金
H65: 投資CF | I65: =-I64 -> -455918 | J65: 設備購入で減った現金
H67: 追加資金（借入・増資等） | I67: =C6 -> 3500000
H68: 財務CF | I68: =I67 -> 3500000
G70: ■ 口座残高
H71: 前月末 口座残高 | I71: =C5 -> 939612
H72: ＋ 営業CF | I72: =I62 -> 0
H73: ＋ 投資CF | I73: =I65 -> -455918
H74: ＋ 財務CF | I74: =I68 -> 3500000
H75: 期末 口座残高 | I75: =I71+I72+I73+I74 -> 3983694 | J75: 翌月に繰越
H77: 【参考】損益と現金の差
H78: 帳簿上の利益（営業利益） | I78: =I39 -> -14433.833
H79: 実際の現金増減（CF合計） | I79: =I72+I73+I74 -> 3044082
H80: 差額（減価償却＋設備投資） | I80: =I79-I78 -> 3058515.8 | J80: ＋なら利益より現金が多い
H82: 期末口座（人件費なし） | I82: =I75 -> 3983694 | J82: 3人の給与を払わない場合
H83: 期末口座（人件費あり） | I83: =I75-M37 -> 3983694 | J83: 3人に給与を払った場合

Sheet 8月
B1: ☕ カフェ経営管理 ─ 8月 | U1: ■ 計画値（売上計画シートから自動取得）
B2: 月末口座（人件費なし） | C2: =I75 -> 956398.6 | E2: 今月出ていくお金 | F2: =C16+SUM(C20:C23)+SUM(C25:C28)+M36+D54+M41 -> 2800000 | H2: 今月の利益 | I2: =I39 -> -241729.23 | L2: 来月必要なお金 | M2: ='9月'!C20+'9月'!C21+'9月'!C22+'9月'!C23+'9月'!C25 -> 0 | U2: 実績の入力時に参考にしてください。差額・達成率も自動表示。
B3: ■ 資金（期首残高） | G3: ■ 売上（定期収入） | L3: ■ 人件費計算
B4: 科目 | C4: 金額 | D4: 詳細 | E4: メモ | G4: カテゴリ | H4: 金額 | I4: 詳細 | J4: メモ | L4: スタッフ名 | M4: 時給 | N4: 日数 | O4: 時間/日 | P4: 交通費/日 | Q4: 小計（給与） | R4: 小計（交通費） | U4: ■ 売上
B5: 前月繰越金 | C5: ='7月'!I75 -> 3983694 | G5: ドリンク（コーヒー） | H5: ='8月日次売上'!C35 -> 0 | Q5: =M5*N5*O5 -> 0 | R5: =P5*N5 -> 0 | U5: 項目 | V5: 計画 | W5: 実績 | X5: 差額 | Y5: 達成率
B6: 追加資金 | E6: 融資 | G6: ドリンク（紅茶・その他） | H6: ='8月日次売上'!D35 -> 0 | Q6: =M6*N6*O6 -> 0 | R6: =P6*N6 -> 0 | U6: 昼 来客数（季節調整後）/日 | V6: ='売上計画'!G38 -> 10 | W6: =IF(H26=0,"",H24/H26/2) -> 0 | X6: =IF(W6="",0,W6-V6) -> -10 | Y6: =IF(OR(W6="",V6=0),0,W6/V6) -> 0
B7: 期首資金 合計 | C7: =SUM(C5:C6) -> 3983694 | G7: フード（軽食） | H7: ='8月日次売上'!E35 -> 0 | Q7: =M7*N7*O7 -> 0 | R7: =P7*N7 -> 0 | U7: 夜 来客数（季節調整後）/日 | V7: ='売上計画'!G39 -> 7 | W7: =IF(H26=0,"",H24/H26/2) -> 0 | X7: =IF(W7="",0,W7-V7) -> -7 | Y7: =IF(OR(W7="",V7=0),0,W7/V7) -> 0
G8: フード（スイーツ） | H8: ='8月日次売上'!F35 -> 0 | Q8: =M8*N8*O8 -> 0 | R8: =P8*N8 -> 0 | U8: 売上合計（月間） | V8: ='売上計画'!G45 -> 654100 | W8: =H20 -> 0 | X8: =W8-V8 -> -654100 | Y8: =IF(V8=0,0,W8/V8) -> 0
B9: ■ 原価（売上原価） | G9: 物販（コーヒー豆・グッズ） | H9: ='8月日次売上'!G35 -> 0 | Q9: =M9*N9*O9 -> 0 | R9: =P9*N9 -> 0 | U9: 客単価 | V9: =IF((V6*'売上計画'!$C$7+V7*'売上計画'!$C$8)=0,0,V8/(V6*'売上計画'!$C$7+V7*'売上計画'!$C$8)) -> 1282.549 | W9: =H25 -> 0 | X9: =W9-V9 -> -1282.549 | Y9: =IF(V9=0,0,W9/V9) -> 0
B10: 科目 | C10: 金額 | D10: 詳細 | E10: メモ | G10: テイクアウト | H10: ='8月日次売上'!H35 -> 0 | Q10: =M10*N10*O10 -> 0 | R10: =P10*N10 -> 0
B11: コーヒー豆・茶葉 | C11: =SUMIFS('freee実績'!$E:$E,'freee実績'!$B:$B,"2026-08",'freee実績'!$C:$C,"仕入高",'freee実績'!$D:$D,"コーヒー豆・茶葉") -> 0 | G11: 売上 合計 | H11: =SUM(H5:H10) -> 0 | Q11: =M11*N11*O11 -> 0 | R11: =P11*N11 -> 0 | U11: ■ 原価・粗利
B12: 牛乳・シロップ等 | C12: =SUMIFS('freee実績'!$E:$E,'freee実績'!$B:$B,"2026-08",'freee実績'!$C:$C,"仕入高",'freee実績'!$D:$D,"牛乳・シロップ等") -> 0 | Q12: =M12*N12*O12 -> 0 | R12: =P12*N12 -> 0 | U12: 項目 | V12: 計画 | W12: 実績 | X12: 差額 | Y12: 原価率
B13: フード材料費 | C13: =SUMIFS('freee実績'!$E:$E,'freee実績'!$B:$B,"2026-08",'freee実績'!$C:$C,"仕入高",'freee実績'!$D:$D,"フード材料費") -> 0 | G13: ■ その他収入（不定期） | L13: アルバイト給与 合計 | Q13: =SUM(Q5:Q12) -> 0 | R13: =SUM(R5:R12) -> 0 | U13: 原価合計 | V13: ='売上計画'!G46 -> 196230 | W13: =C16 -> 0 | X13: =W13-V13 -> -196230 | Y13: =IF(W8=0,0,W13/W8) -> 0
B14: 包装資材・消耗品 | C14: =SUMIFS('freee実績'!$E:$E,'freee実績'!$B:$B,"2026-08",'freee実績'!$C:$C,"仕入高",'freee実績'!$D:$D,"包装資材・消耗品") -> 0 | G14: カテゴリ | H14: 金額 | I14: 詳細 | J14: メモ | U14: 粗利益 | V14: ='売上計画'!G47 -> 457870 | W14: =H20-C16 -> 0 | X14: =W14-V14 -> -457870 | Y14: =IF(W8=0,0,W14/W8) -> 0
B15: その他原価 | C15: =SUMIFS('freee実績'!$E:$E,'freee実績'!$B:$B,"2026-08",'freee実績'!$C:$C,"仕入高",'freee実績'!$D:$D,"その他原価") -> 0 | G15: イベント・貸切 | H15: ='8月日次売上'!I35 -> 0 | L15: ■ 固定人件費（役員報酬・社員給与等）
B16: 原価 合計 | C16: =SUM(C11:C15) -> 0 | G16: その他収入② | L16: 項目 | M16: 月額 | R16: 備考 | U16: ■ 経費
G17: その他収入 | L17: 役員報酬 | U17: 項目 | V17: 計画 | W17: 実績 | X17: 差額
B18: ■ 経費（販管費） | G18: その他収入 合計 | H18: =SUM(H15:H17) -> 0 | L18: 社員給与 | U18: 人件費（バイト+固定） | V18: ='売上計画'!G54 -> 46.5 | W18: =C24 -> 227295.4 | X18: =W18-V18 -> 227248.9
B19: 科目 | C19: 金額 | D19: 詳細 | E19: メモ | L19: 社会保険料（会社負担） | U19: 固定費（家賃+光熱+通信+保険） | V19: ='売上計画'!G57 -> 644 | W19: =C20+C21+C22+C23 -> 0 | X19: =W19-V19 -> -644
B20: 家賃 | C20: =SUMIFS('freee実績'!$E:$E,'freee実績'!$B:$B,"2026-08",'freee実績'!$C:$C,"地代家賃") -> 0 | D20: 固定費 | G20: 売上合計（定期＋不定期） | H20: =H11+H18 -> 0 | L20: その他人件費 | U20: 消耗品 | V20: ='売上計画'!G58 -> 0 | W20: =C25 -> 0 | X20: =W20-V20 -> 0
B21: 水道光熱費 | C21: =SUMIFS('freee実績'!$E:$E,'freee実績'!$B:$B,"2026-08",'freee実績'!$C:$C,"水道光熱費") -> 0 | D21: 固定費 | L21: 固定人件費 合計 | M21: =SUM(M17:M20) -> 0 | U21: 経費合計 | V21: ='売上計画'!G59 -> 0 | W21: =C30 -> 241729.23 | X21: =W21-V21 -> 241729.23
B22: 通信費 | C22: =SUMIFS('freee実績'!$E:$E,'freee実績'!$B:$B,"2026-08",'freee実績'!$C:$C,"通信費") -> 0 | D22: 固定費 | G22: ■ 売上KPI
B23: 保険料 | C23: =SUMIFS('freee実績'!$E:$E,'freee実績'!$B:$B,"2026-08",'freee実績'!$C:$C,"保険料") -> 0 | D23: 固定費 | G23: 指標 | H23: 数値 | J23: 算出方法 | L23: 人件費 総合計 | M23: =Q13+R13+M21 -> 0 | U23: ■ 営業利益
B24: 人件費（給与・社保） | C24: ='役員報酬・社保'!C17+'役員報酬・社保'!E17+'役員報酬・社保'!C71+'役員報酬・社保'!E71+86400 -> 227295.4 | D24: 変動費 | G24: 来客数（人） | H24: ='8月日次売上'!J35 -> 0 | U24: 項目 | V24: 計画 | W24: 実績 | X24: 差額 | Y24: 達成率
B25: 消耗品費 | C25: =SUMIFS('freee実績'!$E:$E,'freee実績'!$B:$B,"2026-08",'freee実績'!$C:$C,"消耗品費") -> 0 | D25: 変動費 | G25: 客単価 | H25: =IF(H24=0,0,H20/H24) -> 0 | J25: 売上÷来客数 | L25: ↑ この金額を左側「人件費（給与・社保）」に転記 | U25: 営業利益 | V25: ='売上計画'!G61 | W25: =I39 -> -241729.23 | X25: =W25-V25 -> -241729.23 | Y25: =IF(V25=0,0,W25/V25) -> 0
B26: 広告宣伝費 | C26: =SUMIFS('freee実績'!$E:$E,'freee実績'!$B:$B,"2026-08",'freee実績'!$C:$C,"広告宣伝費") -> 0 | D26: 変動費 | G26: 営業日数 | H26: 31 | U26: 営業利益率 | V26: ='売上計画'!G62 -> 337870 | W26: =IF(W8=0,0,W25/W8) -> 0 | X26: =W26-V26 -> -337870
B27: 修繕費 | C27: =SUMIFS('freee実績'!$E:$E,'freee実績'!$B:$B,"2026-08",'freee実績'!$C:$C,"修繕費") -> 0 | D27: 変動費 | G27: 日商（1日平均売上） | H27: =IF(H26=0,0,H20/H26) -> 0 | J27: 売上÷営業日数 | L27: ■ 人件費KPI
B28: その他経費 | C28: =SUMIFS('freee実績'!$E:$E,'freee実績'!$B:$B,"2026-08",'freee実績'!$C:$C,"雑費") -> 0 | D28: 変動費 | G28: 原価率 | H28: =IF(H20=0,0,C16/H20) -> 0 | J28: 原価÷売上 | L28: 指標 | M28: 数値 | R28: 算出方法
B29: 減価償却費 | C29: ='固定資産台帳'!P26 -> 14433.833 | D29: 帳簿上のみ | L29: 人件費率 | M29: =IF(H20=0,0,M23/H20) -> 0 | R29: 人件費÷売上
B30: 経費 合計 | C30: =SUM(C20:C29) -> 241729.23 | L30: 人時売上高 | M30: =IF((SUM(N5:N12)*SUM(O5:O12))=0,0,H20/(SUM(N5:N12)*SUM(O5:O12))) -> 0 | R30: 売上÷総労働時間
B32: ■ 一括経費（設備投資等） | G32: ■ 月次損益計算 | L32: ■ オーナー人件費 未払い管理
B33: 科目 | C33: 予算 | D33: 実績 | E33: 差額（残） | F33: メモ | H33: 項目 | I33: 金額 | L33: 帳簿上は計上、実際の支払いは利益が出てから
B34: 設備購入 | E34: =C34-D34 -> 0 | H34: 売上高 | I34: =H20 -> 0 | L34: 今月の人件費 支払い？ | M34: 未払い | N34: ← 「支払い」か「未払い」を入力
B35: 内装工事 | C35: 2800000 | D35: 2800000 | E35: =C35-D35 -> 0 | H35: 原価合計 | I35: =C16 -> 0 | L35: 人件費（帳簿計上額） | M35: =M23 -> 0 | N35: P/Lに反映
B36: その他一括経費 | E36: =C36-D36 -> 0 | H36: 粗利益 | I36: =I34-I35 -> 0 | L36: 実際の支払い額 | M36: =IF(M34="支払い",M35,0) -> 0 | N36: 口座から出るお金
E37: =C37-D37 -> 0 | H37: 粗利率 | I37: =IF(I34=0,0,I36/I34) -> 0 | L37: 今月の未払い額 | M37: =M35-M36 -> 0 | N37: 帳簿上は経費だが現金は出ない
E38: =C38-D38 -> 0 | H38: 経費合計 | I38: =C30 -> 241729.23 | L38: 前月までの未払い累計 | M38: ='7月'!M39 -> 0
E39: =C39-D39 -> 0 | H39: 営業利益 | I39: =I36-I38 -> -241729.23 | L39: 未払い累計（今月末時点） | M39: =M38+M37 -> 0 | N39: 将来支払う必要のある額
E40: =C40-D40 -> 0
E41: =C41-D41 -> 0 | L41: 過去の未払い分 今月支払額 | N41: 未払い累計から取り崩す場合に入力
E42: =C42-D42 -> 0
E43: =C43-D43 -> 0
E44: =C44-D44 -> 0
E45: =C45-D45 -> 0
E46: =C46-D46 -> 0
E47: =C47-D47 -> 0
E48: =C48-D48 -> 0
E49: =C49-D49 -> 0
E50: =C50-D50 -> 0
E51: =C51-D51 -> 0
E52: =C52-D52 -> 0
E53: =C53-D53 -> 0
B54: 一括経費 合計 | C54: =SUM(C34:C53) -> 2800000 | D54: =SUM(D34:D53) -> 2800000 | E54: =C54-D54 -> 0
B56: コスト合計（原価＋経費＋一括） | C56: =C16+C30+D54 -> 3041729.2
G58: ■ キャッシュフロー（実際のお金の動き）
H59: 項目 | I59: 金額
H60: 営業利益 | I60: =I39 -> -241729.23
H61: ＋ 減価償却費（現金支出なし） | I61: =C29 -> 14433.833 | J61: 損益上の経費だが現金は出ない
H62: 営業CF | I62: =I60+I61+M37-M41 -> -227295.4 | J62: 実際に営業で増えた現金
H64: − 設備投資（一括経費） | I64: =D54 -> 2800000 | J64: 実際に出ていった現金
H65: 投資CF | I65: =-I64 -> -2800000 | J65: 設備購入で減った現金
H67: 追加資金（借入・増資等） | I67: =C6
H68: 財務CF | I68: =I67
G70: ■ 口座残高
H71: 前月末 口座残高 | I71: =C5 -> 3983694
H72: ＋ 営業CF | I72: =I62 -> -227295.4
H73: ＋ 投資CF | I73: =I65 -> -2800000
H74: ＋ 財務CF | I74: =I68
H75: 期末 口座残高 | I75: =I71+I72+I73+I74 -> 956398.6 | J75: 翌月に繰越
H77: 【参考】損益と現金の差
H78: 帳簿上の利益（営業利益） | I78: =I39 -> -241729.23
H79: 実際の現金増減（CF合計） | I79: =I72+I73+I74 -> -3027295.4
H80: 差額（減価償却＋設備投資） | I80: =I79-I78 -> -2785566.2 | J80: ＋なら利益より現金が多い
H82: 期末口座（人件費なし） | I82: =I75 -> 956398.6 | J82: 3人の給与を払わない場合
H83: 期末口座（人件費あり） | I83: =I75-M37 -> 956398.6 | J83: 3人に給与を払った場合

Sheet 9月
B1: ☕ カフェ経営管理 ─ 9月 | U1: ■ 計画値（売上計画シートから自動取得）
B2: 月末口座（人件費なし） | C2: =I75 -> 1729103.2 | E2: 今月出ていくお金 | F2: =C16+SUM(C20:C23)+SUM(C25:C28)+M36+D54+M41 -> 0 | H2: 今月の利益 | I2: =I39 -> -241729.23 | L2: 来月必要なお金 | M2: ='10月'!C20+'10月'!C21+'10月'!C22+'10月'!C23+'10月'!C25 -> 0 | U2: 実績の入力時に参考にしてください。差額・達成率も自動表示。
B3: ■ 資金（期首残高） | G3: ■ 売上（定期収入） | L3: ■ 人件費計算
B4: 科目 | C4: 金額 | D4: 詳細 | E4: メモ | G4: カテゴリ | H4: 金額 | I4: 詳細 | J4: メモ | L4: スタッフ名 | M4: 時給 | N4: 日数 | O4: 時間/日 | P4: 交通費/日 | Q4: 小計（給与） | R4: 小計（交通費） | U4: ■ 売上
B5: 前月繰越金 | C5: ='8月'!I75 -> 956398.6 | G5: ドリンク（コーヒー） | H5: ='9月日次売上'!C34 -> 0 | Q5: =M5*N5*O5 -> 0 | R5: =P5*N5 -> 0 | U5: 項目 | V5: 計画 | W5: 実績 | X5: 差額 | Y5: 達成率
B6: 追加資金（借入等） | C6: 1000000 | D6: クラウドファンディング | E6: クラファン100万円入金（9月） | G6: ドリンク（紅茶・その他） | H6: ='9月日次売上'!D34 -> 0 | Q6: =M6*N6*O6 -> 0 | R6: =P6*N6 -> 0 | U6: 昼 来客数（季節調整後）/日 | V6: ='売上計画'!H38 -> 13 | W6: =IF(H26=0,"",H24/H26/2) -> 0 | X6: =IF(W6="",0,W6-V6) -> -13 | Y6: =IF(OR(W6="",V6=0),0,W6/V6) -> 0
B7: 期首資金 合計 | C7: =SUM(C5:C6) -> 1956398.6 | G7: フード（軽食） | H7: ='9月日次売上'!E34 -> 0 | Q7: =M7*N7*O7 -> 0 | R7: =P7*N7 -> 0 | U7: 夜 来客数（季節調整後）/日 | V7: ='売上計画'!H39 -> 7 | W7: =IF(H26=0,"",H24/H26/2) -> 0 | X7: =IF(W7="",0,W7-V7) -> -7 | Y7: =IF(OR(W7="",V7=0),0,W7/V7) -> 0
G8: フード（スイーツ） | H8: ='9月日次売上'!F34 -> 0 | Q8: =M8*N8*O8 -> 0 | R8: =P8*N8 -> 0 | U8: 売上合計（月間） | V8: ='売上計画'!H45 -> 709500 | W8: =H20 -> 0 | X8: =W8-V8 -> -709500 | Y8: =IF(V8=0,0,W8/V8) -> 0
B9: ■ 原価（売上原価） | G9: 物販（コーヒー豆・グッズ） | H9: ='9月日次売上'!G34 -> 0 | Q9: =M9*N9*O9 -> 0 | R9: =P9*N9 -> 0 | U9: 客単価 | V9: =IF((V6*'売上計画'!$C$7+V7*'売上計画'!$C$8)=0,0,V8/(V6*'売上計画'!$C$7+V7*'売上計画'!$C$8)) -> 1182.5 | W9: =H25 -> 0 | X9: =W9-V9 -> -1182.5 | Y9: =IF(V9=0,0,W9/V9) -> 0
B10: 科目 | C10: 金額 | D10: 詳細 | E10: メモ | G10: テイクアウト | H10: ='9月日次売上'!H34 -> 0 | Q10: =M10*N10*O10 -> 0 | R10: =P10*N10 -> 0
B11: コーヒー豆・茶葉 | C11: =SUMIFS('freee実績'!$E:$E,'freee実績'!$B:$B,"2026-09",'freee実績'!$C:$C,"仕入高",'freee実績'!$D:$D,"コーヒー豆・茶葉") -> 0 | G11: 売上 合計 | H11: =SUM(H5:H10) -> 0 | Q11: =M11*N11*O11 -> 0 | R11: =P11*N11 -> 0 | U11: ■ 原価・粗利
B12: 牛乳・シロップ等 | C12: =SUMIFS('freee実績'!$E:$E,'freee実績'!$B:$B,"2026-09",'freee実績'!$C:$C,"仕入高",'freee実績'!$D:$D,"牛乳・シロップ等") -> 0 | Q12: =M12*N12*O12 -> 0 | R12: =P12*N12 -> 0 | U12: 項目 | V12: 計画 | W12: 実績 | X12: 差額 | Y12: 原価率
B13: フード材料費 | C13: =SUMIFS('freee実績'!$E:$E,'freee実績'!$B:$B,"2026-09",'freee実績'!$C:$C,"仕入高",'freee実績'!$D:$D,"フード材料費") -> 0 | G13: ■ その他収入（不定期） | L13: アルバイト給与 合計 | Q13: =SUM(Q5:Q12) -> 0 | R13: =SUM(R5:R12) -> 0 | U13: 原価合計 | V13: ='売上計画'!H46 -> 212850 | W13: =C16 -> 0 | X13: =W13-V13 -> -212850 | Y13: =IF(W8=0,0,W13/W8) -> 0
B14: 包装資材・消耗品 | C14: =SUMIFS('freee実績'!$E:$E,'freee実績'!$B:$B,"2026-09",'freee実績'!$C:$C,"仕入高",'freee実績'!$D:$D,"包装資材・消耗品") -> 0 | G14: カテゴリ | H14: 金額 | I14: 詳細 | J14: メモ | U14: 粗利益 | V14: ='売上計画'!H47 -> 496650 | W14: =H20-C16 -> 0 | X14: =W14-V14 -> -496650 | Y14: =IF(W8=0,0,W14/W8) -> 0
B15: その他原価 | C15: =SUMIFS('freee実績'!$E:$E,'freee実績'!$B:$B,"2026-09",'freee実績'!$C:$C,"仕入高",'freee実績'!$D:$D,"その他原価") -> 0 | G15: イベント・貸切 | H15: ='9月日次売上'!I34 -> 0 | L15: ■ 固定人件費（役員報酬・社員給与等）
B16: 原価 合計 | C16: =SUM(C11:C15) -> 0 | G16: その他収入② | L16: 項目 | M16: 月額 | R16: 備考 | U16: ■ 経費
G17: その他収入 | L17: 役員報酬 | U17: 項目 | V17: 計画 | W17: 実績 | X17: 差額
B18: ■ 経費（販管費） | G18: その他収入 合計 | H18: =SUM(H15:H17) -> 0 | L18: 社員給与 | U18: 人件費（バイト+固定） | V18: ='売上計画'!H54 -> 45 | W18: =C24 -> 227295.4 | X18: =W18-V18 -> 227250.4
B19: 科目 | C19: 金額 | D19: 詳細 | E19: メモ | L19: 社会保険料（会社負担） | U19: 固定費（家賃+光熱+通信+保険） | V19: ='売上計画'!H57 -> 570 | W19: =C20+C21+C22+C23 -> 0 | X19: =W19-V19 -> -570
B20: 家賃 | C20: =SUMIFS('freee実績'!$E:$E,'freee実績'!$B:$B,"2026-09",'freee実績'!$C:$C,"地代家賃") -> 0 | D20: 固定費 | G20: 売上合計（定期＋不定期） | H20: =H11+H18 -> 0 | L20: その他人件費 | U20: 消耗品 | V20: ='売上計画'!H58 -> 0 | W20: =C25 -> 0 | X20: =W20-V20 -> 0
B21: 水道光熱費 | C21: =SUMIFS('freee実績'!$E:$E,'freee実績'!$B:$B,"2026-09",'freee実績'!$C:$C,"水道光熱費") -> 0 | D21: 固定費 | L21: 固定人件費 合計 | M21: =SUM(M17:M20) -> 0 | U21: 経費合計 | V21: ='売上計画'!H59 -> 0 | W21: =C30 -> 241729.23 | X21: =W21-V21 -> 241729.23
B22: 通信費 | C22: =SUMIFS('freee実績'!$E:$E,'freee実績'!$B:$B,"2026-09",'freee実績'!$C:$C,"通信費") -> 0 | D22: 固定費 | G22: ■ 売上KPI
B23: 保険料 | C23: =SUMIFS('freee実績'!$E:$E,'freee実績'!$B:$B,"2026-09",'freee実績'!$C:$C,"保険料") -> 0 | D23: 固定費 | G23: 指標 | H23: 数値 | J23: 算出方法 | L23: 人件費 総合計 | M23: =Q13+R13+M21 -> 0 | U23: ■ 営業利益
B24: 人件費（給与・社保） | C24: ='役員報酬・社保'!C17+'役員報酬・社保'!E17+'役員報酬・社保'!C71+'役員報酬・社保'!E71+86400 -> 227295.4 | D24: 変動費 | G24: 来客数（人） | H24: ='9月日次売上'!J34 -> 0 | U24: 項目 | V24: 計画 | W24: 実績 | X24: 差額 | Y24: 達成率
B25: 消耗品費 | C25: =SUMIFS('freee実績'!$E:$E,'freee実績'!$B:$B,"2026-09",'freee実績'!$C:$C,"消耗品費") -> 0 | D25: 変動費 | G25: 客単価 | H25: =IF(H24=0,0,H20/H24) -> 0 | J25: 売上÷来客数 | L25: ↑ この金額を左側「人件費（給与・社保）」に転記 | U25: 営業利益 | V25: ='売上計画'!H61 | W25: =I39 -> -241729.23 | X25: =W25-V25 -> -241729.23 | Y25: =IF(V25=0,0,W25/V25) -> 0
B26: 広告宣伝費 | C26: =SUMIFS('freee実績'!$E:$E,'freee実績'!$B:$B,"2026-09",'freee実績'!$C:$C,"広告宣伝費") -> 0 | D26: 変動費 | G26: 営業日数 | H26: 30 | U26: 営業利益率 | V26: ='売上計画'!H62 -> 316650 | W26: =IF(W8=0,0,W25/W8) -> 0 | X26: =W26-V26 -> -316650
B27: 修繕費 | C27: =SUMIFS('freee実績'!$E:$E,'freee実績'!$B:$B,"2026-09",'freee実績'!$C:$C,"修繕費") -> 0 | D27: 変動費 | G27: 日商（1日平均売上） | H27: =IF(H26=0,0,H20/H26) -> 0 | J27: 売上÷営業日数 | L27: ■ 人件費KPI
B28: その他経費 | C28: =SUMIFS('freee実績'!$E:$E,'freee実績'!$B:$B,"2026-09",'freee実績'!$C:$C,"雑費") -> 0 | D28: 変動費 | G28: 原価率 | H28: =IF(H20=0,0,C16/H20) -> 0 | J28: 原価÷売上 | L28: 指標 | M28: 数値 | R28: 算出方法
B29: 減価償却費 | C29: ='固定資産台帳'!Q26 -> 14433.833 | D29: 帳簿上のみ | L29: 人件費率 | M29: =IF(H20=0,0,M23/H20) -> 0 | R29: 人件費÷売上
B30: 経費 合計 | C30: =SUM(C20:C29) -> 241729.23 | L30: 人時売上高 | M30: =IF((SUM(N5:N12)*SUM(O5:O12))=0,0,H20/(SUM(N5:N12)*SUM(O5:O12))) -> 0 | R30: 売上÷総労働時間
B32: ■ 一括経費（設備投資等） | G32: ■ 月次損益計算 | L32: ■ オーナー人件費 未払い管理
B33: 科目 | C33: 予算 | D33: 実績 | E33: 差額（残） | F33: メモ | H33: 項目 | I33: 金額 | L33: 帳簿上は計上、実際の支払いは利益が出てから
B34: 設備購入 | E34: =C34-D34 -> 0 | H34: 売上高 | I34: =H20 -> 0 | L34: 今月の人件費 支払い？ | M34: 未払い | N34: ← 「支払い」か「未払い」を入力
B35: 内装工事 | E35: =C35-D35 -> 0 | H35: 原価合計 | I35: =C16 -> 0 | L35: 人件費（帳簿計上額） | M35: =M23 -> 0 | N35: P/Lに反映
B36: その他一括経費 | E36: =C36-D36 -> 0 | H36: 粗利益 | I36: =I34-I35 -> 0 | L36: 実際の支払い額 | M36: =IF(M34="支払い",M35,0) -> 0 | N36: 口座から出るお金
E37: =C37-D37 -> 0 | H37: 粗利率 | I37: =IF(I34=0,0,I36/I34) -> 0 | L37: 今月の未払い額 | M37: =M35-M36 -> 0 | N37: 帳簿上は経費だが現金は出ない
E38: =C38-D38 -> 0 | H38: 経費合計 | I38: =C30 -> 241729.23 | L38: 前月までの未払い累計 | M38: ='8月'!M39 -> 0
E39: =C39-D39 -> 0 | H39: 営業利益 | I39: =I36-I38 -> -241729.23 | L39: 未払い累計（今月末時点） | M39: =M38+M37 -> 0 | N39: 将来支払う必要のある額
E40: =C40-D40 -> 0
E41: =C41-D41 -> 0 | L41: 過去の未払い分 今月支払額 | N41: 未払い累計から取り崩す場合に入力
E42: =C42-D42 -> 0
E43: =C43-D43 -> 0
E44: =C44-D44 -> 0
E45: =C45-D45 -> 0
E46: =C46-D46 -> 0
E47: =C47-D47 -> 0
E48: =C48-D48 -> 0
E49: =C49-D49 -> 0
E50: =C50-D50 -> 0
E51: =C51-D51 -> 0
E52: =C52-D52 -> 0
E53: =C53-D53 -> 0
B54: 一括経費 合計 | C54: =SUM(C34:C53) -> 0 | D54: =SUM(D34:D53) -> 0 | E54: =C54-D54 -> 0
B56: コスト合計（原価＋経費＋一括） | C56: =C16+C30+D54 -> 241729.23
G58: ■ キャッシュフロー（実際のお金の動き）
H59: 項目 | I59: 金額
H60: 営業利益 | I60: =I39 -> -241729.23
H61: ＋ 減価償却費（現金支出なし） | I61: =C29 -> 14433.833 | J61: 損益上の経費だが現金は出ない
H62: 営業CF | I62: =I60+I61+M37-M41 -> -227295.4 | J62: 実際に営業で増えた現金
H64: − 設備投資（一括経費） | I64: =D54 -> 0 | J64: 実際に出ていった現金
H65: 投資CF | I65: =-I64 -> 0 | J65: 設備購入で減った現金
H67: 追加資金（借入・増資等） | I67: =C6 -> 1000000
H68: 財務CF | I68: =I67 -> 1000000
G70: ■ 口座残高
H71: 前月末 口座残高 | I71: =C5 -> 956398.6
H72: ＋ 営業CF | I72: =I62 -> -227295.4
H73: ＋ 投資CF | I73: =I65 -> 0
H74: ＋ 財務CF | I74: =I68 -> 1000000
H75: 期末 口座残高 | I75: =I71+I72+I73+I74 -> 1729103.2 | J75: 翌月に繰越
H77: 【参考】損益と現金の差
H78: 帳簿上の利益（営業利益） | I78: =I39 -> -241729.23
H79: 実際の現金増減（CF合計） | I79: =I72+I73+I74 -> 772704.6
H80: 差額（減価償却＋設備投資） | I80: =I79-I78 -> 1014433.8 | J80: ＋なら利益より現金が多い
H82: 期末口座（人件費なし） | I82: =I75 -> 1729103.2 | J82: 3人の給与を払わない場合
H83: 期末口座（人件費あり） | I83: =I75-M37 -> 1729103.2 | J83: 3人に給与を払った場合

Sheet 10月
B1: ☕ カフェ経営管理 ─ 10月 | U1: ■ 計画値（売上計画シートから自動取得）
B2: 月末口座（人件費なし） | C2: =I75 -> 1431360.1 | E2: 今月出ていくお金 | F2: =C16+SUM(C20:C23)+SUM(C25:C28)+M36+D54+M41 -> 0 | H2: 今月の利益 | I2: =I39 -> -312176.93 | L2: 来月必要なお金 | M2: ='11月'!C20+'11月'!C21+'11月'!C22+'11月'!C23+'11月'!C25 -> 0 | U2: 実績の入力時に参考にしてください。差額・達成率も自動表示。
B3: ■ 資金（期首残高） | G3: ■ 売上（定期収入） | L3: ■ 人件費計算
B4: 科目 | C4: 金額 | D4: 詳細 | E4: メモ | G4: カテゴリ | H4: 金額 | I4: 詳細 | J4: メモ | L4: スタッフ名 | M4: 時給 | N4: 日数 | O4: 時間/日 | P4: 交通費/日 | Q4: 小計（給与） | R4: 小計（交通費） | U4: ■ 売上
B5: 前月繰越金 | C5: ='9月'!I75 -> 1729103.2 | G5: ドリンク（コーヒー） | H5: ='10月日次売上'!C35 -> 0 | Q5: =M5*N5*O5 -> 0 | R5: =P5*N5 -> 0 | U5: 項目 | V5: 計画 | W5: 実績 | X5: 差額 | Y5: 達成率
B6: 追加資金（借入等） | G6: ドリンク（紅茶・その他） | H6: ='10月日次売上'!D35 -> 0 | Q6: =M6*N6*O6 -> 0 | R6: =P6*N6 -> 0 | U6: 昼 来客数（季節調整後）/日 | V6: ='売上計画'!I38 -> 16 | W6: =IF(H26=0,"",H24/H26/2) -> 0 | X6: =IF(W6="",0,W6-V6) -> -16 | Y6: =IF(OR(W6="",V6=0),0,W6/V6) -> 0
B7: 期首資金 合計 | C7: =SUM(C5:C6) -> 1729103.2 | G7: フード（軽食） | H7: ='10月日次売上'!E35 -> 0 | Q7: =M7*N7*O7 -> 0 | R7: =P7*N7 -> 0 | U7: 夜 来客数（季節調整後）/日 | V7: ='売上計画'!I39 -> 12 | W7: =IF(H26=0,"",H24/H26/2) -> 0 | X7: =IF(W7="",0,W7-V7) -> -12 | Y7: =IF(OR(W7="",V7=0),0,W7/V7) -> 0
G8: フード（スイーツ） | H8: ='10月日次売上'!F35 -> 0 | Q8: =M8*N8*O8 -> 0 | R8: =P8*N8 -> 0 | U8: 売上合計（月間） | V8: ='売上計画'!I45 -> 1091200 | W8: =H20 -> 0 | X8: =W8-V8 -> -1091200 | Y8: =IF(V8=0,0,W8/V8) -> 0
B9: ■ 原価（売上原価） | G9: 物販（コーヒー豆・グッズ） | H9: ='10月日次売上'!G35 -> 0 | Q9: =M9*N9*O9 -> 0 | R9: =P9*N9 -> 0 | U9: 客単価 | V9: =IF((V6*'売上計画'!$C$7+V7*'売上計画'!$C$8)=0,0,V8/(V6*'売上計画'!$C$7+V7*'売上計画'!$C$8)) -> 1299.0476 | W9: =H25 -> 0 | X9: =W9-V9 -> -1299.0476 | Y9: =IF(V9=0,0,W9/V9) -> 0
B10: 科目 | C10: 金額 | D10: 詳細 | E10: メモ | G10: テイクアウト | H10: ='10月日次売上'!H35 -> 0 | Q10: =M10*N10*O10 -> 0 | R10: =P10*N10 -> 0
B11: コーヒー豆・茶葉 | C11: =SUMIFS('freee実績'!$E:$E,'freee実績'!$B:$B,"2026-10",'freee実績'!$C:$C,"仕入高",'freee実績'!$D:$D,"コーヒー豆・茶葉") -> 0 | G11: 売上 合計 | H11: =SUM(H5:H10) -> 0 | Q11: =M11*N11*O11 -> 0 | R11: =P11*N11 -> 0 | U11: ■ 原価・粗利
B12: 牛乳・シロップ等 | C12: =SUMIFS('freee実績'!$E:$E,'freee実績'!$B:$B,"2026-10",'freee実績'!$C:$C,"仕入高",'freee実績'!$D:$D,"牛乳・シロップ等") -> 0 | Q12: =M12*N12*O12 -> 0 | R12: =P12*N12 -> 0 | U12: 項目 | V12: 計画 | W12: 実績 | X12: 差額 | Y12: 原価率
B13: フード材料費 | C13: =SUMIFS('freee実績'!$E:$E,'freee実績'!$B:$B,"2026-10",'freee実績'!$C:$C,"仕入高",'freee実績'!$D:$D,"フード材料費") -> 0 | G13: ■ その他収入（不定期） | L13: アルバイト給与 合計 | Q13: =SUM(Q5:Q12) -> 0 | R13: =SUM(R5:R12) -> 0 | U13: 原価合計 | V13: ='売上計画'!I46 -> 327360 | W13: =C16 -> 0 | X13: =W13-V13 -> -327360 | Y13: =IF(W8=0,0,W13/W8) -> 0
B14: 包装資材・消耗品 | C14: =SUMIFS('freee実績'!$E:$E,'freee実績'!$B:$B,"2026-10",'freee実績'!$C:$C,"仕入高",'freee実績'!$D:$D,"包装資材・消耗品") -> 0 | G14: カテゴリ | H14: 金額 | I14: 詳細 | J14: メモ | U14: 粗利益 | V14: ='売上計画'!I47 -> 763840 | W14: =H20-C16 -> 0 | X14: =W14-V14 -> -763840 | Y14: =IF(W8=0,0,W14/W8) -> 0
B15: その他原価 | C15: =SUMIFS('freee実績'!$E:$E,'freee実績'!$B:$B,"2026-10",'freee実績'!$C:$C,"仕入高",'freee実績'!$D:$D,"その他原価") -> 0 | G15: イベント・貸切 | H15: ='10月日次売上'!I35 -> 0 | L15: ■ 固定人件費（役員報酬・社員給与等）
B16: 原価 合計 | C16: =SUM(C11:C15) -> 0 | G16: その他収入② | L16: 項目 | M16: 月額 | R16: 備考 | U16: ■ 経費
G17: その他収入 | L17: 役員報酬 | U17: 項目 | V17: 計画 | W17: 実績 | X17: 差額
B18: ■ 経費（販管費） | G18: その他収入 合計 | H18: =SUM(H15:H17) -> 0 | L18: 社員給与 | U18: 人件費（バイト+固定） | V18: ='売上計画'!I54 -> 46.5 | W18: =C24 -> 297743.1 | X18: =W18-V18 -> 297696.6
B19: 科目 | C19: 金額 | D19: 詳細 | E19: メモ | L19: 社会保険料（会社負担） | U19: 固定費（家賃+光熱+通信+保険） | V19: ='売上計画'!I57 -> 544 | W19: =C20+C21+C22+C23 -> 0 | X19: =W19-V19 -> -544
B20: 家賃 | C20: =SUMIFS('freee実績'!$E:$E,'freee実績'!$B:$B,"2026-10",'freee実績'!$C:$C,"地代家賃") -> 0 | D20: 固定費 | G20: 売上合計（定期＋不定期） | H20: =H11+H18 -> 0 | L20: その他人件費 | U20: 消耗品 | V20: ='売上計画'!I58 -> 0 | W20: =C25 -> 0 | X20: =W20-V20 -> 0
B21: 水道光熱費 | C21: =SUMIFS('freee実績'!$E:$E,'freee実績'!$B:$B,"2026-10",'freee実績'!$C:$C,"水道光熱費") -> 0 | D21: 固定費 | L21: 固定人件費 合計 | M21: =SUM(M17:M20) -> 0 | U21: 経費合計 | V21: ='売上計画'!I59 -> 0 | W21: =C30 -> 312176.93 | X21: =W21-V21 -> 312176.93
B22: 通信費 | C22: =SUMIFS('freee実績'!$E:$E,'freee実績'!$B:$B,"2026-10",'freee実績'!$C:$C,"通信費") -> 0 | D22: 固定費 | G22: ■ 売上KPI
B23: 保険料 | C23: =SUMIFS('freee実績'!$E:$E,'freee実績'!$B:$B,"2026-10",'freee実績'!$C:$C,"保険料") -> 0 | D23: 固定費 | G23: 指標 | H23: 数値 | J23: 算出方法 | L23: 人件費 総合計 | M23: =Q13+R13+M21 -> 0 | U23: ■ 営業利益
B24: 人件費（給与・社保） | C24: ='役員報酬・社保'!C17+'役員報酬・社保'!D17+'役員報酬・社保'!E17+'役員報酬・社保'!F71+86400 -> 297743.1 | D24: 変動費 | G24: 来客数（人） | H24: ='10月日次売上'!J35 -> 0 | U24: 項目 | V24: 計画 | W24: 実績 | X24: 差額 | Y24: 達成率
B25: 消耗品費 | C25: =SUMIFS('freee実績'!$E:$E,'freee実績'!$B:$B,"2026-10",'freee実績'!$C:$C,"消耗品費") -> 0 | D25: 変動費 | G25: 客単価 | H25: =IF(H24=0,0,H20/H24) -> 0 | J25: 売上÷来客数 | L25: ↑ この金額を左側「人件費（給与・社保）」に転記 | U25: 営業利益 | V25: ='売上計画'!I61 | W25: =I39 -> -312176.93 | X25: =W25-V25 -> -312176.93 | Y25: =IF(V25=0,0,W25/V25) -> 0
B26: 広告宣伝費 | C26: =SUMIFS('freee実績'!$E:$E,'freee実績'!$B:$B,"2026-10",'freee実績'!$C:$C,"広告宣伝費") -> 0 | D26: 変動費 | G26: 営業日数 | H26: 31 | U26: 営業利益率 | V26: ='売上計画'!I62 -> 523840 | W26: =IF(W8=0,0,W25/W8) -> 0 | X26: =W26-V26 -> -523840
B27: 修繕費 | C27: =SUMIFS('freee実績'!$E:$E,'freee実績'!$B:$B,"2026-10",'freee実績'!$C:$C,"修繕費") -> 0 | D27: 変動費 | G27: 日商（1日平均売上） | H27: =IF(H26=0,0,H20/H26) -> 0 | J27: 売上÷営業日数 | L27: ■ 人件費KPI
B28: その他経費 | C28: =SUMIFS('freee実績'!$E:$E,'freee実績'!$B:$B,"2026-10",'freee実績'!$C:$C,"雑費") -> 0 | D28: 変動費 | G28: 原価率 | H28: =IF(H20=0,0,C16/H20) -> 0 | J28: 原価÷売上 | L28: 指標 | M28: 数値 | R28: 算出方法
B29: 減価償却費 | C29: ='固定資産台帳'!R26 -> 14433.833 | D29: 帳簿上のみ | L29: 人件費率 | M29: =IF(H20=0,0,M23/H20) -> 0 | R29: 人件費÷売上
B30: 経費 合計 | C30: =SUM(C20:C29) -> 312176.93 | L30: 人時売上高 | M30: =IF((SUM(N5:N12)*SUM(O5:O12))=0,0,H20/(SUM(N5:N12)*SUM(O5:O12))) -> 0 | R30: 売上÷総労働時間
B32: ■ 一括経費（設備投資等） | G32: ■ 月次損益計算 | L32: ■ オーナー人件費 未払い管理
B33: 科目 | C33: 予算 | D33: 実績 | E33: 差額（残） | F33: メモ | H33: 項目 | I33: 金額 | L33: 帳簿上は計上、実際の支払いは利益が出てから
B34: 設備購入 | E34: =C34-D34 -> 0 | H34: 売上高 | I34: =H20 -> 0 | L34: 今月の人件費 支払い？ | M34: 未払い | N34: ← 「支払い」か「未払い」を入力
B35: 内装工事 | E35: =C35-D35 -> 0 | H35: 原価合計 | I35: =C16 -> 0 | L35: 人件費（帳簿計上額） | M35: =M23 -> 0 | N35: P/Lに反映
B36: その他一括経費 | E36: =C36-D36 -> 0 | H36: 粗利益 | I36: =I34-I35 -> 0 | L36: 実際の支払い額 | M36: =IF(M34="支払い",M35,0) -> 0 | N36: 口座から出るお金
E37: =C37-D37 -> 0 | H37: 粗利率 | I37: =IF(I34=0,0,I36/I34) -> 0 | L37: 今月の未払い額 | M37: =M35-M36 -> 0 | N37: 帳簿上は経費だが現金は出ない
E38: =C38-D38 -> 0 | H38: 経費合計 | I38: =C30 -> 312176.93 | L38: 前月までの未払い累計 | M38: ='9月'!M39 -> 0
E39: =C39-D39 -> 0 | H39: 営業利益 | I39: =I36-I38 -> -312176.93 | L39: 未払い累計（今月末時点） | M39: =M38+M37 -> 0 | N39: 将来支払う必要のある額
E40: =C40-D40 -> 0
E41: =C41-D41 -> 0 | L41: 過去の未払い分 今月支払額 | N41: 未払い累計から取り崩す場合に入力
E42: =C42-D42 -> 0
E43: =C43-D43 -> 0
E44: =C44-D44 -> 0
E45: =C45-D45 -> 0
E46: =C46-D46 -> 0
E47: =C47-D47 -> 0
E48: =C48-D48 -> 0
E49: =C49-D49 -> 0
E50: =C50-D50 -> 0
E51: =C51-D51 -> 0
E52: =C52-D52 -> 0
E53: =C53-D53 -> 0
B54: 一括経費 合計 | C54: =SUM(C34:C53) -> 0 | D54: =SUM(D34:D53) -> 0 | E54: =C54-D54 -> 0
B56: コスト合計（原価＋経費＋一括） | C56: =C16+C30+D54 -> 312176.93
G58: ■ キャッシュフロー（実際のお金の動き）
H59: 項目 | I59: 金額
H60: 営業利益 | I60: =I39 -> -312176.93
H61: ＋ 減価償却費（現金支出なし） | I61: =C29 -> 14433.833 | J61: 損益上の経費だが現金は出ない
H62: 営業CF | I62: =I60+I61+M37-M41 -> -297743.1 | J62: 実際に営業で増えた現金
H64: − 設備投資（一括経費） | I64: =D54 -> 0 | J64: 実際に出ていった現金
H65: 投資CF | I65: =-I64 -> 0 | J65: 設備購入で減った現金
H67: 追加資金（借入・増資等） | I67: =C6
H68: 財務CF | I68: =I67
G70: ■ 口座残高
H71: 前月末 口座残高 | I71: =C5 -> 1729103.2
H72: ＋ 営業CF | I72: =I62 -> -297743.1
H73: ＋ 投資CF | I73: =I65 -> 0
H74: ＋ 財務CF | I74: =I68
H75: 期末 口座残高 | I75: =I71+I72+I73+I74 -> 1431360.1 | J75: 翌月に繰越
H77: 【参考】損益と現金の差
H78: 帳簿上の利益（営業利益） | I78: =I39 -> -312176.93
H79: 実際の現金増減（CF合計） | I79: =I72+I73+I74 -> -297743.1
H80: 差額（減価償却＋設備投資） | I80: =I79-I78 -> 14433.833 | J80: ＋なら利益より現金が多い
H82: 期末口座（人件費なし） | I82: =I75 -> 1431360.1 | J82: 3人の給与を払わない場合
H83: 期末口座（人件費あり） | I83: =I75-M37 -> 1431360.1 | J83: 3人に給与を払った場合

Sheet 11月
B1: ☕ カフェ経営管理 ─ 11月 | U1: ■ 計画値（売上計画シートから自動取得）
B2: 月末口座（人件費なし） | C2: =I75 -> 1133617 | E2: 今月出ていくお金 | F2: =C16+SUM(C20:C23)+SUM(C25:C28)+M36+D54+M41 -> 0 | H2: 今月の利益 | I2: =I39 -> -312176.93 | L2: 来月必要なお金 | M2: ='12月'!C20+'12月'!C21+'12月'!C22+'12月'!C23+'12月'!C25 -> 0 | U2: 実績の入力時に参考にしてください。差額・達成率も自動表示。
B3: ■ 資金（期首残高） | G3: ■ 売上（定期収入） | L3: ■ 人件費計算
B4: 科目 | C4: 金額 | D4: 詳細 | E4: メモ | G4: カテゴリ | H4: 金額 | I4: 詳細 | J4: メモ | L4: スタッフ名 | M4: 時給 | N4: 日数 | O4: 時間/日 | P4: 交通費/日 | Q4: 小計（給与） | R4: 小計（交通費） | U4: ■ 売上
B5: 前月繰越金 | C5: ='10月'!I75 -> 1431360.1 | G5: ドリンク（コーヒー） | H5: ='11月日次売上'!C34 -> 0 | Q5: =M5*N5*O5 -> 0 | R5: =P5*N5 -> 0 | U5: 項目 | V5: 計画 | W5: 実績 | X5: 差額 | Y5: 達成率
B6: 追加資金（借入等） | G6: ドリンク（紅茶・その他） | H6: ='11月日次売上'!D34 -> 0 | Q6: =M6*N6*O6 -> 0 | R6: =P6*N6 -> 0 | U6: 昼 来客数（季節調整後）/日 | V6: ='売上計画'!J38 -> 26 | W6: =IF(H26=0,"",H24/H26/2) -> 0 | X6: =IF(W6="",0,W6-V6) -> -26 | Y6: =IF(OR(W6="",V6=0),0,W6/V6) -> 0
B7: 期首資金 合計 | C7: =SUM(C5:C6) -> 1431360.1 | G7: フード（軽食） | H7: ='11月日次売上'!E34 -> 0 | Q7: =M7*N7*O7 -> 0 | R7: =P7*N7 -> 0 | U7: 夜 来客数（季節調整後）/日 | V7: ='売上計画'!J39 -> 16 | W7: =IF(H26=0,"",H24/H26/2) -> 0 | X7: =IF(W7="",0,W7-V7) -> -16 | Y7: =IF(OR(W7="",V7=0),0,W7/V7) -> 0
G8: フード（スイーツ） | H8: ='11月日次売上'!F34 -> 0 | Q8: =M8*N8*O8 -> 0 | R8: =P8*N8 -> 0 | U8: 売上合計（月間） | V8: ='売上計画'!J45 -> 1527000 | W8: =H20 -> 0 | X8: =W8-V8 -> -1527000 | Y8: =IF(V8=0,0,W8/V8) -> 0
B9: ■ 原価（売上原価） | G9: 物販（コーヒー豆・グッズ） | H9: ='11月日次売上'!G34 -> 0 | Q9: =M9*N9*O9 -> 0 | R9: =P9*N9 -> 0 | U9: 客単価 | V9: =IF((V6*'売上計画'!$C$7+V7*'売上計画'!$C$8)=0,0,V8/(V6*'売上計画'!$C$7+V7*'売上計画'!$C$8)) -> 1211.9048 | W9: =H25 -> 0 | X9: =W9-V9 -> -1211.9048 | Y9: =IF(V9=0,0,W9/V9) -> 0
B10: 科目 | C10: 金額 | D10: 詳細 | E10: メモ | G10: テイクアウト | H10: ='11月日次売上'!H34 -> 0 | Q10: =M10*N10*O10 -> 0 | R10: =P10*N10 -> 0
B11: コーヒー豆・茶葉 | C11: =SUMIFS('freee実績'!$E:$E,'freee実績'!$B:$B,"2026-11",'freee実績'!$C:$C,"仕入高",'freee実績'!$D:$D,"コーヒー豆・茶葉") -> 0 | G11: 売上 合計 | H11: =SUM(H5:H10) -> 0 | Q11: =M11*N11*O11 -> 0 | R11: =P11*N11 -> 0 | U11: ■ 原価・粗利
B12: 牛乳・シロップ等 | C12: =SUMIFS('freee実績'!$E:$E,'freee実績'!$B:$B,"2026-11",'freee実績'!$C:$C,"仕入高",'freee実績'!$D:$D,"牛乳・シロップ等") -> 0 | Q12: =M12*N12*O12 -> 0 | R12: =P12*N12 -> 0 | U12: 項目 | V12: 計画 | W12: 実績 | X12: 差額 | Y12: 原価率
B13: フード材料費 | C13: =SUMIFS('freee実績'!$E:$E,'freee実績'!$B:$B,"2026-11",'freee実績'!$C:$C,"仕入高",'freee実績'!$D:$D,"フード材料費") -> 0 | G13: ■ その他収入（不定期） | L13: アルバイト給与 合計 | Q13: =SUM(Q5:Q12) -> 0 | R13: =SUM(R5:R12) -> 0 | U13: 原価合計 | V13: ='売上計画'!J46 -> 458100 | W13: =C16 -> 0 | X13: =W13-V13 -> -458100 | Y13: =IF(W8=0,0,W13/W8) -> 0
B14: 包装資材・消耗品 | C14: =SUMIFS('freee実績'!$E:$E,'freee実績'!$B:$B,"2026-11",'freee実績'!$C:$C,"仕入高",'freee実績'!$D:$D,"包装資材・消耗品") -> 0 | G14: カテゴリ | H14: 金額 | I14: 詳細 | J14: メモ | U14: 粗利益 | V14: ='売上計画'!J47 -> 1068900 | W14: =H20-C16 -> 0 | X14: =W14-V14 -> -1068900 | Y14: =IF(W8=0,0,W14/W8) -> 0
B15: その他原価 | C15: =SUMIFS('freee実績'!$E:$E,'freee実績'!$B:$B,"2026-11",'freee実績'!$C:$C,"仕入高",'freee実績'!$D:$D,"その他原価") -> 0 | G15: イベント・貸切 | H15: ='11月日次売上'!I34 -> 0 | L15: ■ 固定人件費（役員報酬・社員給与等）
B16: 原価 合計 | C16: =SUM(C11:C15) -> 0 | G16: その他収入② | L16: 項目 | M16: 月額 | R16: 備考 | U16: ■ 経費
G17: その他収入 | L17: 役員報酬 | U17: 項目 | V17: 計画 | W17: 実績 | X17: 差額
B18: ■ 経費（販管費） | G18: その他収入 合計 | H18: =SUM(H15:H17) -> 0 | L18: 社員給与 | U18: 人件費（バイト+固定） | V18: ='売上計画'!J54 -> 45 | W18: =C24 -> 297743.1 | X18: =W18-V18 -> 297698.1
B19: 科目 | C19: 金額 | D19: 詳細 | E19: メモ | L19: 社会保険料（会社負担） | U19: 固定費（家賃+光熱+通信+保険） | V19: ='売上計画'!J57 -> 605 | W19: =C20+C21+C22+C23 -> 0 | X19: =W19-V19 -> -605
B20: 家賃 | C20: =SUMIFS('freee実績'!$E:$E,'freee実績'!$B:$B,"2026-11",'freee実績'!$C:$C,"地代家賃") -> 0 | D20: 固定費 | G20: 売上合計（定期＋不定期） | H20: =H11+H18 -> 0 | L20: その他人件費 | U20: 消耗品 | V20: ='売上計画'!J58 -> 0 | W20: =C25 -> 0 | X20: =W20-V20 -> 0
B21: 水道光熱費 | C21: =SUMIFS('freee実績'!$E:$E,'freee実績'!$B:$B,"2026-11",'freee実績'!$C:$C,"水道光熱費") -> 0 | D21: 固定費 | L21: 固定人件費 合計 | M21: =SUM(M17:M20) -> 0 | U21: 経費合計 | V21: ='売上計画'!J59 -> 0 | W21: =C30 -> 312176.93 | X21: =W21-V21 -> 312176.93
B22: 通信費 | C22: =SUMIFS('freee実績'!$E:$E,'freee実績'!$B:$B,"2026-11",'freee実績'!$C:$C,"通信費") -> 0 | D22: 固定費 | G22: ■ 売上KPI
B23: 保険料 | C23: =SUMIFS('freee実績'!$E:$E,'freee実績'!$B:$B,"2026-11",'freee実績'!$C:$C,"保険料") -> 0 | D23: 固定費 | G23: 指標 | H23: 数値 | J23: 算出方法 | L23: 人件費 総合計 | M23: =Q13+R13+M21 -> 0 | U23: ■ 営業利益
B24: 人件費（給与・社保） | C24: ='役員報酬・社保'!C17+'役員報酬・社保'!D17+'役員報酬・社保'!E17+'役員報酬・社保'!F71+86400 -> 297743.1 | D24: 変動費 | G24: 来客数（人） | H24: ='11月日次売上'!J34 -> 0 | U24: 項目 | V24: 計画 | W24: 実績 | X24: 差額 | Y24: 達成率
B25: 消耗品費 | C25: =SUMIFS('freee実績'!$E:$E,'freee実績'!$B:$B,"2026-11",'freee実績'!$C:$C,"消耗品費") -> 0 | D25: 変動費 | G25: 客単価 | H25: =IF(H24=0,0,H20/H24) -> 0 | J25: 売上÷来客数 | L25: ↑ この金額を左側「人件費（給与・社保）」に転記 | U25: 営業利益 | V25: ='売上計画'!J61 | W25: =I39 -> -312176.93 | X25: =W25-V25 -> -312176.93 | Y25: =IF(V25=0,0,W25/V25) -> 0
B26: 広告宣伝費 | C26: =SUMIFS('freee実績'!$E:$E,'freee実績'!$B:$B,"2026-11",'freee実績'!$C:$C,"広告宣伝費") -> 0 | D26: 変動費 | G26: 営業日数 | H26: 30 | U26: 営業利益率 | V26: ='売上計画'!J62 -> 768900 | W26: =IF(W8=0,0,W25/W8) -> 0 | X26: =W26-V26 -> -768900
B27: 修繕費 | C27: =SUMIFS('freee実績'!$E:$E,'freee実績'!$B:$B,"2026-11",'freee実績'!$C:$C,"修繕費") -> 0 | D27: 変動費 | G27: 日商（1日平均売上） | H27: =IF(H26=0,0,H20/H26) -> 0 | J27: 売上÷営業日数 | L27: ■ 人件費KPI
B28: その他経費 | C28: =SUMIFS('freee実績'!$E:$E,'freee実績'!$B:$B,"2026-11",'freee実績'!$C:$C,"雑費") -> 0 | D28: 変動費 | G28: 原価率 | H28: =IF(H20=0,0,C16/H20) -> 0 | J28: 原価÷売上 | L28: 指標 | M28: 数値 | R28: 算出方法
B29: 減価償却費 | C29: ='固定資産台帳'!S26 -> 14433.833 | D29: 帳簿上のみ | L29: 人件費率 | M29: =IF(H20=0,0,M23/H20) -> 0 | R29: 人件費÷売上
B30: 経費 合計 | C30: =SUM(C20:C29) -> 312176.93 | L30: 人時売上高 | M30: =IF((SUM(N5:N12)*SUM(O5:O12))=0,0,H20/(SUM(N5:N12)*SUM(O5:O12))) -> 0 | R30: 売上÷総労働時間
B32: ■ 一括経費（設備投資等） | G32: ■ 月次損益計算 | L32: ■ オーナー人件費 未払い管理
B33: 科目 | C33: 予算 | D33: 実績 | E33: 差額（残） | F33: メモ | H33: 項目 | I33: 金額 | L33: 帳簿上は計上、実際の支払いは利益が出てから
B34: 設備購入 | E34: =C34-D34 -> 0 | H34: 売上高 | I34: =H20 -> 0 | L34: 今月の人件費 支払い？ | M34: 未払い | N34: ← 「支払い」か「未払い」を入力
B35: 内装工事 | E35: =C35-D35 -> 0 | H35: 原価合計 | I35: =C16 -> 0 | L35: 人件費（帳簿計上額） | M35: =M23 -> 0 | N35: P/Lに反映
B36: その他一括経費 | E36: =C36-D36 -> 0 | H36: 粗利益 | I36: =I34-I35 -> 0 | L36: 実際の支払い額 | M36: =IF(M34="支払い",M35,0) -> 0 | N36: 口座から出るお金
E37: =C37-D37 -> 0 | H37: 粗利率 | I37: =IF(I34=0,0,I36/I34) -> 0 | L37: 今月の未払い額 | M37: =M35-M36 -> 0 | N37: 帳簿上は経費だが現金は出ない
E38: =C38-D38 -> 0 | H38: 経費合計 | I38: =C30 -> 312176.93 | L38: 前月までの未払い累計 | M38: ='10月'!M39 -> 0
E39: =C39-D39 -> 0 | H39: 営業利益 | I39: =I36-I38 -> -312176.93 | L39: 未払い累計（今月末時点） | M39: =M38+M37 -> 0 | N39: 将来支払う必要のある額
E40: =C40-D40 -> 0
E41: =C41-D41 -> 0 | L41: 過去の未払い分 今月支払額 | N41: 未払い累計から取り崩す場合に入力
E42: =C42-D42 -> 0
E43: =C43-D43 -> 0
E44: =C44-D44 -> 0
E45: =C45-D45 -> 0
E46: =C46-D46 -> 0
E47: =C47-D47 -> 0
E48: =C48-D48 -> 0
E49: =C49-D49 -> 0
E50: =C50-D50 -> 0
E51: =C51-D51 -> 0
E52: =C52-D52 -> 0
E53: =C53-D53 -> 0
B54: 一括経費 合計 | C54: =SUM(C34:C53) -> 0 | D54: =SUM(D34:D53) -> 0 | E54: =C54-D54 -> 0
B56: コスト合計（原価＋経費＋一括） | C56: =C16+C30+D54 -> 312176.93
G58: ■ キャッシュフロー（実際のお金の動き）
H59: 項目 | I59: 金額
H60: 営業利益 | I60: =I39 -> -312176.93
H61: ＋ 減価償却費（現金支出なし） | I61: =C29 -> 14433.833 | J61: 損益上の経費だが現金は出ない
H62: 営業CF | I62: =I60+I61+M37-M41 -> -297743.1 | J62: 実際に営業で増えた現金
H64: − 設備投資（一括経費） | I64: =D54 -> 0 | J64: 実際に出ていった現金
H65: 投資CF | I65: =-I64 -> 0 | J65: 設備購入で減った現金
H67: 追加資金（借入・増資等） | I67: =C6
H68: 財務CF | I68: =I67
G70: ■ 口座残高
H71: 前月末 口座残高 | I71: =C5 -> 1431360.1
H72: ＋ 営業CF | I72: =I62 -> -297743.1
H73: ＋ 投資CF | I73: =I65 -> 0
H74: ＋ 財務CF | I74: =I68
H75: 期末 口座残高 | I75: =I71+I72+I73+I74 -> 1133617 | J75: 翌月に繰越
H77: 【参考】損益と現金の差
H78: 帳簿上の利益（営業利益） | I78: =I39 -> -312176.93
H79: 実際の現金増減（CF合計） | I79: =I72+I73+I74 -> -297743.1
H80: 差額（減価償却＋設備投資） | I80: =I79-I78 -> 14433.833 | J80: ＋なら利益より現金が多い
H82: 期末口座（人件費なし） | I82: =I75 -> 1133617 | J82: 3人の給与を払わない場合
H83: 期末口座（人件費あり） | I83: =I75-M37 -> 1133617 | J83: 3人に給与を払った場合

Sheet 12月
B1: ☕ カフェ経営管理 ─ 12月 | U1: ■ 計画値（売上計画シートから自動取得）
B2: 月末口座（人件費なし） | C2: =I75 -> 835873.9 | E2: 今月出ていくお金 | F2: =C16+SUM(C20:C23)+SUM(C25:C28)+M36+D54+M41 -> 0 | H2: 今月の利益 | I2: =I39 -> -312176.93 | L2: 来月必要なお金 | M2: ='1月'!C20+'1月'!C21+'1月'!C22+'1月'!C23+'1月'!C25 -> 0 | U2: 実績の入力時に参考にしてください。差額・達成率も自動表示。
B3: ■ 資金（期首残高） | G3: ■ 売上（定期収入） | L3: ■ 人件費計算
B4: 科目 | C4: 金額 | D4: 詳細 | E4: メモ | G4: カテゴリ | H4: 金額 | I4: 詳細 | J4: メモ | L4: スタッフ名 | M4: 時給 | N4: 日数 | O4: 時間/日 | P4: 交通費/日 | Q4: 小計（給与） | R4: 小計（交通費） | U4: ■ 売上
B5: 前月繰越金 | C5: ='11月'!I75 -> 1133617 | G5: ドリンク（コーヒー） | H5: ='12月日次売上'!C35 -> 0 | Q5: =M5*N5*O5 -> 0 | R5: =P5*N5 -> 0 | U5: 項目 | V5: 計画 | W5: 実績 | X5: 差額 | Y5: 達成率
B6: 追加資金（借入等） | G6: ドリンク（紅茶・その他） | H6: ='12月日次売上'!D35 -> 0 | Q6: =M6*N6*O6 -> 0 | R6: =P6*N6 -> 0 | U6: 昼 来客数（季節調整後）/日 | V6: ='売上計画'!K38 -> 17 | W6: =IF(H26=0,"",H24/H26/2) -> 0 | X6: =IF(W6="",0,W6-V6) -> -17 | Y6: =IF(OR(W6="",V6=0),0,W6/V6) -> 0
B7: 期首資金 合計 | C7: =SUM(C5:C6) -> 1133617 | G7: フード（軽食） | H7: ='12月日次売上'!E35 -> 0 | Q7: =M7*N7*O7 -> 0 | R7: =P7*N7 -> 0 | U7: 夜 来客数（季節調整後）/日 | V7: ='売上計画'!K39 -> 23 | W7: =IF(H26=0,"",H24/H26/2) -> 0 | X7: =IF(W7="",0,W7-V7) -> -23 | Y7: =IF(OR(W7="",V7=0),0,W7/V7) -> 0
G8: フード（スイーツ） | H8: ='12月日次売上'!F35 -> 0 | Q8: =M8*N8*O8 -> 0 | R8: =P8*N8 -> 0 | U8: 売上合計（月間） | V8: ='売上計画'!K45 -> 1731350 | W8: =H20 -> 0 | X8: =W8-V8 -> -1731350 | Y8: =IF(V8=0,0,W8/V8) -> 0
B9: ■ 原価（売上原価） | G9: 物販（コーヒー豆・グッズ） | H9: ='12月日次売上'!G35 -> 0 | Q9: =M9*N9*O9 -> 0 | R9: =P9*N9 -> 0 | U9: 客単価 | V9: =IF((V6*'売上計画'!$C$7+V7*'売上計画'!$C$8)=0,0,V8/(V6*'売上計画'!$C$7+V7*'売上計画'!$C$8)) -> 1442.7917 | W9: =H25 -> 0 | X9: =W9-V9 -> -1442.7917 | Y9: =IF(V9=0,0,W9/V9) -> 0
B10: 科目 | C10: 金額 | D10: 詳細 | E10: メモ | G10: テイクアウト | H10: ='12月日次売上'!H35 -> 0 | Q10: =M10*N10*O10 -> 0 | R10: =P10*N10 -> 0
B11: コーヒー豆・茶葉 | C11: =SUMIFS('freee実績'!$E:$E,'freee実績'!$B:$B,"2026-12",'freee実績'!$C:$C,"仕入高",'freee実績'!$D:$D,"コーヒー豆・茶葉") -> 0 | G11: 売上 合計 | H11: =SUM(H5:H10) -> 0 | Q11: =M11*N11*O11 -> 0 | R11: =P11*N11 -> 0 | U11: ■ 原価・粗利
B12: 牛乳・シロップ等 | C12: =SUMIFS('freee実績'!$E:$E,'freee実績'!$B:$B,"2026-12",'freee実績'!$C:$C,"仕入高",'freee実績'!$D:$D,"牛乳・シロップ等") -> 0 | Q12: =M12*N12*O12 -> 0 | R12: =P12*N12 -> 0 | U12: 項目 | V12: 計画 | W12: 実績 | X12: 差額 | Y12: 原価率
B13: フード材料費 | C13: =SUMIFS('freee実績'!$E:$E,'freee実績'!$B:$B,"2026-12",'freee実績'!$C:$C,"仕入高",'freee実績'!$D:$D,"フード材料費") -> 0 | G13: ■ その他収入（不定期） | L13: アルバイト給与 合計 | Q13: =SUM(Q5:Q12) -> 0 | R13: =SUM(R5:R12) -> 0 | U13: 原価合計 | V13: ='売上計画'!K46 -> 519405 | W13: =C16 -> 0 | X13: =W13-V13 -> -519405 | Y13: =IF(W8=0,0,W13/W8) -> 0
B14: 包装資材・消耗品 | C14: =SUMIFS('freee実績'!$E:$E,'freee実績'!$B:$B,"2026-12",'freee実績'!$C:$C,"仕入高",'freee実績'!$D:$D,"包装資材・消耗品") -> 0 | G14: カテゴリ | H14: 金額 | I14: 詳細 | J14: メモ | U14: 粗利益 | V14: ='売上計画'!K47 -> 1211945 | W14: =H20-C16 -> 0 | X14: =W14-V14 -> -1211945 | Y14: =IF(W8=0,0,W14/W8) -> 0
B15: その他原価 | C15: =SUMIFS('freee実績'!$E:$E,'freee実績'!$B:$B,"2026-12",'freee実績'!$C:$C,"仕入高",'freee実績'!$D:$D,"その他原価") -> 0 | G15: イベント・貸切 | H15: ='12月日次売上'!I35 -> 0 | L15: ■ 固定人件費（役員報酬・社員給与等）
B16: 原価 合計 | C16: =SUM(C11:C15) -> 0 | G16: その他収入② | L16: 項目 | M16: 月額 | R16: 備考 | U16: ■ 経費
G17: その他収入 | L17: 役員報酬 | U17: 項目 | V17: 計画 | W17: 実績 | X17: 差額
B18: ■ 経費（販管費） | G18: その他収入 合計 | H18: =SUM(H15:H17) -> 0 | L18: 社員給与 | U18: 人件費（バイト+固定） | V18: ='売上計画'!K54 -> 46.5 | W18: =C24 -> 297743.1 | X18: =W18-V18 -> 297696.6
B19: 科目 | C19: 金額 | D19: 詳細 | E19: メモ | L19: 社会保険料（会社負担） | U19: 固定費（家賃+光熱+通信+保険） | V19: ='売上計画'!K57 -> 583.5 | W19: =C20+C21+C22+C23 -> 0 | X19: =W19-V19 -> -583.5
B20: 家賃 | C20: =SUMIFS('freee実績'!$E:$E,'freee実績'!$B:$B,"2026-12",'freee実績'!$C:$C,"地代家賃") -> 0 | D20: 固定費 | G20: 売上合計（定期＋不定期） | H20: =H11+H18 -> 0 | L20: その他人件費 | U20: 消耗品 | V20: ='売上計画'!K58 -> 0 | W20: =C25 -> 0 | X20: =W20-V20 -> 0
B21: 水道光熱費 | C21: =SUMIFS('freee実績'!$E:$E,'freee実績'!$B:$B,"2026-12",'freee実績'!$C:$C,"水道光熱費") -> 0 | D21: 固定費 | L21: 固定人件費 合計 | M21: =SUM(M17:M20) -> 0 | U21: 経費合計 | V21: ='売上計画'!K59 -> 0 | W21: =C30 -> 312176.93 | X21: =W21-V21 -> 312176.93
B22: 通信費 | C22: =SUMIFS('freee実績'!$E:$E,'freee実績'!$B:$B,"2026-12",'freee実績'!$C:$C,"通信費") -> 0 | D22: 固定費 | G22: ■ 売上KPI
B23: 保険料 | C23: =SUMIFS('freee実績'!$E:$E,'freee実績'!$B:$B,"2026-12",'freee実績'!$C:$C,"保険料") -> 0 | D23: 固定費 | G23: 指標 | H23: 数値 | J23: 算出方法 | L23: 人件費 総合計 | M23: =Q13+R13+M21 -> 0 | U23: ■ 営業利益
B24: 人件費（給与・社保） | C24: ='役員報酬・社保'!C17+'役員報酬・社保'!D17+'役員報酬・社保'!E17+'役員報酬・社保'!F71+86400 -> 297743.1 | D24: 変動費 | G24: 来客数（人） | H24: ='12月日次売上'!J35 -> 0 | U24: 項目 | V24: 計画 | W24: 実績 | X24: 差額 | Y24: 達成率
B25: 消耗品費 | C25: =SUMIFS('freee実績'!$E:$E,'freee実績'!$B:$B,"2026-12",'freee実績'!$C:$C,"消耗品費") -> 0 | D25: 変動費 | G25: 客単価 | H25: =IF(H24=0,0,H20/H24) -> 0 | J25: 売上÷来客数 | L25: ↑ この金額を左側「人件費（給与・社保）」に転記 | U25: 営業利益 | V25: ='売上計画'!K61 | W25: =I39 -> -312176.93 | X25: =W25-V25 -> -312176.93 | Y25: =IF(V25=0,0,W25/V25) -> 0
B26: 広告宣伝費 | C26: =SUMIFS('freee実績'!$E:$E,'freee実績'!$B:$B,"2026-12",'freee実績'!$C:$C,"広告宣伝費") -> 0 | D26: 変動費 | G26: 営業日数 | H26: 31 | U26: 営業利益率 | V26: ='売上計画'!K62 -> 851945 | W26: =IF(W8=0,0,W25/W8) -> 0 | X26: =W26-V26 -> -851945
B27: 修繕費 | C27: =SUMIFS('freee実績'!$E:$E,'freee実績'!$B:$B,"2026-12",'freee実績'!$C:$C,"修繕費") -> 0 | D27: 変動費 | G27: 日商（1日平均売上） | H27: =IF(H26=0,0,H20/H26) -> 0 | J27: 売上÷営業日数 | L27: ■ 人件費KPI
B28: その他経費 | C28: =SUMIFS('freee実績'!$E:$E,'freee実績'!$B:$B,"2026-12",'freee実績'!$C:$C,"雑費") -> 0 | D28: 変動費 | G28: 原価率 | H28: =IF(H20=0,0,C16/H20) -> 0 | J28: 原価÷売上 | L28: 指標 | M28: 数値 | R28: 算出方法
B29: 減価償却費 | C29: ='固定資産台帳'!T26 -> 14433.833 | D29: 帳簿上のみ | L29: 人件費率 | M29: =IF(H20=0,0,M23/H20) -> 0 | R29: 人件費÷売上
B30: 経費 合計 | C30: =SUM(C20:C29) -> 312176.93 | L30: 人時売上高 | M30: =IF((SUM(N5:N12)*SUM(O5:O12))=0,0,H20/(SUM(N5:N12)*SUM(O5:O12))) -> 0 | R30: 売上÷総労働時間
B32: ■ 一括経費（設備投資等） | G32: ■ 月次損益計算 | L32: ■ オーナー人件費 未払い管理
B33: 科目 | C33: 予算 | D33: 実績 | E33: 差額（残） | F33: メモ | H33: 項目 | I33: 金額 | L33: 帳簿上は計上、実際の支払いは利益が出てから
B34: 設備購入 | E34: =C34-D34 -> 0 | H34: 売上高 | I34: =H20 -> 0 | L34: 今月の人件費 支払い？ | M34: 未払い | N34: ← 「支払い」か「未払い」を入力
B35: 内装工事 | E35: =C35-D35 -> 0 | H35: 原価合計 | I35: =C16 -> 0 | L35: 人件費（帳簿計上額） | M35: =M23 -> 0 | N35: P/Lに反映
B36: その他一括経費 | E36: =C36-D36 -> 0 | H36: 粗利益 | I36: =I34-I35 -> 0 | L36: 実際の支払い額 | M36: =IF(M34="支払い",M35,0) -> 0 | N36: 口座から出るお金
E37: =C37-D37 -> 0 | H37: 粗利率 | I37: =IF(I34=0,0,I36/I34) -> 0 | L37: 今月の未払い額 | M37: =M35-M36 -> 0 | N37: 帳簿上は経費だが現金は出ない
E38: =C38-D38 -> 0 | H38: 経費合計 | I38: =C30 -> 312176.93 | L38: 前月までの未払い累計 | M38: ='11月'!M39 -> 0
E39: =C39-D39 -> 0 | H39: 営業利益 | I39: =I36-I38 -> -312176.93 | L39: 未払い累計（今月末時点） | M39: =M38+M37 -> 0 | N39: 将来支払う必要のある額
E40: =C40-D40 -> 0
E41: =C41-D41 -> 0 | L41: 過去の未払い分 今月支払額 | N41: 未払い累計から取り崩す場合に入力
E42: =C42-D42 -> 0
E43: =C43-D43 -> 0
E44: =C44-D44 -> 0
E45: =C45-D45 -> 0
E46: =C46-D46 -> 0
E47: =C47-D47 -> 0
E48: =C48-D48 -> 0
E49: =C49-D49 -> 0
E50: =C50-D50 -> 0
E51: =C51-D51 -> 0
E52: =C52-D52 -> 0
E53: =C53-D53 -> 0
B54: 一括経費 合計 | C54: =SUM(C34:C53) -> 0 | D54: =SUM(D34:D53) -> 0 | E54: =C54-D54 -> 0
B56: コスト合計（原価＋経費＋一括） | C56: =C16+C30+D54 -> 312176.93
G58: ■ キャッシュフロー（実際のお金の動き）
H59: 項目 | I59: 金額
H60: 営業利益 | I60: =I39 -> -312176.93
H61: ＋ 減価償却費（現金支出なし） | I61: =C29 -> 14433.833 | J61: 損益上の経費だが現金は出ない
H62: 営業CF | I62: =I60+I61+M37-M41 -> -297743.1 | J62: 実際に営業で増えた現金
H64: − 設備投資（一括経費） | I64: =D54 -> 0 | J64: 実際に出ていった現金
H65: 投資CF | I65: =-I64 -> 0 | J65: 設備購入で減った現金
H67: 追加資金（借入・増資等） | I67: =C6
H68: 財務CF | I68: =I67
G70: ■ 口座残高
H71: 前月末 口座残高 | I71: =C5 -> 1133617
H72: ＋ 営業CF | I72: =I62 -> -297743.1
H73: ＋ 投資CF | I73: =I65 -> 0
H74: ＋ 財務CF | I74: =I68
H75: 期末 口座残高 | I75: =I71+I72+I73+I74 -> 835873.9 | J75: 翌月に繰越
H77: 【参考】損益と現金の差
H78: 帳簿上の利益（営業利益） | I78: =I39 -> -312176.93
H79: 実際の現金増減（CF合計） | I79: =I72+I73+I74 -> -297743.1
H80: 差額（減価償却＋設備投資） | I80: =I79-I78 -> 14433.833 | J80: ＋なら利益より現金が多い
H82: 期末口座（人件費なし） | I82: =I75 -> 835873.9 | J82: 3人の給与を払わない場合
H83: 期末口座（人件費あり） | I83: =I75-M37 -> 835873.9 | J83: 3人に給与を払った場合

Sheet 1月
B1: ☕ カフェ経営管理 ─ 1月 | U1: ■ 計画値（売上計画シートから自動取得）
B2: 月末口座（人件費なし） | C2: =I75 -> 538130.8 | E2: 今月出ていくお金 | F2: =C16+SUM(C20:C23)+SUM(C25:C28)+M36+D54+M41 -> 0 | H2: 今月の利益 | I2: =I39 -> -312176.93 | L2: 来月必要なお金 | M2: ='2月'!C20+'2月'!C21+'2月'!C22+'2月'!C23+'2月'!C25 -> 0 | U2: 実績の入力時に参考にしてください。差額・達成率も自動表示。
B3: ■ 資金（期首残高） | G3: ■ 売上（定期収入） | L3: ■ 人件費計算
B4: 科目 | C4: 金額 | D4: 詳細 | E4: メモ | G4: カテゴリ | H4: 金額 | I4: 詳細 | J4: メモ | L4: スタッフ名 | M4: 時給 | N4: 日数 | O4: 時間/日 | P4: 交通費/日 | Q4: 小計（給与） | R4: 小計（交通費） | U4: ■ 売上
B5: 前月繰越金 | C5: ='12月'!I75 -> 835873.9 | G5: ドリンク（コーヒー） | H5: ='1月日次売上'!C35 -> 0 | Q5: =M5*N5*O5 -> 0 | R5: =P5*N5 -> 0 | U5: 項目 | V5: 計画 | W5: 実績 | X5: 差額 | Y5: 達成率
B6: 追加資金（借入等） | G6: ドリンク（紅茶・その他） | H6: ='1月日次売上'!D35 -> 0 | Q6: =M6*N6*O6 -> 0 | R6: =P6*N6 -> 0 | U6: 昼 来客数（季節調整後）/日 | V6: ='売上計画'!L38 -> 14 | W6: =IF(H26=0,"",H24/H26/2) -> 0 | X6: =IF(W6="",0,W6-V6) -> -14 | Y6: =IF(OR(W6="",V6=0),0,W6/V6) -> 0
B7: 期首資金 合計 | C7: =SUM(C5:C6) -> 835873.9 | G7: フード（軽食） | H7: ='1月日次売上'!E35 -> 0 | Q7: =M7*N7*O7 -> 0 | R7: =P7*N7 -> 0 | U7: 夜 来客数（季節調整後）/日 | V7: ='売上計画'!L39 -> 13 | W7: =IF(H26=0,"",H24/H26/2) -> 0 | X7: =IF(W7="",0,W7-V7) -> -13 | Y7: =IF(OR(W7="",V7=0),0,W7/V7) -> 0
G8: フード（スイーツ） | H8: ='1月日次売上'!F35 -> 0 | Q8: =M8*N8*O8 -> 0 | R8: =P8*N8 -> 0 | U8: 売上合計（月間） | V8: ='売上計画'!L45 -> 1094300 | W8: =H20 -> 0 | X8: =W8-V8 -> -1094300 | Y8: =IF(V8=0,0,W8/V8) -> 0
B9: ■ 原価（売上原価） | G9: 物販（コーヒー豆・グッズ） | H9: ='1月日次売上'!G35 -> 0 | Q9: =M9*N9*O9 -> 0 | R9: =P9*N9 -> 0 | U9: 客単価 | V9: =IF((V6*'売上計画'!$C$7+V7*'売上計画'!$C$8)=0,0,V8/(V6*'売上計画'!$C$7+V7*'売上計画'!$C$8)) -> 1350.9877 | W9: =H25 -> 0 | X9: =W9-V9 -> -1350.9877 | Y9: =IF(V9=0,0,W9/V9) -> 0
B10: 科目 | C10: 金額 | D10: 詳細 | E10: メモ | G10: テイクアウト | H10: ='1月日次売上'!H35 -> 0 | Q10: =M10*N10*O10 -> 0 | R10: =P10*N10 -> 0
B11: コーヒー豆・茶葉 | C11: =SUMIFS('freee実績'!$E:$E,'freee実績'!$B:$B,"2027-01",'freee実績'!$C:$C,"仕入高",'freee実績'!$D:$D,"コーヒー豆・茶葉") -> 0 | G11: 売上 合計 | H11: =SUM(H5:H10) -> 0 | Q11: =M11*N11*O11 -> 0 | R11: =P11*N11 -> 0 | U11: ■ 原価・粗利
B12: 牛乳・シロップ等 | C12: =SUMIFS('freee実績'!$E:$E,'freee実績'!$B:$B,"2027-01",'freee実績'!$C:$C,"仕入高",'freee実績'!$D:$D,"牛乳・シロップ等") -> 0 | Q12: =M12*N12*O12 -> 0 | R12: =P12*N12 -> 0 | U12: 項目 | V12: 計画 | W12: 実績 | X12: 差額 | Y12: 原価率
B13: フード材料費 | C13: =SUMIFS('freee実績'!$E:$E,'freee実績'!$B:$B,"2027-01",'freee実績'!$C:$C,"仕入高",'freee実績'!$D:$D,"フード材料費") -> 0 | G13: ■ その他収入（不定期） | L13: アルバイト給与 合計 | Q13: =SUM(Q5:Q12) -> 0 | R13: =SUM(R5:R12) -> 0 | U13: 原価合計 | V13: ='売上計画'!L46 -> 328290 | W13: =C16 -> 0 | X13: =W13-V13 -> -328290 | Y13: =IF(W8=0,0,W13/W8) -> 0
B14: 包装資材・消耗品 | C14: =SUMIFS('freee実績'!$E:$E,'freee実績'!$B:$B,"2027-01",'freee実績'!$C:$C,"仕入高",'freee実績'!$D:$D,"包装資材・消耗品") -> 0 | G14: カテゴリ | H14: 金額 | I14: 詳細 | J14: メモ | U14: 粗利益 | V14: ='売上計画'!L47 -> 766010 | W14: =H20-C16 -> 0 | X14: =W14-V14 -> -766010 | Y14: =IF(W8=0,0,W14/W8) -> 0
B15: その他原価 | C15: =SUMIFS('freee実績'!$E:$E,'freee実績'!$B:$B,"2027-01",'freee実績'!$C:$C,"仕入高",'freee実績'!$D:$D,"その他原価") -> 0 | G15: イベント・貸切 | H15: ='1月日次売上'!I35 -> 0 | L15: ■ 固定人件費（役員報酬・社員給与等）
B16: 原価 合計 | C16: =SUM(C11:C15) -> 0 | G16: その他収入② | L16: 項目 | M16: 月額 | R16: 備考 | U16: ■ 経費
G17: その他収入 | L17: 役員報酬 | U17: 項目 | V17: 計画 | W17: 実績 | X17: 差額
B18: ■ 経費（販管費） | G18: その他収入 合計 | H18: =SUM(H15:H17) -> 0 | L18: 社員給与 | U18: 人件費（バイト+固定） | V18: ='売上計画'!L54 -> 46.5 | W18: =C24 -> 297743.1 | X18: =W18-V18 -> 297696.6
B19: 科目 | C19: 金額 | D19: 詳細 | E19: メモ | L19: 社会保険料（会社負担） | U19: 固定費（家賃+光熱+通信+保険） | V19: ='売上計画'!L57 -> 583.5 | W19: =C20+C21+C22+C23 -> 0 | X19: =W19-V19 -> -583.5
B20: 家賃 | C20: =SUMIFS('freee実績'!$E:$E,'freee実績'!$B:$B,"2027-01",'freee実績'!$C:$C,"地代家賃") -> 0 | D20: 固定費 | G20: 売上合計（定期＋不定期） | H20: =H11+H18 -> 0 | L20: その他人件費 | U20: 消耗品 | V20: ='売上計画'!L58 -> 0 | W20: =C25 -> 0 | X20: =W20-V20 -> 0
B21: 水道光熱費 | C21: =SUMIFS('freee実績'!$E:$E,'freee実績'!$B:$B,"2027-01",'freee実績'!$C:$C,"水道光熱費") -> 0 | D21: 固定費 | L21: 固定人件費 合計 | M21: =SUM(M17:M20) -> 0 | U21: 経費合計 | V21: ='売上計画'!L59 -> 0 | W21: =C30 -> 312176.93 | X21: =W21-V21 -> 312176.93
B22: 通信費 | C22: =SUMIFS('freee実績'!$E:$E,'freee実績'!$B:$B,"2027-01",'freee実績'!$C:$C,"通信費") -> 0 | D22: 固定費 | G22: ■ 売上KPI
B23: 保険料 | C23: =SUMIFS('freee実績'!$E:$E,'freee実績'!$B:$B,"2027-01",'freee実績'!$C:$C,"保険料") -> 0 | D23: 固定費 | G23: 指標 | H23: 数値 | J23: 算出方法 | L23: 人件費 総合計 | M23: =Q13+R13+M21 -> 0 | U23: ■ 営業利益
B24: 人件費（給与・社保） | C24: ='役員報酬・社保'!C17+'役員報酬・社保'!D17+'役員報酬・社保'!E17+'役員報酬・社保'!F71+86400 -> 297743.1 | D24: 変動費 | G24: 来客数（人） | H24: ='1月日次売上'!J35 -> 0 | U24: 項目 | V24: 計画 | W24: 実績 | X24: 差額 | Y24: 達成率
B25: 消耗品費 | C25: =SUMIFS('freee実績'!$E:$E,'freee実績'!$B:$B,"2027-01",'freee実績'!$C:$C,"消耗品費") -> 0 | D25: 変動費 | G25: 客単価 | H25: =IF(H24=0,0,H20/H24) -> 0 | J25: 売上÷来客数 | L25: ↑ この金額を左側「人件費（給与・社保）」に転記 | U25: 営業利益 | V25: ='売上計画'!L61 | W25: =I39 -> -312176.93 | X25: =W25-V25 -> -312176.93 | Y25: =IF(V25=0,0,W25/V25) -> 0
B26: 広告宣伝費 | C26: =SUMIFS('freee実績'!$E:$E,'freee実績'!$B:$B,"2027-01",'freee実績'!$C:$C,"広告宣伝費") -> 0 | D26: 変動費 | G26: 営業日数 | H26: 31 | U26: 営業利益率 | V26: ='売上計画'!L62 -> 406010 | W26: =IF(W8=0,0,W25/W8) -> 0 | X26: =W26-V26 -> -406010
B27: 修繕費 | C27: =SUMIFS('freee実績'!$E:$E,'freee実績'!$B:$B,"2027-01",'freee実績'!$C:$C,"修繕費") -> 0 | D27: 変動費 | G27: 日商（1日平均売上） | H27: =IF(H26=0,0,H20/H26) -> 0 | J27: 売上÷営業日数 | L27: ■ 人件費KPI
B28: その他経費 | C28: =SUMIFS('freee実績'!$E:$E,'freee実績'!$B:$B,"2027-01",'freee実績'!$C:$C,"雑費") -> 0 | D28: 変動費 | G28: 原価率 | H28: =IF(H20=0,0,C16/H20) -> 0 | J28: 原価÷売上 | L28: 指標 | M28: 数値 | R28: 算出方法
B29: 減価償却費 | C29: ='固定資産台帳'!U26 -> 14433.833 | D29: 帳簿上のみ | L29: 人件費率 | M29: =IF(H20=0,0,M23/H20) -> 0 | R29: 人件費÷売上
B30: 経費 合計 | C30: =SUM(C20:C29) -> 312176.93 | L30: 人時売上高 | M30: =IF((SUM(N5:N12)*SUM(O5:O12))=0,0,H20/(SUM(N5:N12)*SUM(O5:O12))) -> 0 | R30: 売上÷総労働時間
B32: ■ 一括経費（設備投資等） | G32: ■ 月次損益計算 | L32: ■ オーナー人件費 未払い管理
B33: 科目 | C33: 予算 | D33: 実績 | E33: 差額（残） | F33: メモ | H33: 項目 | I33: 金額 | L33: 帳簿上は計上、実際の支払いは利益が出てから
B34: 設備購入 | E34: =C34-D34 -> 0 | H34: 売上高 | I34: =H20 -> 0 | L34: 今月の人件費 支払い？ | M34: 未払い | N34: ← 「支払い」か「未払い」を入力
B35: 内装工事 | E35: =C35-D35 -> 0 | H35: 原価合計 | I35: =C16 -> 0 | L35: 人件費（帳簿計上額） | M35: =M23 -> 0 | N35: P/Lに反映
B36: その他一括経費 | E36: =C36-D36 -> 0 | H36: 粗利益 | I36: =I34-I35 -> 0 | L36: 実際の支払い額 | M36: =IF(M34="支払い",M35,0) -> 0 | N36: 口座から出るお金
E37: =C37-D37 -> 0 | H37: 粗利率 | I37: =IF(I34=0,0,I36/I34) -> 0 | L37: 今月の未払い額 | M37: =M35-M36 -> 0 | N37: 帳簿上は経費だが現金は出ない
E38: =C38-D38 -> 0 | H38: 経費合計 | I38: =C30 -> 312176.93 | L38: 前月までの未払い累計 | M38: ='12月'!M39 -> 0
E39: =C39-D39 -> 0 | H39: 営業利益 | I39: =I36-I38 -> -312176.93 | L39: 未払い累計（今月末時点） | M39: =M38+M37 -> 0 | N39: 将来支払う必要のある額
E40: =C40-D40 -> 0
E41: =C41-D41 -> 0 | L41: 過去の未払い分 今月支払額 | N41: 未払い累計から取り崩す場合に入力
E42: =C42-D42 -> 0
E43: =C43-D43 -> 0
E44: =C44-D44 -> 0
E45: =C45-D45 -> 0
E46: =C46-D46 -> 0
E47: =C47-D47 -> 0
E48: =C48-D48 -> 0
E49: =C49-D49 -> 0
E50: =C50-D50 -> 0
E51: =C51-D51 -> 0
E52: =C52-D52 -> 0
E53: =C53-D53 -> 0
B54: 一括経費 合計 | C54: =SUM(C34:C53) -> 0 | D54: =SUM(D34:D53) -> 0 | E54: =C54-D54 -> 0
B56: コスト合計（原価＋経費＋一括） | C56: =C16+C30+D54 -> 312176.93
G58: ■ キャッシュフロー（実際のお金の動き）
H59: 項目 | I59: 金額
H60: 営業利益 | I60: =I39 -> -312176.93
H61: ＋ 減価償却費（現金支出なし） | I61: =C29 -> 14433.833 | J61: 損益上の経費だが現金は出ない
H62: 営業CF | I62: =I60+I61+M37-M41 -> -297743.1 | J62: 実際に営業で増えた現金
H64: − 設備投資（一括経費） | I64: =D54 -> 0 | J64: 実際に出ていった現金
H65: 投資CF | I65: =-I64 -> 0 | J65: 設備購入で減った現金
H67: 追加資金（借入・増資等） | I67: =C6
H68: 財務CF | I68: =I67
G70: ■ 口座残高
H71: 前月末 口座残高 | I71: =C5 -> 835873.9
H72: ＋ 営業CF | I72: =I62 -> -297743.1
H73: ＋ 投資CF | I73: =I65 -> 0
H74: ＋ 財務CF | I74: =I68
H75: 期末 口座残高 | I75: =I71+I72+I73+I74 -> 538130.8 | J75: 翌月に繰越
H77: 【参考】損益と現金の差
H78: 帳簿上の利益（営業利益） | I78: =I39 -> -312176.93
H79: 実際の現金増減（CF合計） | I79: =I72+I73+I74 -> -297743.1
H80: 差額（減価償却＋設備投資） | I80: =I79-I78 -> 14433.833 | J80: ＋なら利益より現金が多い
H82: 期末口座（人件費なし） | I82: =I75 -> 538130.8 | J82: 3人の給与を払わない場合
H83: 期末口座（人件費あり） | I83: =I75-M37 -> 538130.8 | J83: 3人に給与を払った場合

Sheet 2月
B1: ☕ カフェ経営管理 ─ 2月 | U1: ■ 計画値（売上計画シートから自動取得）
B2: 月末口座（人件費なし） | C2: =I75 -> 240387.7 | E2: 今月出ていくお金 | F2: =C16+SUM(C20:C23)+SUM(C25:C28)+M36+D54+M41 -> 0 | H2: 今月の利益 | I2: =I39 -> -312176.93 | L2: 来月必要なお金 | M2: ='3月'!C20+'3月'!C21+'3月'!C22+'3月'!C23+'3月'!C25 -> 0 | U2: 実績の入力時に参考にしてください。差額・達成率も自動表示。
B3: ■ 資金（期首残高） | G3: ■ 売上（定期収入） | L3: ■ 人件費計算
B4: 科目 | C4: 金額 | D4: 詳細 | E4: メモ | G4: カテゴリ | H4: 金額 | I4: 詳細 | J4: メモ | L4: スタッフ名 | M4: 時給 | N4: 日数 | O4: 時間/日 | P4: 交通費/日 | Q4: 小計（給与） | R4: 小計（交通費） | U4: ■ 売上
B5: 前月繰越金 | C5: ='1月'!I75 -> 538130.8 | G5: ドリンク（コーヒー） | H5: ='2月日次売上'!C32 -> 0 | Q5: =M5*N5*O5 -> 0 | R5: =P5*N5 -> 0 | U5: 項目 | V5: 計画 | W5: 実績 | X5: 差額 | Y5: 達成率
B6: 追加資金（借入等） | G6: ドリンク（紅茶・その他） | H6: ='2月日次売上'!D32 -> 0 | Q6: =M6*N6*O6 -> 0 | R6: =P6*N6 -> 0 | U6: 昼 来客数（季節調整後）/日 | V6: ='売上計画'!M38 -> 14 | W6: =IF(H26=0,"",H24/H26/2) -> 0 | X6: =IF(W6="",0,W6-V6) -> -14 | Y6: =IF(OR(W6="",V6=0),0,W6/V6) -> 0
B7: 期首資金 合計 | C7: =SUM(C5:C6) -> 538130.8 | G7: フード（軽食） | H7: ='2月日次売上'!E32 -> 0 | Q7: =M7*N7*O7 -> 0 | R7: =P7*N7 -> 0 | U7: 夜 来客数（季節調整後）/日 | V7: ='売上計画'!M39 -> 14 | W7: =IF(H26=0,"",H24/H26/2) -> 0 | X7: =IF(W7="",0,W7-V7) -> -14 | Y7: =IF(OR(W7="",V7=0),0,W7/V7) -> 0
G8: フード（スイーツ） | H8: ='2月日次売上'!F32 -> 0 | Q8: =M8*N8*O8 -> 0 | R8: =P8*N8 -> 0 | U8: 売上合計（月間） | V8: ='売上計画'!M45 -> 1038800 | W8: =H20 -> 0 | X8: =W8-V8 -> -1038800 | Y8: =IF(V8=0,0,W8/V8) -> 0
B9: ■ 原価（売上原価） | G9: 物販（コーヒー豆・グッズ） | H9: ='2月日次売上'!G32 -> 0 | Q9: =M9*N9*O9 -> 0 | R9: =P9*N9 -> 0 | U9: 客単価 | V9: =IF((V6*'売上計画'!$C$7+V7*'売上計画'!$C$8)=0,0,V8/(V6*'売上計画'!$C$7+V7*'売上計画'!$C$8)) -> 1236.6667 | W9: =H25 -> 0 | X9: =W9-V9 -> -1236.6667 | Y9: =IF(V9=0,0,W9/V9) -> 0
B10: 科目 | C10: 金額 | D10: 詳細 | E10: メモ | G10: テイクアウト | H10: ='2月日次売上'!H32 -> 0 | Q10: =M10*N10*O10 -> 0 | R10: =P10*N10 -> 0
B11: コーヒー豆・茶葉 | C11: =SUMIFS('freee実績'!$E:$E,'freee実績'!$B:$B,"2027-02",'freee実績'!$C:$C,"仕入高",'freee実績'!$D:$D,"コーヒー豆・茶葉") -> 0 | G11: 売上 合計 | H11: =SUM(H5:H10) -> 0 | Q11: =M11*N11*O11 -> 0 | R11: =P11*N11 -> 0 | U11: ■ 原価・粗利
B12: 牛乳・シロップ等 | C12: =SUMIFS('freee実績'!$E:$E,'freee実績'!$B:$B,"2027-02",'freee実績'!$C:$C,"仕入高",'freee実績'!$D:$D,"牛乳・シロップ等") -> 0 | Q12: =M12*N12*O12 -> 0 | R12: =P12*N12 -> 0 | U12: 項目 | V12: 計画 | W12: 実績 | X12: 差額 | Y12: 原価率
B13: フード材料費 | C13: =SUMIFS('freee実績'!$E:$E,'freee実績'!$B:$B,"2027-02",'freee実績'!$C:$C,"仕入高",'freee実績'!$D:$D,"フード材料費") -> 0 | G13: ■ その他収入（不定期） | L13: アルバイト給与 合計 | Q13: =SUM(Q5:Q12) -> 0 | R13: =SUM(R5:R12) -> 0 | U13: 原価合計 | V13: ='売上計画'!M46 -> 311640 | W13: =C16 -> 0 | X13: =W13-V13 -> -311640 | Y13: =IF(W8=0,0,W13/W8) -> 0
B14: 包装資材・消耗品 | C14: =SUMIFS('freee実績'!$E:$E,'freee実績'!$B:$B,"2027-02",'freee実績'!$C:$C,"仕入高",'freee実績'!$D:$D,"包装資材・消耗品") -> 0 | G14: カテゴリ | H14: 金額 | I14: 詳細 | J14: メモ | U14: 粗利益 | V14: ='売上計画'!M47 -> 727160 | W14: =H20-C16 -> 0 | X14: =W14-V14 -> -727160 | Y14: =IF(W8=0,0,W14/W8) -> 0
B15: その他原価 | C15: =SUMIFS('freee実績'!$E:$E,'freee実績'!$B:$B,"2027-02",'freee実績'!$C:$C,"仕入高",'freee実績'!$D:$D,"その他原価") -> 0 | G15: イベント・貸切 | H15: ='2月日次売上'!I32 -> 0 | L15: ■ 固定人件費（役員報酬・社員給与等）
B16: 原価 合計 | C16: =SUM(C11:C15) -> 0 | G16: その他収入② | L16: 項目 | M16: 月額 | R16: 備考 | U16: ■ 経費
G17: その他収入 | L17: 役員報酬 | U17: 項目 | V17: 計画 | W17: 実績 | X17: 差額
B18: ■ 経費（販管費） | G18: その他収入 合計 | H18: =SUM(H15:H17) -> 0 | L18: 社員給与 | U18: 人件費（バイト+固定） | V18: ='売上計画'!M54 -> 42 | W18: =C24 -> 297743.1 | X18: =W18-V18 -> 297701.1
B19: 科目 | C19: 金額 | D19: 詳細 | E19: メモ | L19: 社会保険料（会社負担） | U19: 固定費（家賃+光熱+通信+保険） | V19: ='売上計画'!M57 -> 498 | W19: =C20+C21+C22+C23 -> 0 | X19: =W19-V19 -> -498
B20: 家賃 | C20: =SUMIFS('freee実績'!$E:$E,'freee実績'!$B:$B,"2027-02",'freee実績'!$C:$C,"地代家賃") -> 0 | D20: 固定費 | G20: 売上合計（定期＋不定期） | H20: =H11+H18 -> 0 | L20: その他人件費 | U20: 消耗品 | V20: ='売上計画'!M58 -> 0 | W20: =C25 -> 0 | X20: =W20-V20 -> 0
B21: 水道光熱費 | C21: =SUMIFS('freee実績'!$E:$E,'freee実績'!$B:$B,"2027-02",'freee実績'!$C:$C,"水道光熱費") -> 0 | D21: 固定費 | L21: 固定人件費 合計 | M21: =SUM(M17:M20) -> 0 | U21: 経費合計 | V21: ='売上計画'!M59 -> 0 | W21: =C30 -> 312176.93 | X21: =W21-V21 -> 312176.93
B22: 通信費 | C22: =SUMIFS('freee実績'!$E:$E,'freee実績'!$B:$B,"2027-02",'freee実績'!$C:$C,"通信費") -> 0 | D22: 固定費 | G22: ■ 売上KPI
B23: 保険料 | C23: =SUMIFS('freee実績'!$E:$E,'freee実績'!$B:$B,"2027-02",'freee実績'!$C:$C,"保険料") -> 0 | D23: 固定費 | G23: 指標 | H23: 数値 | J23: 算出方法 | L23: 人件費 総合計 | M23: =Q13+R13+M21 -> 0 | U23: ■ 営業利益
B24: 人件費（給与・社保） | C24: ='役員報酬・社保'!C17+'役員報酬・社保'!D17+'役員報酬・社保'!E17+'役員報酬・社保'!F71+86400 -> 297743.1 | D24: 変動費 | G24: 来客数（人） | H24: ='2月日次売上'!J32 -> 0 | U24: 項目 | V24: 計画 | W24: 実績 | X24: 差額 | Y24: 達成率
B25: 消耗品費 | C25: =SUMIFS('freee実績'!$E:$E,'freee実績'!$B:$B,"2027-02",'freee実績'!$C:$C,"消耗品費") -> 0 | D25: 変動費 | G25: 客単価 | H25: =IF(H24=0,0,H20/H24) -> 0 | J25: 売上÷来客数 | L25: ↑ この金額を左側「人件費（給与・社保）」に転記 | U25: 営業利益 | V25: ='売上計画'!M61 | W25: =I39 -> -312176.93 | X25: =W25-V25 -> -312176.93 | Y25: =IF(V25=0,0,W25/V25) -> 0
B26: 広告宣伝費 | C26: =SUMIFS('freee実績'!$E:$E,'freee実績'!$B:$B,"2027-02",'freee実績'!$C:$C,"広告宣伝費") -> 0 | D26: 変動費 | G26: 営業日数 | H26: 28 | U26: 営業利益率 | V26: ='売上計画'!M62 -> 367160 | W26: =IF(W8=0,0,W25/W8) -> 0 | X26: =W26-V26 -> -367160
B27: 修繕費 | C27: =SUMIFS('freee実績'!$E:$E,'freee実績'!$B:$B,"2027-02",'freee実績'!$C:$C,"修繕費") -> 0 | D27: 変動費 | G27: 日商（1日平均売上） | H27: =IF(H26=0,0,H20/H26) -> 0 | J27: 売上÷営業日数 | L27: ■ 人件費KPI
B28: その他経費 | C28: =SUMIFS('freee実績'!$E:$E,'freee実績'!$B:$B,"2027-02",'freee実績'!$C:$C,"雑費") -> 0 | D28: 変動費 | G28: 原価率 | H28: =IF(H20=0,0,C16/H20) -> 0 | J28: 原価÷売上 | L28: 指標 | M28: 数値 | R28: 算出方法
B29: 減価償却費 | C29: ='固定資産台帳'!V26 -> 14433.833 | D29: 帳簿上のみ | L29: 人件費率 | M29: =IF(H20=0,0,M23/H20) -> 0 | R29: 人件費÷売上
B30: 経費 合計 | C30: =SUM(C20:C29) -> 312176.93 | L30: 人時売上高 | M30: =IF((SUM(N5:N12)*SUM(O5:O12))=0,0,H20/(SUM(N5:N12)*SUM(O5:O12))) -> 0 | R30: 売上÷総労働時間
B32: ■ 一括経費（設備投資等） | G32: ■ 月次損益計算 | L32: ■ オーナー人件費 未払い管理
B33: 科目 | C33: 予算 | D33: 実績 | E33: 差額（残） | F33: メモ | H33: 項目 | I33: 金額 | L33: 帳簿上は計上、実際の支払いは利益が出てから
B34: 設備購入 | E34: =C34-D34 -> 0 | H34: 売上高 | I34: =H20 -> 0 | L34: 今月の人件費 支払い？ | M34: 未払い | N34: ← 「支払い」か「未払い」を入力
B35: 内装工事 | E35: =C35-D35 -> 0 | H35: 原価合計 | I35: =C16 -> 0 | L35: 人件費（帳簿計上額） | M35: =M23 -> 0 | N35: P/Lに反映
B36: その他一括経費 | E36: =C36-D36 -> 0 | H36: 粗利益 | I36: =I34-I35 -> 0 | L36: 実際の支払い額 | M36: =IF(M34="支払い",M35,0) -> 0 | N36: 口座から出るお金
E37: =C37-D37 -> 0 | H37: 粗利率 | I37: =IF(I34=0,0,I36/I34) -> 0 | L37: 今月の未払い額 | M37: =M35-M36 -> 0 | N37: 帳簿上は経費だが現金は出ない
E38: =C38-D38 -> 0 | H38: 経費合計 | I38: =C30 -> 312176.93 | L38: 前月までの未払い累計 | M38: ='1月'!M39 -> 0
E39: =C39-D39 -> 0 | H39: 営業利益 | I39: =I36-I38 -> -312176.93 | L39: 未払い累計（今月末時点） | M39: =M38+M37 -> 0 | N39: 将来支払う必要のある額
E40: =C40-D40 -> 0
E41: =C41-D41 -> 0 | L41: 過去の未払い分 今月支払額 | N41: 未払い累計から取り崩す場合に入力
E42: =C42-D42 -> 0
E43: =C43-D43 -> 0
E44: =C44-D44 -> 0
E45: =C45-D45 -> 0
E46: =C46-D46 -> 0
E47: =C47-D47 -> 0
E48: =C48-D48 -> 0
E49: =C49-D49 -> 0
E50: =C50-D50 -> 0
E51: =C51-D51 -> 0
E52: =C52-D52 -> 0
E53: =C53-D53 -> 0
B54: 一括経費 合計 | C54: =SUM(C34:C53) -> 0 | D54: =SUM(D34:D53) -> 0 | E54: =C54-D54 -> 0
B56: コスト合計（原価＋経費＋一括） | C56: =C16+C30+D54 -> 312176.93
G58: ■ キャッシュフロー（実際のお金の動き）
H59: 項目 | I59: 金額
H60: 営業利益 | I60: =I39 -> -312176.93
H61: ＋ 減価償却費（現金支出なし） | I61: =C29 -> 14433.833 | J61: 損益上の経費だが現金は出ない
H62: 営業CF | I62: =I60+I61+M37-M41 -> -297743.1 | J62: 実際に営業で増えた現金
H64: − 設備投資（一括経費） | I64: =D54 -> 0 | J64: 実際に出ていった現金
H65: 投資CF | I65: =-I64 -> 0 | J65: 設備購入で減った現金
H67: 追加資金（借入・増資等） | I67: =C6
H68: 財務CF | I68: =I67
G70: ■ 口座残高
H71: 前月末 口座残高 | I71: =C5 -> 538130.8
H72: ＋ 営業CF | I72: =I62 -> -297743.1
H73: ＋ 投資CF | I73: =I65 -> 0
H74: ＋ 財務CF | I74: =I68
H75: 期末 口座残高 | I75: =I71+I72+I73+I74 -> 240387.7 | J75: 翌月に繰越
H77: 【参考】損益と現金の差
H78: 帳簿上の利益（営業利益） | I78: =I39 -> -312176.93
H79: 実際の現金増減（CF合計） | I79: =I72+I73+I74 -> -297743.1
H80: 差額（減価償却＋設備投資） | I80: =I79-I78 -> 14433.833 | J80: ＋なら利益より現金が多い
H82: 期末口座（人件費なし） | I82: =I75 -> 240387.7 | J82: 3人の給与を払わない場合
H83: 期末口座（人件費あり） | I83: =I75-M37 -> 240387.7 | J83: 3人に給与を払った場合

Sheet 3月
B1: ☕ カフェ経営管理 ─ 3月 | U1: ■ 計画値（売上計画シートから自動取得）
B2: 月末口座（人件費なし） | C2: =I75 -> -57355.4 | E2: 今月出ていくお金 | F2: =C16+SUM(C20:C23)+SUM(C25:C28)+M36+D54+M41 -> 0 | H2: 今月の利益 | I2: =I39 -> -312176.93 | L2: 来月必要なお金 | M2: 0 | U2: 実績の入力時に参考にしてください。差額・達成率も自動表示。
B3: ■ 資金（期首残高） | G3: ■ 売上（定期収入） | L3: ■ 人件費計算
B4: 科目 | C4: 金額 | D4: 詳細 | E4: メモ | G4: カテゴリ | H4: 金額 | I4: 詳細 | J4: メモ | L4: スタッフ名 | M4: 時給 | N4: 日数 | O4: 時間/日 | P4: 交通費/日 | Q4: 小計（給与） | R4: 小計（交通費） | U4: ■ 売上
B5: 前月繰越金 | C5: ='2月'!I75 -> 240387.7 | G5: ドリンク（コーヒー） | H5: ='3月日次売上'!C35 -> 0 | Q5: =M5*N5*O5 -> 0 | R5: =P5*N5 -> 0 | U5: 項目 | V5: 計画 | W5: 実績 | X5: 差額 | Y5: 達成率
B6: 追加資金（借入等） | G6: ドリンク（紅茶・その他） | H6: ='3月日次売上'!D35 -> 0 | Q6: =M6*N6*O6 -> 0 | R6: =P6*N6 -> 0 | U6: 昼 来客数（季節調整後）/日 | V6: ='売上計画'!N38 -> 25 | W6: =IF(H26=0,"",H24/H26/2) -> 0 | X6: =IF(W6="",0,W6-V6) -> -25 | Y6: =IF(OR(W6="",V6=0),0,W6/V6) -> 0
B7: 期首資金 合計 | C7: =SUM(C5:C6) -> 240387.7 | G7: フード（軽食） | H7: ='3月日次売上'!E35 -> 0 | Q7: =M7*N7*O7 -> 0 | R7: =P7*N7 -> 0 | U7: 夜 来客数（季節調整後）/日 | V7: ='売上計画'!N39 -> 24 | W7: =IF(H26=0,"",H24/H26/2) -> 0 | X7: =IF(W7="",0,W7-V7) -> -24 | Y7: =IF(OR(W7="",V7=0),0,W7/V7) -> 0
G8: フード（スイーツ） | H8: ='3月日次売上'!F35 -> 0 | Q8: =M8*N8*O8 -> 0 | R8: =P8*N8 -> 0 | U8: 売上合計（月間） | V8: ='売上計画'!N45 -> 1997950 | W8: =H20 -> 0 | X8: =W8-V8 -> -1997950 | Y8: =IF(V8=0,0,W8/V8) -> 0
B9: ■ 原価（売上原価） | G9: 物販（コーヒー豆・グッズ） | H9: ='3月日次売上'!G35 -> 0 | Q9: =M9*N9*O9 -> 0 | R9: =P9*N9 -> 0 | U9: 客単価 | V9: =IF((V6*'売上計画'!$C$7+V7*'売上計画'!$C$8)=0,0,V8/(V6*'売上計画'!$C$7+V7*'売上計画'!$C$8)) -> 1359.1497 | W9: =H25 -> 0 | X9: =W9-V9 -> -1359.1497 | Y9: =IF(V9=0,0,W9/V9) -> 0
B10: 科目 | C10: 金額 | D10: 詳細 | E10: メモ | G10: テイクアウト | H10: ='3月日次売上'!H35 -> 0 | Q10: =M10*N10*O10 -> 0 | R10: =P10*N10 -> 0
B11: コーヒー豆・茶葉 | C11: =SUMIFS('freee実績'!$E:$E,'freee実績'!$B:$B,"2027-03",'freee実績'!$C:$C,"仕入高",'freee実績'!$D:$D,"コーヒー豆・茶葉") -> 0 | G11: 売上 合計 | H11: =SUM(H5:H10) -> 0 | Q11: =M11*N11*O11 -> 0 | R11: =P11*N11 -> 0 | U11: ■ 原価・粗利
B12: 牛乳・シロップ等 | C12: =SUMIFS('freee実績'!$E:$E,'freee実績'!$B:$B,"2027-03",'freee実績'!$C:$C,"仕入高",'freee実績'!$D:$D,"牛乳・シロップ等") -> 0 | Q12: =M12*N12*O12 -> 0 | R12: =P12*N12 -> 0 | U12: 項目 | V12: 計画 | W12: 実績 | X12: 差額 | Y12: 原価率
B13: フード材料費 | C13: =SUMIFS('freee実績'!$E:$E,'freee実績'!$B:$B,"2027-03",'freee実績'!$C:$C,"仕入高",'freee実績'!$D:$D,"フード材料費") -> 0 | G13: ■ その他収入（不定期） | L13: アルバイト給与 合計 | Q13: =SUM(Q5:Q12) -> 0 | R13: =SUM(R5:R12) -> 0 | U13: 原価合計 | V13: ='売上計画'!N46 -> 599385 | W13: =C16 -> 0 | X13: =W13-V13 -> -599385 | Y13: =IF(W8=0,0,W13/W8) -> 0
B14: 包装資材・消耗品 | C14: =SUMIFS('freee実績'!$E:$E,'freee実績'!$B:$B,"2027-03",'freee実績'!$C:$C,"仕入高",'freee実績'!$D:$D,"包装資材・消耗品") -> 0 | G14: カテゴリ | H14: 金額 | I14: 詳細 | J14: メモ | U14: 粗利益 | V14: ='売上計画'!N47 -> 1398565 | W14: =H20-C16 -> 0 | X14: =W14-V14 -> -1398565 | Y14: =IF(W8=0,0,W14/W8) -> 0
B15: その他原価 | C15: =SUMIFS('freee実績'!$E:$E,'freee実績'!$B:$B,"2027-03",'freee実績'!$C:$C,"仕入高",'freee実績'!$D:$D,"その他原価") -> 0 | G15: イベント・貸切 | H15: ='3月日次売上'!I35 -> 0 | L15: ■ 固定人件費（役員報酬・社員給与等）
B16: 原価 合計 | C16: =SUM(C11:C15) -> 0 | G16: その他収入② | L16: 項目 | M16: 月額 | R16: 備考 | U16: ■ 経費
G17: その他収入 | L17: 役員報酬 | U17: 項目 | V17: 計画 | W17: 実績 | X17: 差額
B18: ■ 経費（販管費） | G18: その他収入 合計 | H18: =SUM(H15:H17) -> 0 | L18: 社員給与 | U18: 人件費（バイト+固定） | V18: ='売上計画'!N54 -> 46.5 | W18: =C24 -> 297743.1 | X18: =W18-V18 -> 297696.6
B19: 科目 | C19: 金額 | D19: 詳細 | E19: メモ | L19: 社会保険料（会社負担） | U19: 固定費（家賃+光熱+通信+保険） | V19: ='売上計画'!N57 -> 583.5 | W19: =C20+C21+C22+C23 -> 0 | X19: =W19-V19 -> -583.5
B20: 家賃 | C20: =SUMIFS('freee実績'!$E:$E,'freee実績'!$B:$B,"2027-03",'freee実績'!$C:$C,"地代家賃") -> 0 | D20: 固定費 | G20: 売上合計（定期＋不定期） | H20: =H11+H18 -> 0 | L20: その他人件費 | U20: 消耗品 | V20: ='売上計画'!N58 -> 0 | W20: =C25 -> 0 | X20: =W20-V20 -> 0
B21: 水道光熱費 | C21: =SUMIFS('freee実績'!$E:$E,'freee実績'!$B:$B,"2027-03",'freee実績'!$C:$C,"水道光熱費") -> 0 | D21: 固定費 | L21: 固定人件費 合計 | M21: =SUM(M17:M20) -> 0 | U21: 経費合計 | V21: ='売上計画'!N59 -> 0 | W21: =C30 -> 312176.93 | X21: =W21-V21 -> 312176.93
B22: 通信費 | C22: =SUMIFS('freee実績'!$E:$E,'freee実績'!$B:$B,"2027-03",'freee実績'!$C:$C,"通信費") -> 0 | D22: 固定費 | G22: ■ 売上KPI
B23: 保険料 | C23: =SUMIFS('freee実績'!$E:$E,'freee実績'!$B:$B,"2027-03",'freee実績'!$C:$C,"保険料") -> 0 | D23: 固定費 | G23: 指標 | H23: 数値 | J23: 算出方法 | L23: 人件費 総合計 | M23: =Q13+R13+M21 -> 0 | U23: ■ 営業利益
B24: 人件費（給与・社保） | C24: ='役員報酬・社保'!C17+'役員報酬・社保'!D17+'役員報酬・社保'!E17+'役員報酬・社保'!F71+86400 -> 297743.1 | D24: 変動費 | G24: 来客数（人） | H24: ='3月日次売上'!J35 -> 0 | U24: 項目 | V24: 計画 | W24: 実績 | X24: 差額 | Y24: 達成率
B25: 消耗品費 | C25: =SUMIFS('freee実績'!$E:$E,'freee実績'!$B:$B,"2027-03",'freee実績'!$C:$C,"消耗品費") -> 0 | D25: 変動費 | G25: 客単価 | H25: =IF(H24=0,0,H20/H24) -> 0 | J25: 売上÷来客数 | L25: ↑ この金額を左側「人件費（給与・社保）」に転記 | U25: 営業利益 | V25: ='売上計画'!N61 | W25: =I39 -> -312176.93 | X25: =W25-V25 -> -312176.93 | Y25: =IF(V25=0,0,W25/V25) -> 0
B26: 広告宣伝費 | C26: =SUMIFS('freee実績'!$E:$E,'freee実績'!$B:$B,"2027-03",'freee実績'!$C:$C,"広告宣伝費") -> 0 | D26: 変動費 | G26: 営業日数 | H26: 31 | U26: 営業利益率 | V26: ='売上計画'!N62 -> 1038565 | W26: =IF(W8=0,0,W25/W8) -> 0 | X26: =W26-V26 -> -1038565
B27: 修繕費 | C27: =SUMIFS('freee実績'!$E:$E,'freee実績'!$B:$B,"2027-03",'freee実績'!$C:$C,"修繕費") -> 0 | D27: 変動費 | G27: 日商（1日平均売上） | H27: =IF(H26=0,0,H20/H26) -> 0 | J27: 売上÷営業日数 | L27: ■ 人件費KPI
B28: その他経費 | C28: =SUMIFS('freee実績'!$E:$E,'freee実績'!$B:$B,"2027-03",'freee実績'!$C:$C,"雑費") -> 0 | D28: 変動費 | G28: 原価率 | H28: =IF(H20=0,0,C16/H20) -> 0 | J28: 原価÷売上 | L28: 指標 | M28: 数値 | R28: 算出方法
B29: 減価償却費 | C29: ='固定資産台帳'!W26 -> 14433.833 | D29: 帳簿上のみ | L29: 人件費率 | M29: =IF(H20=0,0,M23/H20) -> 0 | R29: 人件費÷売上
B30: 経費 合計 | C30: =SUM(C20:C29) -> 312176.93 | L30: 人時売上高 | M30: =IF((SUM(N5:N12)*SUM(O5:O12))=0,0,H20/(SUM(N5:N12)*SUM(O5:O12))) -> 0 | R30: 売上÷総労働時間
B32: ■ 一括経費（設備投資等） | G32: ■ 月次損益計算 | L32: ■ オーナー人件費 未払い管理
B33: 科目 | C33: 予算 | D33: 実績 | E33: 差額（残） | F33: メモ | H33: 項目 | I33: 金額 | L33: 帳簿上は計上、実際の支払いは利益が出てから
B34: 設備購入 | E34: =C34-D34 -> 0 | H34: 売上高 | I34: =H20 -> 0 | L34: 今月の人件費 支払い？ | M34: 未払い | N34: ← 「支払い」か「未払い」を入力
B35: 内装工事 | E35: =C35-D35 -> 0 | H35: 原価合計 | I35: =C16 -> 0 | L35: 人件費（帳簿計上額） | M35: =M23 -> 0 | N35: P/Lに反映
B36: その他一括経費 | E36: =C36-D36 -> 0 | H36: 粗利益 | I36: =I34-I35 -> 0 | L36: 実際の支払い額 | M36: =IF(M34="支払い",M35,0) -> 0 | N36: 口座から出るお金
E37: =C37-D37 -> 0 | H37: 粗利率 | I37: =IF(I34=0,0,I36/I34) -> 0 | L37: 今月の未払い額 | M37: =M35-M36 -> 0 | N37: 帳簿上は経費だが現金は出ない
E38: =C38-D38 -> 0 | H38: 経費合計 | I38: =C30 -> 312176.93 | L38: 前月までの未払い累計 | M38: ='2月'!M39 -> 0
E39: =C39-D39 -> 0 | H39: 営業利益 | I39: =I36-I38 -> -312176.93 | L39: 未払い累計（今月末時点） | M39: =M38+M37 -> 0 | N39: 将来支払う必要のある額
E40: =C40-D40 -> 0
E41: =C41-D41 -> 0 | L41: 過去の未払い分 今月支払額 | N41: 未払い累計から取り崩す場合に入力
E42: =C42-D42 -> 0
E43: =C43-D43 -> 0
E44: =C44-D44 -> 0
E45: =C45-D45 -> 0
E46: =C46-D46 -> 0
E47: =C47-D47 -> 0
E48: =C48-D48 -> 0
E49: =C49-D49 -> 0
E50: =C50-D50 -> 0
E51: =C51-D51 -> 0
E52: =C52-D52 -> 0
E53: =C53-D53 -> 0
B54: 一括経費 合計 | C54: =SUM(C34:C53) -> 0 | D54: =SUM(D34:D53) -> 0 | E54: =C54-D54 -> 0
B56: コスト合計（原価＋経費＋一括） | C56: =C16+C30+D54 -> 312176.93
G58: ■ キャッシュフロー（実際のお金の動き）
H59: 項目 | I59: 金額
H60: 営業利益 | I60: =I39 -> -312176.93
H61: ＋ 減価償却費（現金支出なし） | I61: =C29 -> 14433.833 | J61: 損益上の経費だが現金は出ない
H62: 営業CF | I62: =I60+I61+M37-M41 -> -297743.1 | J62: 実際に営業で増えた現金
H64: − 設備投資（一括経費） | I64: =D54 -> 0 | J64: 実際に出ていった現金
H65: 投資CF | I65: =-I64 -> 0 | J65: 設備購入で減った現金
H67: 追加資金（借入・増資等） | I67: =C6
H68: 財務CF | I68: =I67
G70: ■ 口座残高
H71: 前月末 口座残高 | I71: =C5 -> 240387.7
H72: ＋ 営業CF | I72: =I62 -> -297743.1
H73: ＋ 投資CF | I73: =I65 -> 0
H74: ＋ 財務CF | I74: =I68
H75: 期末 口座残高 | I75: =I71+I72+I73+I74 -> -57355.4 | J75: 翌月に繰越
H77: 【参考】損益と現金の差
H78: 帳簿上の利益（営業利益） | I78: =I39 -> -312176.93
H79: 実際の現金増減（CF合計） | I79: =I72+I73+I74 -> -297743.1
H80: 差額（減価償却＋設備投資） | I80: =I79-I78 -> 14433.833 | J80: ＋なら利益より現金が多い
H82: 期末口座（人件費なし） | I82: =I75 -> -57355.4 | J82: 3人の給与を払わない場合
H83: 期末口座（人件費あり） | I83: =I75-M37 -> -57355.4 | J83: 3人に給与を払った場合

Sheet 4月日次売上
B1: ☕ 日次売上記録 ─ 4月
B3: 日 | C3: ドリンク（コーヒー） | D3: ドリンク（紅茶・その他） | E3: フード（軽食） | F3: フード（スイーツ） | G3: 物販（コーヒー豆・グッズ） | H3: テイクアウト | I3: イベント・その他 | J3: 来客数 | L3: 日計
B4: 1 | L4: =SUM(C4:I4) -> 0
B5: 2 | L5: =SUM(C5:I5) -> 0
B6: 3 | L6: =SUM(C6:I6) -> 0
B7: 4 | L7: =SUM(C7:I7) -> 0
B8: 5 | L8: =SUM(C8:I8) -> 0
B9: 6 | L9: =SUM(C9:I9) -> 0
B10: 7 | L10: =SUM(C10:I10) -> 0
B11: 8 | L11: =SUM(C11:I11) -> 0
B12: 9 | L12: =SUM(C12:I12) -> 0
B13: 10 | L13: =SUM(C13:I13) -> 0
B14: 11 | L14: =SUM(C14:I14) -> 0
B15: 12 | L15: =SUM(C15:I15) -> 0
... B33: 30 | L33: =SUM(C33:I33) -> 0
B34: 月計 | C34: =SUM(C4:C33) -> 0 | D34: =SUM(D4:D33) -> 0 | E34: =SUM(E4:E33) -> 0 | F34: =SUM(F4:F33) -> 0 | G34: =SUM(G4:G33) -> 0 | H34: =SUM(H4:H33) -> 0 | I34: =SUM(I4:I33) -> 0 | J34: =SUM(J4:J33) -> 0 | L34: =SUM(L4:L33) -> 0
B36: 月次シートへの連携
B37: ドリンク（コーヒー） | C37: =C34 -> 0 | D37: → 4月 H5
B38: ドリンク（紅茶・その他） | C38: =D34 -> 0 | D38: → 4月 H6
B39: フード（軽食） | C39: =E34 -> 0 | D39: → 4月 H7
B40: フード（スイーツ） | C40: =F34 -> 0 | D40: → 4月 H8
B41: 物販 | C41: =G34 -> 0 | D41: → 4月 H9
B42: テイクアウト | C42: =H34 -> 0 | D42: → 4月 H10
B43: イベント・その他 | C43: =I34 -> 0 | D43: → 4月 H15
B44: 来客数合計 | C44: =J34 -> 0 | D44: → 4月 H24

Sheet 5月日次売上
B1: ☕ 日次売上記録 ─ 5月
B3: 日 | C3: ドリンク（コーヒー） | D3: ドリンク（紅茶・その他） | E3: フード（軽食） | F3: フード（スイーツ） | G3: 物販（コーヒー豆・グッズ） | H3: テイクアウト | I3: イベント・その他 | J3: 来客数 | L3: 日計
B4: 1 | L4: =SUM(C4:I4) -> 0
B5: 2 | L5: =SUM(C5:I5) -> 0
B6: 3 | L6: =SUM(C6:I6) -> 0
B7: 4 | L7: =SUM(C7:I7) -> 0
B8: 5 | L8: =SUM(C8:I8) -> 0
B9: 6 | L9: =SUM(C9:I9) -> 0
B10: 7 | L10: =SUM(C10:I10) -> 0
B11: 8 | L11: =SUM(C11:I11) -> 0
B12: 9 | L12: =SUM(C12:I12) -> 0
B13: 10 | L13: =SUM(C13:I13) -> 0
B14: 11 | L14: =SUM(C14:I14) -> 0
B15: 12 | L15: =SUM(C15:I15) -> 0
... B34: 31 | L34: =SUM(C34:I34) -> 0
B35: 月計 | C35: =SUM(C4:C34) -> 0 | D35: =SUM(D4:D34) -> 0 | E35: =SUM(E4:E34) -> 0 | F35: =SUM(F4:F34) -> 0 | G35: =SUM(G4:G34) -> 0 | H35: =SUM(H4:H34) -> 0 | I35: =SUM(I4:I34) -> 0 | J35: =SUM(J4:J34) -> 0 | L35: =SUM(L4:L34) -> 0
B37: 月次シートへの連携
B38: ドリンク（コーヒー） | C38: =C35 -> 0 | D38: → 5月 H5
B39: ドリンク（紅茶・その他） | C39: =D35 -> 0 | D39: → 5月 H6
B40: フード（軽食） | C40: =E35 -> 0 | D40: → 5月 H7
B41: フード（スイーツ） | C41: =F35 -> 0 | D41: → 5月 H8
B42: 物販 | C42: =G35 -> 0 | D42: → 5月 H9
B43: テイクアウト | C43: =H35 -> 0 | D43: → 5月 H10
B44: イベント・その他 | C44: =I35 -> 0 | D44: → 5月 H15
B45: 来客数合計 | C45: =J35 -> 0 | D45: → 5月 H24

Sheet 6月日次売上
B1: ☕ 日次売上記録 ─ 6月
B3: 日 | C3: ドリンク（コーヒー） | D3: ドリンク（紅茶・その他） | E3: フード（軽食） | F3: フード（スイーツ） | G3: 物販（コーヒー豆・グッズ） | H3: テイクアウト | I3: イベント・その他 | J3: 来客数 | L3: 日計
B4: 1 | L4: =SUM(C4:I4) -> 0
B5: 2 | L5: =SUM(C5:I5) -> 0
B6: 3 | L6: =SUM(C6:I6) -> 0
B7: 4 | L7: =SUM(C7:I7) -> 0
B8: 5 | L8: =SUM(C8:I8) -> 0
B9: 6 | L9: =SUM(C9:I9) -> 0
B10: 7 | L10: =SUM(C10:I10) -> 0
B11: 8 | L11: =SUM(C11:I11) -> 0
B12: 9 | L12: =SUM(C12:I12) -> 0
B13: 10 | L13: =SUM(C13:I13) -> 0
B14: 11 | L14: =SUM(C14:I14) -> 0
B15: 12 | L15: =SUM(C15:I15) -> 0
... B33: 30 | L33: =SUM(C33:I33) -> 0
B34: 月計 | C34: =SUM(C4:C33) -> 0 | D34: =SUM(D4:D33) -> 0 | E34: =SUM(E4:E33) -> 0 | F34: =SUM(F4:F33) -> 0 | G34: =SUM(G4:G33) -> 0 | H34: =SUM(H4:H33) -> 0 | I34: =SUM(I4:I33) -> 0 | J34: =SUM(J4:J33) -> 0 | L34: =SUM(L4:L33) -> 0
B36: 月次シートへの連携
B37: ドリンク（コーヒー） | C37: =C34 -> 0 | D37: → 6月 H5
B38: ドリンク（紅茶・その他） | C38: =D34 -> 0 | D38: → 6月 H6
B39: フード（軽食） | C39: =E34 -> 0 | D39: → 6月 H7
B40: フード（スイーツ） | C40: =F34 -> 0 | D40: → 6月 H8
B41: 物販 | C41: =G34 -> 0 | D41: → 6月 H9
B42: テイクアウト | C42: =H34 -> 0 | D42: → 6月 H10
B43: イベント・その他 | C43: =I34 -> 0 | D43: → 6月 H15
B44: 来客数合計 | C44: =J34 -> 0 | D44: → 6月 H24

Sheet 7月日次売上
B1: ☕ 日次売上記録 ─ 7月
B3: 日 | C3: ドリンク（コーヒー） | D3: ドリンク（紅茶・その他） | E3: フード（軽食） | F3: フード（スイーツ） | G3: 物販（コーヒー豆・グッズ） | H3: テイクアウト | I3: イベント・その他 | J3: 来客数 | L3: 日計
B4: 1 | L4: =SUM(C4:I4) -> 0
B5: 2 | L5: =SUM(C5:I5) -> 0
B6: 3 | L6: =SUM(C6:I6) -> 0
B7: 4 | L7: =SUM(C7:I7) -> 0
B8: 5 | L8: =SUM(C8:I8) -> 0
B9: 6 | L9: =SUM(C9:I9) -> 0
B10: 7 | L10: =SUM(C10:I10) -> 0
B11: 8 | L11: =SUM(C11:I11) -> 0
B12: 9 | L12: =SUM(C12:I12) -> 0
B13: 10 | L13: =SUM(C13:I13) -> 0
B14: 11 | L14: =SUM(C14:I14) -> 0
B15: 12 | L15: =SUM(C15:I15) -> 0
... B34: 31 | L34: =SUM(C34:I34) -> 0
B35: 月計 | C35: =SUM(C4:C34) -> 0 | D35: =SUM(D4:D34) -> 0 | E35: =SUM(E4:E34) -> 0 | F35: =SUM(F4:F34) -> 0 | G35: =SUM(G4:G34) -> 0 | H35: =SUM(H4:H34) -> 0 | I35: =SUM(I4:I34) -> 0 | J35: =SUM(J4:J34) -> 0 | L35: =SUM(L4:L34) -> 0
B37: 月次シートへの連携
B38: ドリンク（コーヒー） | C38: =C35 -> 0 | D38: → 7月 H5
B39: ドリンク（紅茶・その他） | C39: =D35 -> 0 | D39: → 7月 H6
B40: フード（軽食） | C40: =E35 -> 0 | D40: → 7月 H7
B41: フード（スイーツ） | C41: =F35 -> 0 | D41: → 7月 H8
B42: 物販 | C42: =G35 -> 0 | D42: → 7月 H9
B43: テイクアウト | C43: =H35 -> 0 | D43: → 7月 H10
B44: イベント・その他 | C44: =I35 -> 0 | D44: → 7月 H15
B45: 来客数合計 | C45: =J35 -> 0 | D45: → 7月 H24

Sheet 8月日次売上
B1: ☕ 日次売上記録 ─ 8月
B3: 日 | C3: ドリンク（コーヒー） | D3: ドリンク（紅茶・その他） | E3: フード（軽食） | F3: フード（スイーツ） | G3: 物販（コーヒー豆・グッズ） | H3: テイクアウト | I3: イベント・その他 | J3: 来客数 | L3: 日計
B4: 1 | L4: =SUM(C4:I4) -> 0
B5: 2 | L5: =SUM(C5:I5) -> 0
B6: 3 | L6: =SUM(C6:I6) -> 0
B7: 4 | L7: =SUM(C7:I7) -> 0
B8: 5 | L8: =SUM(C8:I8) -> 0
B9: 6 | L9: =SUM(C9:I9) -> 0
B10: 7 | L10: =SUM(C10:I10) -> 0
B11: 8 | L11: =SUM(C11:I11) -> 0
B12: 9 | L12: =SUM(C12:I12) -> 0
B13: 10 | L13: =SUM(C13:I13) -> 0
B14: 11 | L14: =SUM(C14:I14) -> 0
B15: 12 | L15: =SUM(C15:I15) -> 0
... B34: 31 | L34: =SUM(C34:I34) -> 0
B35: 月計 | C35: =SUM(C4:C34) -> 0 | D35: =SUM(D4:D34) -> 0 | E35: =SUM(E4:E34) -> 0 | F35: =SUM(F4:F34) -> 0 | G35: =SUM(G4:G34) -> 0 | H35: =SUM(H4:H34) -> 0 | I35: =SUM(I4:I34) -> 0 | J35: =SUM(J4:J34) -> 0 | L35: =SUM(L4:L34) -> 0
B37: 月次シートへの連携
B38: ドリンク（コーヒー） | C38: =C35 -> 0 | D38: → 8月 H5
B39: ドリンク（紅茶・その他） | C39: =D35 -> 0 | D39: → 8月 H6
B40: フード（軽食） | C40: =E35 -> 0 | D40: → 8月 H7
B41: フード（スイーツ） | C41: =F35 -> 0 | D41: → 8月 H8
B42: 物販 | C42: =G35 -> 0 | D42: → 8月 H9
B43: テイクアウト | C43: =H35 -> 0 | D43: → 8月 H10
B44: イベント・その他 | C44: =I35 -> 0 | D44: → 8月 H15
B45: 来客数合計 | C45: =J35 -> 0 | D45: → 8月 H24

Sheet 9月日次売上
B1: ☕ 日次売上記録 ─ 9月
B3: 日 | C3: ドリンク（コーヒー） | D3: ドリンク（紅茶・その他） | E3: フード（軽食） | F3: フード（スイーツ） | G3: 物販（コーヒー豆・グッズ） | H3: テイクアウト | I3: イベント・その他 | J3: 来客数 | L3: 日計
B4: 1 | L4: =SUM(C4:I4) -> 0
B5: 2 | L5: =SUM(C5:I5) -> 0
B6: 3 | L6: =SUM(C6:I6) -> 0
B7: 4 | L7: =SUM(C7:I7) -> 0
B8: 5 | L8: =SUM(C8:I8) -> 0
B9: 6 | L9: =SUM(C9:I9) -> 0
B10: 7 | L10: =SUM(C10:I10) -> 0
B11: 8 | L11: =SUM(C11:I11) -> 0
B12: 9 | L12: =SUM(C12:I12) -> 0
B13: 10 | L13: =SUM(C13:I13) -> 0
B14: 11 | L14: =SUM(C14:I14) -> 0
B15: 12 | L15: =SUM(C15:I15) -> 0
... B33: 30 | L33: =SUM(C33:I33) -> 0
B34: 月計 | C34: =SUM(C4:C33) -> 0 | D34: =SUM(D4:D33) -> 0 | E34: =SUM(E4:E33) -> 0 | F34: =SUM(F4:F33) -> 0 | G34: =SUM(G4:G33) -> 0 | H34: =SUM(H4:H33) -> 0 | I34: =SUM(I4:I33) -> 0 | J34: =SUM(J4:J33) -> 0 | L34: =SUM(L4:L33) -> 0
B36: 月次シートへの連携
B37: ドリンク（コーヒー） | C37: =C34 -> 0 | D37: → 9月 H5
B38: ドリンク（紅茶・その他） | C38: =D34 -> 0 | D38: → 9月 H6
B39: フード（軽食） | C39: =E34 -> 0 | D39: → 9月 H7
B40: フード（スイーツ） | C40: =F34 -> 0 | D40: → 9月 H8
B41: 物販 | C41: =G34 -> 0 | D41: → 9月 H9
B42: テイクアウト | C42: =H34 -> 0 | D42: → 9月 H10
B43: イベント・その他 | C43: =I34 -> 0 | D43: → 9月 H15
B44: 来客数合計 | C44: =J34 -> 0 | D44: → 9月 H24

Sheet 10月日次売上
B1: ☕ 日次売上記録 ─ 10月
B3: 日 | C3: ドリンク（コーヒー） | D3: ドリンク（紅茶・その他） | E3: フード（軽食） | F3: フード（スイーツ） | G3: 物販（コーヒー豆・グッズ） | H3: テイクアウト | I3: イベント・その他 | J3: 来客数 | L3: 日計
B4: 1 | L4: =SUM(C4:I4) -> 0
B5: 2 | L5: =SUM(C5:I5) -> 0
B6: 3 | L6: =SUM(C6:I6) -> 0
B7: 4 | L7: =SUM(C7:I7) -> 0
B8: 5 | L8: =SUM(C8:I8) -> 0
B9: 6 | L9: =SUM(C9:I9) -> 0
B10: 7 | L10: =SUM(C10:I10) -> 0
B11: 8 | L11: =SUM(C11:I11) -> 0
B12: 9 | L12: =SUM(C12:I12) -> 0
B13: 10 | L13: =SUM(C13:I13) -> 0
B14: 11 | L14: =SUM(C14:I14) -> 0
B15: 12 | L15: =SUM(C15:I15) -> 0
... B34: 31 | L34: =SUM(C34:I34) -> 0
B35: 月計 | C35: =SUM(C4:C34) -> 0 | D35: =SUM(D4:D34) -> 0 | E35: =SUM(E4:E34) -> 0 | F35: =SUM(F4:F34) -> 0 | G35: =SUM(G4:G34) -> 0 | H35: =SUM(H4:H34) -> 0 | I35: =SUM(I4:I34) -> 0 | J35: =SUM(J4:J34) -> 0 | L35: =SUM(L4:L34) -> 0
B37: 月次シートへの連携
B38: ドリンク（コーヒー） | C38: =C35 -> 0 | D38: → 10月 H5
B39: ドリンク（紅茶・その他） | C39: =D35 -> 0 | D39: → 10月 H6
B40: フード（軽食） | C40: =E35 -> 0 | D40: → 10月 H7
B41: フード（スイーツ） | C41: =F35 -> 0 | D41: → 10月 H8
B42: 物販 | C42: =G35 -> 0 | D42: → 10月 H9
B43: テイクアウト | C43: =H35 -> 0 | D43: → 10月 H10
B44: イベント・その他 | C44: =I35 -> 0 | D44: → 10月 H15
B45: 来客数合計 | C45: =J35 -> 0 | D45: → 10月 H24

Sheet 11月日次売上
B1: ☕ 日次売上記録 ─ 11月
B3: 日 | C3: ドリンク（コーヒー） | D3: ドリンク（紅茶・その他） | E3: フード（軽食） | F3: フード（スイーツ） | G3: 物販（コーヒー豆・グッズ） | H3: テイクアウト | I3: イベント・その他 | J3: 来客数 | L3: 日計
B4: 1 | L4: =SUM(C4:I4) -> 0
B5: 2 | L5: =SUM(C5:I5) -> 0
B6: 3 | L6: =SUM(C6:I6) -> 0
B7: 4 | L7: =SUM(C7:I7) -> 0
B8: 5 | L8: =SUM(C8:I8) -> 0
B9: 6 | L9: =SUM(C9:I9) -> 0
B10: 7 | L10: =SUM(C10:I10) -> 0
B11: 8 | L11: =SUM(C11:I11) -> 0
B12: 9 | L12: =SUM(C12:I12) -> 0
B13: 10 | L13: =SUM(C13:I13) -> 0
B14: 11 | L14: =SUM(C14:I14) -> 0
B15: 12 | L15: =SUM(C15:I15) -> 0
... B33: 30 | L33: =SUM(C33:I33) -> 0
B34: 月計 | C34: =SUM(C4:C33) -> 0 | D34: =SUM(D4:D33) -> 0 | E34: =SUM(E4:E33) -> 0 | F34: =SUM(F4:F33) -> 0 | G34: =SUM(G4:G33) -> 0 | H34: =SUM(H4:H33) -> 0 | I34: =SUM(I4:I33) -> 0 | J34: =SUM(J4:J33) -> 0 | L34: =SUM(L4:L33) -> 0
B36: 月次シートへの連携
B37: ドリンク（コーヒー） | C37: =C34 -> 0 | D37: → 11月 H5
B38: ドリンク（紅茶・その他） | C38: =D34 -> 0 | D38: → 11月 H6
B39: フード（軽食） | C39: =E34 -> 0 | D39: → 11月 H7
B40: フード（スイーツ） | C40: =F34 -> 0 | D40: → 11月 H8
B41: 物販 | C41: =G34 -> 0 | D41: → 11月 H9
B42: テイクアウト | C42: =H34 -> 0 | D42: → 11月 H10
B43: イベント・その他 | C43: =I34 -> 0 | D43: → 11月 H15
B44: 来客数合計 | C44: =J34 -> 0 | D44: → 11月 H24

Sheet 12月日次売上
B1: ☕ 日次売上記録 ─ 12月
B3: 日 | C3: ドリンク（コーヒー） | D3: ドリンク（紅茶・その他） | E3: フード（軽食） | F3: フード（スイーツ） | G3: 物販（コーヒー豆・グッズ） | H3: テイクアウト | I3: イベント・その他 | J3: 来客数 | L3: 日計
B4: 1 | L4: =SUM(C4:I4) -> 0
B5: 2 | L5: =SUM(C5:I5) -> 0
B6: 3 | L6: =SUM(C6:I6) -> 0
B7: 4 | L7: =SUM(C7:I7) -> 0
B8: 5 | L8: =SUM(C8:I8) -> 0
B9: 6 | L9: =SUM(C9:I9) -> 0
B10: 7 | L10: =SUM(C10:I10) -> 0
B11: 8 | L11: =SUM(C11:I11) -> 0
B12: 9 | L12: =SUM(C12:I12) -> 0
B13: 10 | L13: =SUM(C13:I13) -> 0
B14: 11 | L14: =SUM(C14:I14) -> 0
B15: 12 | L15: =SUM(C15:I15) -> 0
... B34: 31 | L34: =SUM(C34:I34) -> 0
B35: 月計 | C35: =SUM(C4:C34) -> 0 | D35: =SUM(D4:D34) -> 0 | E35: =SUM(E4:E34) -> 0 | F35: =SUM(F4:F34) -> 0 | G35: =SUM(G4:G34) -> 0 | H35: =SUM(H4:H34) -> 0 | I35: =SUM(I4:I34) -> 0 | J35: =SUM(J4:J34) -> 0 | L35: =SUM(L4:L34) -> 0
B37: 月次シートへの連携
B38: ドリンク（コーヒー） | C38: =C35 -> 0 | D38: → 12月 H5
B39: ドリンク（紅茶・その他） | C39: =D35 -> 0 | D39: → 12月 H6
B40: フード（軽食） | C40: =E35 -> 0 | D40: → 12月 H7
B41: フード（スイーツ） | C41: =F35 -> 0 | D41: → 12月 H8
B42: 物販 | C42: =G35 -> 0 | D42: → 12月 H9
B43: テイクアウト | C43: =H35 -> 0 | D43: → 12月 H10
B44: イベント・その他 | C44: =I35 -> 0 | D44: → 12月 H15
B45: 来客数合計 | C45: =J35 -> 0 | D45: → 12月 H24

Sheet 1月日次売上
B1: ☕ 日次売上記録 ─ 1月
B3: 日 | C3: ドリンク（コーヒー） | D3: ドリンク（紅茶・その他） | E3: フード（軽食） | F3: フード（スイーツ） | G3: 物販（コーヒー豆・グッズ） | H3: テイクアウト | I3: イベント・その他 | J3: 来客数 | L3: 日計
B4: 1 | L4: =SUM(C4:I4) -> 0
B5: 2 | L5: =SUM(C5:I5) -> 0
B6: 3 | L6: =SUM(C6:I6) -> 0
B7: 4 | L7: =SUM(C7:I7) -> 0
B8: 5 | L8: =SUM(C8:I8) -> 0
B9: 6 | L9: =SUM(C9:I9) -> 0
B10: 7 | L10: =SUM(C10:I10) -> 0
B11: 8 | L11: =SUM(C11:I11) -> 0
B12: 9 | L12: =SUM(C12:I12) -> 0
B13: 10 | L13: =SUM(C13:I13) -> 0
B14: 11 | L14: =SUM(C14:I14) -> 0
B15: 12 | L15: =SUM(C15:I15) -> 0
... B34: 31 | L34: =SUM(C34:I34) -> 0
B35: 月計 | C35: =SUM(C4:C34) -> 0 | D35: =SUM(D4:D34) -> 0 | E35: =SUM(E4:E34) -> 0 | F35: =SUM(F4:F34) -> 0 | G35: =SUM(G4:G34) -> 0 | H35: =SUM(H4:H34) -> 0 | I35: =SUM(I4:I34) -> 0 | J35: =SUM(J4:J34) -> 0 | L35: =SUM(L4:L34) -> 0
B37: 月次シートへの連携
B38: ドリンク（コーヒー） | C38: =C35 -> 0 | D38: → 1月 H5
B39: ドリンク（紅茶・その他） | C39: =D35 -> 0 | D39: → 1月 H6
B40: フード（軽食） | C40: =E35 -> 0 | D40: → 1月 H7
B41: フード（スイーツ） | C41: =F35 -> 0 | D41: → 1月 H8
B42: 物販 | C42: =G35 -> 0 | D42: → 1月 H9
B43: テイクアウト | C43: =H35 -> 0 | D43: → 1月 H10
B44: イベント・その他 | C44: =I35 -> 0 | D44: → 1月 H15
B45: 来客数合計 | C45: =J35 -> 0 | D45: → 1月 H24

Sheet 2月日次売上
B1: ☕ 日次売上記録 ─ 2月
B3: 日 | C3: ドリンク（コーヒー） | D3: ドリンク（紅茶・その他） | E3: フード（軽食） | F3: フード（スイーツ） | G3: 物販（コーヒー豆・グッズ） | H3: テイクアウト | I3: イベント・その他 | J3: 来客数 | L3: 日計
B4: 1 | L4: =SUM(C4:I4) -> 0
B5: 2 | L5: =SUM(C5:I5) -> 0
B6: 3 | L6: =SUM(C6:I6) -> 0
B7: 4 | L7: =SUM(C7:I7) -> 0
B8: 5 | L8: =SUM(C8:I8) -> 0
B9: 6 | L9: =SUM(C9:I9) -> 0
B10: 7 | L10: =SUM(C10:I10) -> 0
B11: 8 | L11: =SUM(C11:I11) -> 0
B12: 9 | L12: =SUM(C12:I12) -> 0
B13: 10 | L13: =SUM(C13:I13) -> 0
B14: 11 | L14: =SUM(C14:I14) -> 0
B15: 12 | L15: =SUM(C15:I15) -> 0
... B31: 28 | L31: =SUM(C31:I31) -> 0
B32: 月計 | C32: =SUM(C4:C31) -> 0 | D32: =SUM(D4:D31) -> 0 | E32: =SUM(E4:E31) -> 0 | F32: =SUM(F4:F31) -> 0 | G32: =SUM(G4:G31) -> 0 | H32: =SUM(H4:H31) -> 0 | I32: =SUM(I4:I31) -> 0 | J32: =SUM(J4:J31) -> 0 | L32: =SUM(L4:L31) -> 0
B34: 月次シートへの連携
B35: ドリンク（コーヒー） | C35: =C32 -> 0 | D35: → 2月 H5
B36: ドリンク（紅茶・その他） | C36: =D32 -> 0 | D36: → 2月 H6
B37: フード（軽食） | C37: =E32 -> 0 | D37: → 2月 H7
B38: フード（スイーツ） | C38: =F32 -> 0 | D38: → 2月 H8
B39: 物販 | C39: =G32 -> 0 | D39: → 2月 H9
B40: テイクアウト | C40: =H32 -> 0 | D40: → 2月 H10
B41: イベント・その他 | C41: =I32 -> 0 | D41: → 2月 H15
B42: 来客数合計 | C42: =J32 -> 0 | D42: → 2月 H24

Sheet 3月日次売上
B1: ☕ 日次売上記録 ─ 3月
B3: 日 | C3: ドリンク（コーヒー） | D3: ドリンク（紅茶・その他） | E3: フード（軽食） | F3: フード（スイーツ） | G3: 物販（コーヒー豆・グッズ） | H3: テイクアウト | I3: イベント・その他 | J3: 来客数 | L3: 日計
B4: 1 | L4: =SUM(C4:I4) -> 0
B5: 2 | L5: =SUM(C5:I5) -> 0
B6: 3 | L6: =SUM(C6:I6) -> 0
B7: 4 | L7: =SUM(C7:I7) -> 0
B8: 5 | L8: =SUM(C8:I8) -> 0
B9: 6 | L9: =SUM(C9:I9) -> 0
B10: 7 | L10: =SUM(C10:I10) -> 0
B11: 8 | L11: =SUM(C11:I11) -> 0
B12: 9 | L12: =SUM(C12:I12) -> 0
B13: 10 | L13: =SUM(C13:I13) -> 0
B14: 11 | L14: =SUM(C14:I14) -> 0
B15: 12 | L15: =SUM(C15:I15) -> 0
... B34: 31 | L34: =SUM(C34:I34) -> 0
B35: 月計 | C35: =SUM(C4:C34) -> 0 | D35: =SUM(D4:D34) -> 0 | E35: =SUM(E4:E34) -> 0 | F35: =SUM(F4:F34) -> 0 | G35: =SUM(G4:G34) -> 0 | H35: =SUM(H4:H34) -> 0 | I35: =SUM(I4:I34) -> 0 | J35: =SUM(J4:J34) -> 0 | L35: =SUM(L4:L34) -> 0
B37: 月次シートへの連携
B38: ドリンク（コーヒー） | C38: =C35 -> 0 | D38: → 3月 H5
B39: ドリンク（紅茶・その他） | C39: =D35 -> 0 | D39: → 3月 H6
B40: フード（軽食） | C40: =E35 -> 0 | D40: → 3月 H7
B41: フード（スイーツ） | C41: =F35 -> 0 | D41: → 3月 H8
B42: 物販 | C42: =G35 -> 0 | D42: → 3月 H9
B43: テイクアウト | C43: =H35 -> 0 | D43: → 3月 H10
B44: イベント・その他 | C44: =I35 -> 0 | D44: → 3月 H15
B45: 来客数合計 | C45: =J35 -> 0 | D45: → 3月 H24

Sheet 固定資産台帳
B1: ☕ 固定資産台帳 ─ 減価償却自動計算
B2: 青文字セルに入力 → 月額償却費が自動計算 → 各月タブの減価償却費に自動反映
B4: ■ 固定資産一覧 | L4: ■ 月別償却額
B5: 資産名 | C5: カテゴリ | D5: 取得年月 | E5: 取得価額 | F5: 耐用年数 （年） | G5: 残存価額 | H5: 償却方法 | I5: 年間償却額 | J5: 月額償却費 | L5: 4月 | M5: 5月 | N5: 6月 | O5: 7月 | P5: 8月 | Q5: 9月 | R5: 10月 | S5: 11月 | T5: 12月 | U5: 1月 | V5: 2月 | W5: 3月
B6: エスプレッソマシン（La Marzocco） | C6: 機械・備品 | D6: 2026/06 | E6: 500000 | F6: 5 | G6: 0 | H6: 定額法 | I6: =IF(F6=0,0,(E6-G6)/F6) -> 100000 | J6: =IF(I6=0,0,I6/12) -> 8333.3333 | L6: 0 | M6: 0 | N6: =J6 -> 8333.3333 | O6: =J6 -> 8333.3333 | P6: =J6 -> 8333.3333 | Q6: =J6 -> 8333.3333 | R6: =J6 -> 8333.3333 | S6: =J6 -> 8333.3333 | T6: =J6 -> 8333.3333 | U6: =J6 -> 8333.3333 | V6: =J6 -> 8333.3333 | W6: =J6 -> 8333.3333
B7: コーヒーグラインダー（Mazzer） | C7: 機械・備品 | D7: 2026/06 | E7: 70000 | F7: 5 | G7: 0 | H7: 定額法 | I7: =IF(F7=0,0,(E7-G7)/F7) -> 14000 | J7: =IF(I7=0,0,I7/12) -> 1166.6667 | L7: 0 | M7: 0 | N7: =J7 -> 1166.6667 | O7: =J7 -> 1166.6667 | P7: =J7 -> 1166.6667 | Q7: =J7 -> 1166.6667 | R7: =J7 -> 1166.6667 | S7: =J7 -> 1166.6667 | T7: =J7 -> 1166.6667 | U7: =J7 -> 1166.6667 | V7: =J7 -> 1166.6667 | W7: =J7 -> 1166.6667
B8: 製氷機（ダイワ DRI-25LME1） | C8: 機械・備品 | D8: 2026/06 | E8: 82500 | F8: 6 | G8: 0 | H8: 定額法 | I8: =IF(F8=0,0,(E8-G8)/F8) -> 13750 | J8: =IF(I8=0,0,I8/12) -> 1145.8333 | L8: 0 | M8: 0 | N8: =J8 -> 1145.8333 | O8: =J8 -> 1145.8333 | P8: =J8 -> 1145.8333 | Q8: =J8 -> 1145.8333 | R8: =J8 -> 1145.8333 | S8: =J8 -> 1145.8333 | T8: =J8 -> 1145.8333 | U8: =J8 -> 1145.8333 | V8: =J8 -> 1145.8333 | W8: =J8 -> 1145.8333
B9: 業務用冷蔵庫 | C9: 機械・備品 | D9: 2026/06 | E9: 60000 | F9: 6 | G9: 0 | H9: 定額法 | I9: =IF(F9=0,0,(E9-G9)/F9) -> 10000 | J9: =IF(I9=0,0,I9/12) -> 833.33333 | L9: 0 | M9: 0 | N9: =J9 -> 833.33333 | O9: =J9 -> 833.33333 | P9: =J9 -> 833.33333 | Q9: =J9 -> 833.33333 | R9: =J9 -> 833.33333 | S9: =J9 -> 833.33333 | T9: =J9 -> 833.33333 | U9: =J9 -> 833.33333 | V9: =J9 -> 833.33333 | W9: =J9 -> 833.33333
B10: ガス高速オーブン（リンナイ） | C10: 機械・備品 | D10: 2026/06 | E10: 110000 | F10: 5 | G10: 0 | H10: 定額法 | I10: =IF(F10=0,0,(E10-G10)/F10) -> 22000 | J10: =IF(I10=0,0,I10/12) -> 1833.3333 | L10: 0 | M10: 0 | N10: =J10 -> 1833.3333 | O10: =J10 -> 1833.3333 | P10: =J10 -> 1833.3333 | Q10: =J10 -> 1833.3333 | R10: =J10 -> 1833.3333 | S10: =J10 -> 1833.3333 | T10: =J10 -> 1833.3333 | U10: =J10 -> 1833.3333 | V10: =J10 -> 1833.3333 | W10: =J10 -> 1833.3333
B11: 内装工事（壁塗装・床） | C11: 建物付属設備 | D11: 2026/06 | E11: 134560 | F11: 10 | G11: 0 | H11: 定額法 | I11: =IF(F11=0,0,(E11-G11)/F11) -> 13456 | J11: =IF(I11=0,0,I11/12) -> 1121.3333 | L11: 0 | M11: 0 | N11: =J11 -> 1121.3333 | O11: =J11 -> 1121.3333 | P11: =J11 -> 1121.3333 | Q11: =J11 -> 1121.3333 | R11: =J11 -> 1121.3333 | S11: =J11 -> 1121.3333 | T11: =J11 -> 1121.3333 | U11: =J11 -> 1121.3333 | V11: =J11 -> 1121.3333 | W11: =J11 -> 1121.3333
H12: 定額法 | I12: =IF(F12=0,0,(E12-G12)/F12) -> 0 | J12: =IF(I12=0,0,I12/12) -> 0 | L12: 0 | M12: 0 | N12: =J12 -> 0 | O12: =J12 -> 0 | P12: =J12 -> 0 | Q12: =J12 -> 0 | R12: =J12 -> 0 | S12: =J12 -> 0 | T12: =J12 -> 0 | U12: =J12 -> 0 | V12: =J12 -> 0 | W12: =J12 -> 0
H13: 定額法 | I13: =IF(F13=0,0,(E13-G13)/F13) -> 0 | J13: =IF(I13=0,0,I13/12) -> 0 | L13: 0 | M13: 0 | N13: =J13 -> 0 | O13: =J13 -> 0 | P13: =J13 -> 0 | Q13: =J13 -> 0 | R13: =J13 -> 0 | S13: =J13 -> 0 | T13: =J13 -> 0 | U13: =J13 -> 0 | V13: =J13 -> 0 | W13: =J13 -> 0
H14: 定額法 | I14: =IF(F14=0,0,(E14-G14)/F14) -> 0 | J14: =IF(I14=0,0,I14/12) -> 0 | L14: 0 | M14: 0 | N14: =J14 -> 0 | O14: =J14 -> 0 | P14: =J14 -> 0 | Q14: =J14 -> 0 | R14: =J14 -> 0 | S14: =J14 -> 0 | T14: =J14 -> 0 | U14: =J14 -> 0 | V14: =J14 -> 0 | W14: =J14 -> 0
H15: 定額法 | I15: =IF(F15=0,0,(E15-G15)/F15) -> 0 | J15: =IF(I15=0,0,I15/12) -> 0 | L15: 0 | M15: 0 | N15: =J15 -> 0 | O15: =J15 -> 0 | P15: =J15 -> 0 | Q15: =J15 -> 0 | R15: =J15 -> 0 | S15: =J15 -> 0 | T15: =J15 -> 0 | U15: =J15 -> 0 | V15: =J15 -> 0 | W15: =J15 -> 0
H16: 定額法 | I16: =IF(F16=0,0,(E16-G16)/F16) -> 0 | J16: =IF(I16=0,0,I16/12) -> 0 | L16: 0 | M16: 0 | N16: =J16 -> 0 | O16: =J16 -> 0 | P16: =J16 -> 0 | Q16: =J16 -> 0 | R16: =J16 -> 0 | S16: =J16 -> 0 | T16: =J16 -> 0 | U16: =J16 -> 0 | V16: =J16 -> 0 | W16: =J16 -> 0
H17: 定額法 | I17: =IF(F17=0,0,(E17-G17)/F17) -> 0 | J17: =IF(I17=0,0,I17/12) -> 0 | L17: 0 | M17: 0 | N17: =J17 -> 0 | O17: =J17 -> 0 | P17: =J17 -> 0 | Q17: =J17 -> 0 | R17: =J17 -> 0 | S17: =J17 -> 0 | T17: =J17 -> 0 | U17: =J17 -> 0 | V17: =J17 -> 0 | W17: =J17 -> 0
H18: 定額法 | I18: =IF(F18=0,0,(E18-G18)/F18) -> 0 | J18: =IF(I18=0,0,I18/12) -> 0 | L18: 0 | M18: 0 | N18: =J18 -> 0 | O18: =J18 -> 0 | P18: =J18 -> 0 | Q18: =J18 -> 0 | R18: =J18 -> 0 | S18: =J18 -> 0 | T18: =J18 -> 0 | U18: =J18 -> 0 | V18: =J18 -> 0 | W18: =J18 -> 0
H19: 定額法 | I19: =IF(F19=0,0,(E19-G19)/F19) -> 0 | J19: =IF(I19=0,0,I19/12) -> 0 | L19: 0 | M19: 0 | N19: =J19 -> 0 | O19: =J19 -> 0 | P19: =J19 -> 0 | Q19: =J19 -> 0 | R19: =J19 -> 0 | S19: =J19 -> 0 | T19: =J19 -> 0 | U19: =J19 -> 0 | V19: =J19 -> 0 | W19: =J19 -> 0
H20: 定額法 | I20: =IF(F20=0,0,(E20-G20)/F20) -> 0 | J20: =IF(I20=0,0,I20/12) -> 0 | L20: 0 | M20: 0 | N20: =J20 -> 0 | O20: =J20 -> 0 | P20: =J20 -> 0 | Q20: =J20 -> 0 | R20: =J20 -> 0 | S20: =J20 -> 0 | T20: =J20 -> 0 | U20: =J20 -> 0 | V20: =J20 -> 0 | W20: =J20 -> 0
H21: 定額法 | I21: =IF(F21=0,0,(E21-G21)/F21) -> 0 | J21: =IF(I21=0,0,I21/12) -> 0 | L21: 0 | M21: 0 | N21: =J21 -> 0 | O21: =J21 -> 0 | P21: =J21 -> 0 | Q21: =J21 -> 0 | R21: =J21 -> 0 | S21: =J21 -> 0 | T21: =J21 -> 0 | U21: =J21 -> 0 | V21: =J21 -> 0 | W21: =J21 -> 0
H22: 定額法 | I22: =IF(F22=0,0,(E22-G22)/F22) -> 0 | J22: =IF(I22=0,0,I22/12) -> 0 | L22: 0 | M22: 0 | N22: =J22 -> 0 | O22: =J22 -> 0 | P22: =J22 -> 0 | Q22: =J22 -> 0 | R22: =J22 -> 0 | S22: =J22 -> 0 | T22: =J22 -> 0 | U22: =J22 -> 0 | V22: =J22 -> 0 | W22: =J22 -> 0
H23: 定額法 | I23: =IF(F23=0,0,(E23-G23)/F23) -> 0 | J23: =IF(I23=0,0,I23/12) -> 0 | L23: 0 | M23: 0 | N23: =J23 -> 0 | O23: =J23 -> 0 | P23: =J23 -> 0 | Q23: =J23 -> 0 | R23: =J23 -> 0 | S23: =J23 -> 0 | T23: =J23 -> 0 | U23: =J23 -> 0 | V23: =J23 -> 0 | W23: =J23 -> 0
... H25: 定額法 | I25: =IF(F25=0,0,(E25-G25)/F25) -> 0 | J25: =IF(I25=0,0,I25/12) -> 0 | L25: 0 | M25: 0 | N25: =J25 -> 0 | O25: =J25 -> 0 | P25: =J25 -> 0 | Q25: =J25 -> 0 | R25: =J25 -> 0 | S25: =J25 -> 0 | T25: =J25 -> 0 | U25: =J25 -> 0 | V25: =J25 -> 0 | W25: =J25 -> 0
B26: 合計 | E26: =SUM(E6:E25) -> 957060 | I26: =SUM(I6:I25) -> 173206 | J26: =SUM(J6:J25) -> 14433.833 | L26: =SUM(L6:L25) -> 0 | M26: =SUM(M6:M25) -> 0 | N26: =SUM(N6:N25) -> 14433.833 | O26: =SUM(O6:O25) -> 14433.833 | P26: =SUM(P6:P25) -> 14433.833 | Q26: =SUM(Q6:Q25) -> 14433.833 | R26: =SUM(R6:R25) -> 14433.833 | S26: =SUM(S6:S25) -> 14433.833 | ... W26: =SUM(W6:W25) -> 14433.833
B28: ■ 資産サマリー
B29: 固定資産 取得価額合計 | C29: =E26 -> 957060
B30: 年間 減価償却費合計 | C30: =I26 -> 173206
B31: 月額 減価償却費合計 | C31: =J26 -> 14433.833
B33: 【使い方】
B34: ① 資産名・取得価額・耐用年数を入力（青文字セル）
B35: ② 残存価額がある場合は入力（通常は0円 or 取得価額の10%）
B36: ③ 月額が自動計算され、各月タブの「減価償却費」に反映
B38: 【耐用年数の目安（カフェ関連）】
B39: エスプレッソマシン・グラインダー … 5〜6年（機械・備品）
B40: 業務用冷蔵庫・製氷機 … 6年（機械・備品）
B41: 内装工事 … 賃借期間 or 10〜15年（建物付属設備）
B42: POS・レジ・タブレット … 4〜5年（器具・備品）
B43: テーブル・椅子 … 5〜8年（器具・備品）
B44: 看板 … 3〜10年（構築物）
B46: 【注意】
... B50: ・詳細は税理士にご確認ください

Sheet メニュー別原価率
B1: ☕ メニュー別原価率表（flat. 確定メニュー）
B2: Notionの確定メニュー（2026/3/30更新）に基づく
B4: ■ ドリンク（10種＋ミルク変更3種） | I4: ■ 原価率の目安
B5: メニュー名 | C5: 売価 | D5: 原価 | E5: 原価率 | J5: ドリンク | K5: フード | L5: 物販
B6: ドリップコーヒー | C6: 450 | D6: 65 | E6: 0.14 | I6: ◎ 優秀 | J6: 〜25% | K6: 〜25% | L6: 〜40%
B7: カフェラテ（牛乳） | C7: 500 | D7: 100 | E7: 0.2 | I7: ○ 良好 | J7: 25〜35% | K7: 25〜35% | L7: 40〜50%
B8: └ アーモンドミルク変更（+80円） | C8: +80 | D8: +40 | F8: カフェラテに+変更料金 | I8: △ 要改善 | J8: 35〜45% | K8: 35〜45% | L8: 50〜60%
B9: └ オーツミルク変更（+80円） | C9: +80 | D9: +50 | F9: カフェラテに+変更料金 | I9: ✕ 危険 | J9: 45%〜 | K9: 45%〜 | L9: 60%〜
B10: └ 豆乳変更（+50円） | C10: +50 | D10: +10 | F10: カフェラテに+変更料金
B11: アイスアメリカーノ | C11: 450 | D11: 60 | E11: 0.13
B12: エスプレッソ | C12: 400 | D12: 50 | E12: 0.13 | I12: 【原価率改善のヒント】
B13: 抹茶ラテ | C13: 550 | D13: 130 | E13: 0.24 | I13: ・高原価メニューと低原価メニューをセットにする
B14: ティー | C14: 400 | D14: 50 | E14: 0.13 | I14: ・ドリンクは原価率が低いので客単価UPの柱
B15: チャイ | C15: 500 | D15: 80 | E15: 0.16 | I15: ・フードは廃棄ロスも考慮して原価率＋5%で見る
B16: ココア | C16: 500 | D16: 80 | E16: 0.16 | I16: ・季節メニューで食材の安い時期を活用
B17: 牛乳 | C17: 300 | D17: 60 | E17: 0.2 | I17: ・仕入先の見直し（まとめ買い、業務用）
B18: オレンジジュース | C18: 400 | D18: 100 | E18: 0.25
B19: ドリンク平均 | C19: 445 | D19: 78 | E19: 0.17
B21: ■ スイーツ（4種・全て自家製）
B22: メニュー名 | C22: 売価 | D22: 原価 | E22: 原価率
B23: バスクチーズケーキ ★看板 | C23: 480 | D23: 178 | E23: 0.37
B24: バナナクランブルマフィン | C24: 400 | D24: 80 | E24: 0.2
B25: チョコクッキー ★利益貢献 | C25: 300 | D25: 45 | E25: 0.15
B26: 季節のパウンドケーキ | C26: 420 | D26: 90 | E26: 0.21
B27: スイーツ平均 | C27: 400 | D27: 98 | E27: 0.25
B29: ■ セットメニュー
B30: ドリンク＋スイーツ セット | C30: 800
B32: 客単価目標: ¥850（ドリンクのみ3割＋セット5割＋複数注文2割の加重平均）
B33: ※ Notion「📁 04_カフェ運営・R&D」確定メニュー（2026/3/30更新）に基づく
B34: ※ Notion確定メニューには「フード（軽食）」がない（スイーツのみ）。月次・日次の「フード（軽食）」枠は将来メニュー拡張用

Sheet 仕入先・支払管理
B1: ☕ 仕入先・支払管理表
B2: 仕入先ごとの取引条件と支払スケジュールを管理
B4: ■ 仕入先マスタ
B5: 仕入先名 | C5: カテゴリ | D5: 担当者 | E5: 電話番号 | F5: 締め日 | G5: 支払日 | H5: 支払方法 | I5: 月額目安 | J5: 備考
B6: コーヒー豆卸 | C6: コーヒー豆 | F6: 月末 | G6: 翌月末 | H6: 振込
B7: 牛乳配達 | C7: 乳製品 | F7: 月末 | G7: 翌月15日 | H7: 振込
B8: パン卸 | C8: フード材料 | F8: 毎週 | G8: 翌週 | H8: 現金
B9: 製菓材料店 | C9: フード材料 | F9: 月末 | G9: 翌月末 | H9: 振込
B10: 包装資材 | C10: 資材 | F10: 月末 | G10: 翌月末 | H10: 振込
B11: 清掃業者 | C11: 外注 | F11: 月末 | G11: 翌月末 | H11: 振込
B27: ■ 月次支払スケジュール
B28: 支払日 | C28: 仕入先 | D28: 内容 | E28: 金額 | F28: 支払方法 | G28: ステータス | H28: 備考
B49: 支払合計 | E49: =SUM(E29:E48) -> 0

Sheet 予実管理
B1: ☕ 予実管理（予算 vs 実績）
B2: 月次の予算を立てて実績と比較。達成率で進捗を管理します。
D3: （月名を入力してシートを参照） | E3: 対象月： | F3: 4月
B4: ■ 月次予実比較 | H4: ■ 年間 売上予実推移
B5: 項目 | C5: 予算 | D5: 実績 | E5: 差異 | F5: 達成率 | H5: 4月 | I5: 5月 | J5: 6月 | K5: 7月 | L5: 8月 | M5: 9月 | N5: 10月 | O5: 11月 | P5: 12月 | Q5: 1月 | R5: 2月 | S5: 3月
B6: 売上高 | C6: {=INDEX('売上計画'!$C$45:$N$45, 1, MATCH($F$3, '売上計画'!$C$42:$N$42, 0))} -> 0 | D6: {=IFERROR(INDIRECT("'"&$F$3&"'!H20"),0)} -> 0 | E6: =D6-C6 -> 0 | F6: =IF(C6=0,0,D6/C6) -> 0 | G6: 売上予算 | H6: ='売上計画'!C45 -> 0 | I6: ='売上計画'!D45 -> 0 | J6: ='売上計画'!E45 -> 0 | K6: ='売上計画'!F45 -> 0 | L6: ='売上計画'!G45 -> 654100 | M6: ='売上計画'!H45 -> 709500 | N6: ='売上計画'!I45 -> 1091200 | O6: ='売上計画'!J45 -> 1527000 | ... S6: ='売上計画'!N45 -> 1997950
B7: 原価合計 | C7: {=INDEX('売上計画'!$C$46:$N$46, 1, MATCH($F$3, '売上計画'!$C$42:$N$42, 0))} -> 0 | D7: {=IFERROR(INDIRECT("'"&$F$3&"'!C16"),0)} -> 0 | E7: =D7-C7 -> 0 | F7: =IF(C7=0,0,D7/C7) -> 0 | G7: 売上実績 | H7: ='4月'!H20 -> 0 | I7: ='5月'!H20 -> 0 | J7: ='6月'!H20 -> 0 | K7: ='7月'!H20 -> 0 | L7: ='8月'!H20 -> 0 | M7: ='9月'!H20 -> 0 | N7: ='10月'!H20 -> 0 | O7: ='11月'!H20 -> 0 | P7: ='12月'!H20 -> 0 | Q7: ='1月'!H20 -> 0 | R7: ='2月'!H20 -> 0 | S7: ='3月'!H20 -> 0
B8: 粗利益 | C8: =C6-C7 -> 0 | D8: =D6-D7 -> 0 | E8: =D8-C8 -> 0 | F8: =IF(C8=0,0,D8/C8) -> 0 | G8: 達成率 | H8: =IF(H6=0,0,H7/H6) -> 0 | I8: =IF(I6=0,0,I7/I6) -> 0 | J8: =IF(J6=0,0,J7/J6) -> 0 | K8: =IF(K6=0,0,K7/K6) -> 0 | L8: =IF(L6=0,0,L7/L6) -> 0 | M8: =IF(M6=0,0,M7/M6) -> 0 | N8: =IF(N6=0,0,N7/N6) -> 0 | O8: =IF(O6=0,0,O7/O6) -> 0 | ... S8: =IF(S6=0,0,S7/S6) -> 0
B9: 人件費 | C9: {=INDEX('売上計画'!$C$54:$N$54, 1, MATCH($F$3, '売上計画'!$C$42:$N$42, 0))} -> 0 | D9: {=IFERROR(INDIRECT("'"&$F$3&"'!C20"),0)} -> 0 | E9: =D9-C9 -> 0 | F9: =IF(C9=0,0,D9/C9) -> 0
B10: 家賃 | C10: {=INDIRECT("'"&$F$3&"'!C20")} -> 0 | D10: {=IFERROR(INDIRECT("'"&$F$3&"'!C21"),0)} -> 0 | E10: =D10-C10 -> 0 | F10: =IF(C10=0,0,D10/C10) -> 0 | G10: 利益予算 | H10: ='売上計画'!C61 | I10: ='売上計画'!D61 | J10: ='売上計画'!E61 | K10: ='売上計画'!F61 | L10: ='売上計画'!G61 | M10: ='売上計画'!H61 | N10: ='売上計画'!I61 | O10: ='売上計画'!J61 | ... S10: ='売上計画'!N61
B11: 水道光熱費 | C11: {=INDIRECT("'"&$F$3&"'!C21")} -> 0 | D11: {=IFERROR(INDIRECT("'"&$F$3&"'!C22"),0)} -> 0 | E11: =D11-C11 -> 0 | F11: =IF(C11=0,0,D11/C11) -> 0 | G11: 利益実績 | H11: ='4月'!I39 -> 0 | I11: ='5月'!I39 -> 0 | J11: ='6月'!I39 -> -14433.833 | K11: ='7月'!I39 -> -14433.833 | L11: ='8月'!I39 -> -241729.23 | M11: ='9月'!I39 -> -241729.23 | N11: ='10月'!I39 -> -312176.93 | O11: ='11月'!I39 -> -312176.93 | P11: ='12月'!I39 -> -312176.93 | Q11: ='1月'!I39 -> -312176.93 | R11: ='2月'!I39 -> -312176.93 | S11: ='3月'!I39 -> -312176.93
B12: その他経費 | C12: =C13-C9-C10-C11 -> 0 | D12: =D13-D9-D10-D11 -> 0 | E12: =D12-C12 -> 0 | F12: =IF(C12=0,0,D12/C12) -> 0 | G12: 達成率 | H12: =IF(H10=0,0,H11/H10) -> 0 | I12: =IF(I10=0,0,I11/I10) -> 0 | J12: =IF(J10=0,0,J11/J10) -> 0 | K12: =IF(K10=0,0,K11/K10) -> 0 | L12: =IF(L10=0,0,L11/L10) -> 0 | M12: =IF(M10=0,0,M11/M10) -> 0 | N12: =IF(N10=0,0,N11/N10) -> 0 | O12: =IF(O10=0,0,O11/O10) -> 0 | ... S12: =IF(S10=0,0,S11/S10) -> 0
B13: 経費合計 | C13: {=INDEX('売上計画'!$C$59:$N$59, 1, MATCH($F$3, '売上計画'!$C$42:$N$42, 0))} -> 0 | D13: {=IFERROR(INDIRECT("'"&$F$3&"'!C30"),0)} -> 0 | E13: =D13-C13 -> 0 | F13: =IF(C13=0,0,D13/C13) -> 0
B14: 一括経費 | C14: {=INDIRECT("'"&$F$3&"'!C54")} -> 0 | D14: {=IFERROR(INDIRECT("'"&$F$3&"'!C54"),0)} -> 0 | E14: =D14-C14 -> 0 | F14: =IF(C14=0,0,D14/C14) -> 0
B15: 営業利益 | C15: =C8-C13-C14 -> 0 | D15: =D8-D13-D14 -> 0 | E15: =D15-C15 -> 0 | F15: =IF(C15=0,0,D15/C15) -> 0

Sheet 売上計画
B1: ☕ 売上計画（来客数→売上→人件費→利益 自動計算）
B2: 目標来客数を入力するだけで、人件費・利益計画が自動で立てられます
B4: ■ 基本設定
B5: 昼カフェ客単価 | C5: 850 | D5: 9:00-18:00
B6: 夜カフェ客単価 | C6: 1800 | D6: 18:00-24:00（アルコール込み）
B7: 昼 営業日数 ※注: 月次シートH26を参照（自動） | C7: 30 | D7: 月次シート各月!H26の平均（参考表示）
B8: 夜 営業日数 ※注: 月次シートH26を参照（自動） | C8: =C7 -> 30 | D8: 昼夜同じ日数で運営する想定
B9: 原材料費率 | C9: 0.3
B10: 時給 | C10: 1200
B11: 昼の営業時間 | C11: 9 | D11: h（9:00-18:00）
B12: 夜の営業時間 | C12: 6 | D12: h（18:00-24:00）
B14: ■ 来客数→必要人員テーブル（昼）
B15: 来客数/日 | C15: 必要人員 | E15: 考え方
B16: 0〜15人 | C16: 1 | E16: ワンオペ
B17: 16〜30人 | C17: 1.5 | E17: 1人フル + 1人ハーフ
B18: 31〜40人 | C18: 2 | E18: 2人フル
B19: 41人〜 | C19: 2.5 | E19: 2人フル + 1人ハーフ
B20: ■ 来客数→必要人員テーブル（夜）
B21: 来客数/日 | C21: 必要人員 | E21: 考え方
B22: 0〜10人 | C22: 1 | E22: ワンオペ
B23: 11〜20人 | C23: 1.5 | E23: 1人フル + 1人ハーフ
B24: 21〜25人 | C24: 2 | E24: 2人フル
B25: 26人〜 | C25: 2.5 | E25: 2人フル + 1人ハーフ
B27: ■ 目標来客数（人/日）を入力
C28: 4月 | D28: 5月 | E28: 6月 | F28: 7月 | G28: 8月 | H28: 9月 | I28: 10月 | J28: 11月 | K28: 12月 | L28: 1月 | M28: 2月 | N28: 3月 | O28: 平均
B29: 🟢 楽観（昼） | C29: 0 | D29: 0 | E29: 0 | F29: 0 | G29: 10 | H29: 14 | I29: 18 | J29: 22 | K29: 26 | L29: 30 | M29: 32 | N29: 32 | O29: =IFERROR(AVERAGEIF(C28:N28,">0"),0) -> 0
B30: 🟡 標準（昼） | C30: 0 | D30: 0 | E30: 0 | F30: 0 | G30: 8 | H30: 11 | I30: 14 | J30: 17 | K30: 20 | L30: 23 | M30: 25 | N30: 25 | O30: =IFERROR(AVERAGEIF(C29:N29,">0"),0) -> 23
B31: 🔴 保守（昼） | C31: 0 | D31: 0 | E31: 0 | F31: 0 | G31: 6 | H31: 8 | I31: 10 | J31: 12 | K31: 14 | L31: 16 | M31: 18 | N31: 18 | O31: =IFERROR(AVERAGEIF(C30:N30,">0"),0) -> 17.875
B32: ★ 昼カフェ目標 | C32: 0 | D32: 0 | E32: 0 | F32: 0 | G32: 8 | H32: 11 | I32: 14 | J32: 17 | K32: 20 | L32: 23 | M32: 25 | N32: 25 | O32: =IFERROR(AVERAGEIF(C31:N31,">0"),0) -> 12.75
B33: 🟢 楽観（夜） | C33: 0 | D33: 0 | E33: 0 | F33: 0 | G33: 6 | H33: 9 | I33: 13 | J33: 16 | K33: 20 | L33: 22 | M33: 26 | N33: 26 | O33: =IFERROR(AVERAGEIF(C32:N32,">0"),0) -> 17.875
B34: 🟡 標準（夜） | C34: 0 | D34: 0 | E34: 0 | F34: 0 | G34: 5 | H34: 7 | I34: 10 | J34: 12 | K34: 15 | L34: 17 | M34: 20 | N34: 20 | O34: =IFERROR(AVERAGEIF(C33:N33,">0"),0) -> 17.25
B35: 🔴 保守（夜） | C35: 0 | D35: 0 | E35: 0 | F35: 0 | G35: 4 | H35: 5 | I35: 7 | J35: 8 | K35: 10 | L35: 12 | M35: 14 | N35: 14 | O35: =IFERROR(AVERAGEIF(C34:N34,">0"),0) -> 13.25
B36: ★ 夜カフェ目標 | C36: 0 | D36: 0 | E36: 0 | F36: 0 | G36: 5 | H36: 7 | I36: 10 | J36: 12 | K36: 15 | L36: 17 | M36: 20 | N36: 20 | O36: =IFERROR(AVERAGEIF(C35:N35,">0"),0) -> 9.25
B37: ↓ 上の目標 × 季節変動係数 = 調整後の来客目標 ↓
B38: ★ 昼 季節調整済み目標 | C38: =ROUND(C32*C98,0) -> 0 | D38: =ROUND(D32*D98,0) -> 0 | E38: =ROUND(E32*E98,0) -> 0 | F38: =ROUND(F32*F98,0) -> 0 | G38: =ROUND(G32*G98,0) -> 10 | H38: =ROUND(H32*H98,0) -> 13 | I38: =ROUND(I32*I98,0) -> 16 | J38: =ROUND(J32*J98,0) -> 26 | ... N38: =ROUND(N32*N98,0) -> 25 | O38: =IFERROR(AVERAGEIF(C38:N38,">0"),0) -> 16.875
B39: ★ 夜 季節調整済み目標 | C39: =ROUND(C36*C99,0) -> 0 | D39: =ROUND(D36*D99,0) -> 0 | E39: =ROUND(E36*E99,0) -> 0 | F39: =ROUND(F36*F99,0) -> 0 | G39: =ROUND(G36*G99,0) -> 7 | H39: =ROUND(H36*H99,0) -> 7 | I39: =ROUND(I36*I99,0) -> 12 | J39: =ROUND(J36*J99,0) -> 16 | ... N39: =ROUND(N36*N99,0) -> 24 | O39: =IFERROR(AVERAGEIF(C39:N39,">0"),0) -> 14.5
B40: 月間来客数（昼+夜）= 1日あたり×営業日数 | C40: =(C38+C39)*'4月'!H26 -> 0 | D40: =(D38+D39)*'5月'!H26 -> 0 | E40: =(E38+E39)*'6月'!H26 -> 0 | F40: =(F38+F39)*'7月'!H26 -> 0 | G40: =(G38+G39)*'8月'!H26 -> 527 | H40: =(H38+H39)*'9月'!H26 -> 600 | I40: =(I38+I39)*'10月'!H26 -> 868 | J40: =(J38+J39)*'11月'!H26 -> 1260 | K40: =(K38+K39)*'12月'!H26 -> 1240 | L40: =(L38+L39)*'1月'!H26 -> 837 | M40: =(M38+M39)*'2月'!H26 -> 784 | N40: =(N38+N39)*'3月'!H26 -> 1519 | O40: =SUM(C40:N40) -> 7635
B41: ■ 売上計画（自動計算）
C42: 4月 | D42: 5月 | E42: 6月 | F42: 7月 | G42: 8月 | H42: 9月 | I42: 10月 | J42: 11月 | K42: 12月 | L42: 1月 | M42: 2月 | N42: 3月 | O42: 年間合計
B43: 昼カフェ売上 | C43: =C38*$C$5*'4月'!H26 -> 0 | D43: =D38*$C$5*'5月'!H26 -> 0 | E43: =E38*$C$5*'6月'!H26 -> 0 | F43: =F38*$C$5*'7月'!H26 -> 0 | G43: =G38*$C$5*'8月'!H26 -> 263500 | H43: =H38*$C$5*'9月'!H26 -> 331500 | I43: =I38*$C$5*'10月'!H26 -> 421600 | J43: =J38*$C$5*'11月'!H26 -> 663000 | K43: =K38*$C$5*'12月'!H26 -> 447950 | L43: =L38*$C$5*'1月'!H26 -> 368900 | M43: =M38*$C$5*'2月'!H26 -> 333200 | N43: =N38*$C$5*'3月'!H26 -> 658750 | O43: =SUM(C43:N43) -> 3488400
B44: 夜カフェ売上 | C44: =C39*$C$6*'4月'!H26 -> 0 | D44: =D39*$C$6*'5月'!H26 -> 0 | E44: =E39*$C$6*'6月'!H26 -> 0 | F44: =F39*$C$6*'7月'!H26 -> 0 | G44: =G39*$C$6*'8月'!H26 -> 390600 | H44: =H39*$C$6*'9月'!H26 -> 378000 | I44: =I39*$C$6*'10月'!H26 -> 669600 | J44: =J39*$C$6*'11月'!H26 -> 864000 | K44: =K39*$C$6*'12月'!H26 -> 1283400 | L44: =L39*$C$6*'1月'!H26 -> 725400 | M44: =M39*$C$6*'2月'!H26 -> 705600 | N44: =N39*$C$6*'3月'!H26 -> 1339200 | O44: =SUM(C44:N44) -> 6355800
B45: 売上合計 | C45: =C43+C44 -> 0 | D45: =D43+D44 -> 0 | E45: =E43+E44 -> 0 | F45: =F43+F44 -> 0 | G45: =G43+G44 -> 654100 | H45: =H43+H44 -> 709500 | I45: =I43+I44 -> 1091200 | J45: =J43+J44 -> 1527000 | ... N45: =N43+N44 -> 1997950 | O45: =SUM(C45:N45) -> 9844200
B46: 原価（30%） | C46: =C45*$C$9 -> 0 | D46: =D45*$C$9 -> 0 | E46: =E45*$C$9 -> 0 | F46: =F45*$C$9 -> 0 | G46: =G45*$C$9 -> 196230 | H46: =H45*$C$9 -> 212850 | I46: =I45*$C$9 -> 327360 | J46: =J45*$C$9 -> 458100 | ... N46: =N45*$C$9 -> 599385 | O46: =SUM(C46:N46) -> 2953260
B47: 粗利益 | C47: =C45-C46 -> 0 | D47: =D45-D46 -> 0 | E47: =E45-E46 -> 0 | F47: =F45-F46 -> 0 | G47: =G45-G46 -> 457870 | H47: =H45-H46 -> 496650 | I47: =I45-I46 -> 763840 | J47: =J45-J46 -> 1068900 | ... N47: =N45-N46 -> 1398565 | O47: =SUM(C47:N47) -> 6890940
B48: ■ 人件費計画（アルバイトのみ、オーナー労働分は人件費にカウントしない）
B49: スタッフ（昼）必要人員/日 | C49: 0 | D49: 0 | E49: 0 | F49: 0 | G49: 1.5 | H49: 1.5 | I49: 1.5 | J49: 2 | K49: 2 | L49: 2 | M49: 2 | N49: 2 | O49: =AVERAGE(C49:N49) -> 1.2083333
B50: スタッフ（夜）必要人員/日 | C50: 0 | D50: 0 | E50: 0 | F50: 0 | G50: 1.5 | H50: 1.5 | I50: 1.5 | J50: 1.5 | K50: 1.5 | L50: 1.5 | M50: 1.5 | N50: 1.5 | O50: =AVERAGE(C50:N50) -> 1
B51: 必要総労働時間（昼） | C51: =C49*$C$11*'4月'!H26 -> 0 | D51: =D49*$C$11*'5月'!H26 -> 0 | E51: =E49*$C$11*'6月'!H26 -> 0 | F51: =F49*$C$11*'7月'!H26 -> 0 | G51: =G49*$C$11*'8月'!H26 -> 418.5 | H51: =H49*$C$11*'9月'!H26 -> 405 | I51: =I49*$C$11*'10月'!H26 -> 418.5 | J51: =J49*$C$11*'11月'!H26 -> 540 | K51: =K49*$C$11*'12月'!H26 -> 558 | L51: =L49*$C$11*'1月'!H26 -> 558 | M51: =M49*$C$11*'2月'!H26 -> 504 | N51: =N49*$C$11*'3月'!H26 -> 558 | O51: =SUM(C51:N51) -> 3960
B52: 必要総労働時間（夜） | C52: =C50*$C$12*'4月'!H26 -> 0 | D52: =D50*$C$12*'5月'!H26 -> 0 | E52: =E50*$C$12*'6月'!H26 -> 0 | F52: =F50*$C$12*'7月'!H26 -> 0 | G52: =G50*$C$12*'8月'!H26 -> 279 | H52: =H50*$C$12*'9月'!H26 -> 270 | I52: =I50*$C$12*'10月'!H26 -> 279 | J52: =J50*$C$12*'11月'!H26 -> 270 | K52: =K50*$C$12*'12月'!H26 -> 279 | L52: =L50*$C$12*'1月'!H26 -> 279 | M52: =M50*$C$12*'2月'!H26 -> 252 | N52: =N50*$C$12*'3月'!H26 -> 279 | O52: =SUM(C52:N52) -> 2187
B53: 営業時間外労働時間/日（仕込み・締めなど） | C53: 0 | D53: 0 | E53: 0 | F53: 0 | G53: 1.5 | H53: 1.5 | I53: 1.5 | J53: 1.5 | K53: 1.5 | L53: 1.5 | M53: 1.5 | N53: 1.5 | O53: =AVERAGE(C53:N53) -> 1
B54: 営業時間外労働時間 合計/月 | C54: =C53*'4月'!H26 -> 0 | D54: =D53*'5月'!H26 -> 0 | E54: =E53*'6月'!H26 -> 0 | F54: =F53*'7月'!H26 -> 0 | G54: =G53*'8月'!H26 -> 46.5 | H54: =H53*'9月'!H26 -> 45 | I54: =I53*'10月'!H26 -> 46.5 | J54: =J53*'11月'!H26 -> 45 | K54: =K53*'12月'!H26 -> 46.5 | L54: =L53*'1月'!H26 -> 46.5 | M54: =M53*'2月'!H26 -> 42 | N54: =N53*'3月'!H26 -> 46.5 | O54: =SUM(C54:N54) -> 364.5
B55: アルバイトに働いてもらう時間 | C55: 0 | D55: 0 | E55: 0 | F55: 0 | G55: 100 | H55: 150 | I55: 200 | J55: 250 | K55: 300 | L55: 300 | M55: 300 | N55: 300 | O55: =SUM(C55:N55) -> 1900
B56: 人件費（アルバイト分のみ） | C56: =C55*$C$10 -> 0 | D56: =D55*$C$10 -> 0 | E56: =E55*$C$10 -> 0 | F56: =F55*$C$10 -> 0 | G56: =G55*$C$10 -> 120000 | H56: =H55*$C$10 -> 180000 | I56: =I55*$C$10 -> 240000 | J56: =J55*$C$10 -> 300000 | ... N56: =N55*$C$10 -> 360000 | O56: =SUM(C56:N56) -> 2280000
B57: （参考）オーナーがカバーする時間 | C57: =MAX(0,C51+C52+C54-C55) -> 0 | D57: =MAX(0,D51+D52+D54-D55) -> 0 | E57: =MAX(0,E51+E52+E54-E55) -> 0 | F57: =MAX(0,F51+F52+F54-F55) -> 0 | G57: =MAX(0,G51+G52+G54-G55) -> 644 | H57: =MAX(0,H51+H52+H54-H55) -> 570 | I57: =MAX(0,I51+I52+I54-I55) -> 544 | J57: =MAX(0,J51+J52+J54-J55) -> 605 | ... N57: =MAX(0,N51+N52+N54-N55) -> 583.5 | O57: =SUM(C57:N57) -> 4611.5
B58: 固定費（家賃+光熱+通信+保険） | C58: ='4月'!C20+'4月'!C21+'4月'!C22+'4月'!C23 -> 0 | D58: ='5月'!C20+'5月'!C21+'5月'!C22+'5月'!C23 -> 0 | E58: ='6月'!C20+'6月'!C21+'6月'!C22+'6月'!C23 -> 0 | F58: ='7月'!C20+'7月'!C21+'7月'!C22+'7月'!C23 -> 0 | G58: ='8月'!C20+'8月'!C21+'8月'!C22+'8月'!C23 -> 0 | H58: ='9月'!C20+'9月'!C21+'9月'!C22+'9月'!C23 -> 0 | I58: ='10月'!C20+'10月'!C21+'10月'!C22+'10月'!C23 -> 0 | J58: ='11月'!C20+'11月'!C21+'11月'!C22+'11月'!C23 -> 0 | K58: ='12月'!C20+'12月'!C21+'12月'!C22+'12月'!C23 -> 0 | L58: ='1月'!C20+'1月'!C21+'1月'!C22+'1月'!C23 -> 0 | M58: ='2月'!C20+'2月'!C21+'2月'!C22+'2月'!C23 -> 0 | N58: ='3月'!C20+'3月'!C21+'3月'!C22+'3月'!C23 -> 0 | O58: =SUM(C58:N58) -> 0
B59: 消耗品 | C59: ='4月'!C25 -> 0 | D59: ='5月'!C25 -> 0 | E59: ='6月'!C25 -> 0 | F59: ='7月'!C25 -> 0 | G59: ='8月'!C25 -> 0 | H59: ='9月'!C25 -> 0 | I59: ='10月'!C25 -> 0 | J59: ='11月'!C25 -> 0 | K59: ='12月'!C25 -> 0 | L59: ='1月'!C25 -> 0 | M59: ='2月'!C25 -> 0 | N59: ='3月'!C25 -> 0 | O59: =SUM(C59:N59) -> 0
B60: 経費合計（人件費+固定費+消耗品） | C60: =C56+C58+C59 -> 0 | D60: =D56+D58+D59 -> 0 | E60: =E56+E58+E59 -> 0 | F60: =F56+F58+F59 -> 0 | G60: =G56+G58+G59 -> 120000 | H60: =H56+H58+H59 -> 180000 | I60: =I56+I58+I59 -> 240000 | J60: =J56+J58+J59 -> 300000 | ... N60: =N56+N58+N59 -> 360000 | O60: =SUM(C60:N60) -> 2280000
B62: 営業利益（粗利益 − 経費合計） | C62: =C47-C60 -> 0 | D62: =D47-D60 -> 0 | E62: =E47-E60 -> 0 | F62: =F47-F60 -> 0 | G62: =G47-G60 -> 337870 | H62: =H47-H60 -> 316650 | I62: =I47-I60 -> 523840 | J62: =J47-J60 -> 768900 | ... N62: =N47-N60 -> 1038565 | O62: =SUM(C62:N62) -> 4610940
B63: 営業利益率 | C63: =IF(C45=0,0,C62/C45) -> 0 | D63: =IF(D45=0,0,D62/D45) -> 0 | E63: =IF(E45=0,0,E62/E45) -> 0 | F63: =IF(F45=0,0,F62/F45) -> 0 | G63: =IF(G45=0,0,G62/G45) -> 0.51654181 | H63: =IF(H45=0,0,H62/H45) -> 0.44630021 | I63: =IF(I45=0,0,I62/I45) -> 0.48005865 | J63: =IF(J45=0,0,J62/J45) -> 0.50353635 | ... O63: =IF(O45=0,0,O62/O45) -> 0.46839154
B75: ■ 月末口座残高（4-9月=月次シート実績、10月以降=計画ベースで自動算出）
B76: 項目 | C76: 4月 | D76: 5月 | E76: 6月 | F76: 7月 | G76: 8月 | H76: 9月 | I76: 10月 | J76: 11月 | K76: 12月 | L76: 1月 | M76: 2月 | N76: 3月
B77: 営業利益（R62、参考） | C77: =C62 -> 0 | D77: =D62 -> 0 | E77: =E62 -> 0 | F77: =F62 -> 0 | G77: =G62 -> 337870 | H77: =H62 -> 316650 | I77: =I62 -> 523840 | J77: =J62 -> 768900 | ... N77: =N62 -> 1038565
B78: 役員報酬＋社保（参考、月次固定支出） | C78: 0 | D78: 0 | E78: 0 | F78: 0 | G78: =('役員報酬・社保'!$C$17+'役員報酬・社保'!$D$17+'役員報酬・社保'!$E$17+'役員報酬・社保'!$F$71) -> 211343.1 | H78: =('役員報酬・社保'!$C$17+'役員報酬・社保'!$D$17+'役員報酬・社保'!$E$17+'役員報酬・社保'!$F$71) -> 211343.1 | I78: =('役員報酬・社保'!$C$17+'役員報酬・社保'!$D$17+'役員報酬・社保'!$E$17+'役員報酬・社保'!$F$71) -> 211343.1 | J78: =('役員報酬・社保'!$C$17+'役員報酬・社保'!$D$17+'役員報酬・社保'!$E$17+'役員報酬・社保'!$F$71) -> 211343.1 | K78: =('役員報酬・社保'!$C$17+'役員報酬・社保'!$D$17+'役員報酬・社保'!$E$17+'役員報酬・社保'!$F$71) -> 211343.1 | L78: =('役員報酬・社保'!$C$17+'役員報酬・社保'!$D$17+'役員報酬・社保'!$E$17+'役員報酬・社保'!$F$71) -> 211343.1 | M78: =('役員報酬・社保'!$C$17+'役員報酬・社保'!$D$17+'役員報酬・社保'!$E$17+'役員報酬・社保'!$F$71) -> 211343.1 | N78: =('役員報酬・社保'!$C$17+'役員報酬・社保'!$D$17+'役員報酬・社保'!$E$17+'役員報酬・社保'!$F$71) -> 211343.1
B79: 一括経費（参考、設備投資など） | C79: ='4月'!D54 -> 0 | D79: ='5月'!D54 -> 114000 | E79: ='6月'!D54 -> 1946388 | F79: ='7月'!D54 -> 455918 | G79: ='8月'!D54 -> 2800000 | H79: ='9月'!D54 -> 0 | I79: ='10月'!D54 -> 0 | J79: ='11月'!D54 -> 0 | K79: ='12月'!D54 -> 0 | L79: ='1月'!D54 -> 0 | M79: ='2月'!D54 -> 0 | N79: ='3月'!D54 -> 0
B80: 【月末口座残高】 | C80: ='4月'!I75 -> 0 | D80: ='5月'!I75 -> 2886000 | E80: ='6月'!I75 -> 939612 | F80: ='7月'!I75 -> 3983694 | G80: =F80+G77-G78-G79 -> 1310220.9 | H80: =G80+H77-H78-H79 -> 1415527.8 | I80: =H80+I77-I78-I79 -> 1728024.7 | J80: =I80+J77-J78-J79 -> 2285581.6 | K80: =J80+K77-K78-K79 -> 2926183.5 | L80: =K80+L77-L78-L79 -> 3120850.4 | M80: =L80+M77-M78-M79 -> 3276667.3 | N80: =M80+N77-N78-N79 -> 4103889.2
B81: ※ 4-9月（緑）: 月次シートI75の実績値 / 10-3月（橙）: 前月末 + 営業利益 − 役員報酬 − 社保 − 一括経費
B82: ※ 役員報酬＋社保: 月173,750円（坂本50,000+櫻井20,000+町田50,000=120,000＋社保会社負担25,343）
B83: ※ 10月以降の数字を変えたい場合: R62 営業利益を見直すか、R77-R79の月次値を直接修正
B91: ③ 102行: バイト給与を入力 → 追加の人件費として口座から出る
B92: ④ 115行: 口座残高が自動計算。色で経営状態がわかる（🔴<1倍 / 🟡<2.5倍 / 🟢≥6倍）
B93: ■ 役員報酬・社保の使い方
B94: ⑤ 役員報酬は「役員報酬・社保」シートで月額を設定 → R165-180で月次展開
B95: ⑥ C167 で開始月を切替（開業月8月=5、6月なら3）
B96: ⑦ C168 で「未払い」を選ぶと口座から出ない（帳簿上は経費計上）
B97: ⑧ 未払い運用時、役員報酬未払い累計は R182 に表示される | C97: 4月 | D97: 5月 | E97: 6月 | F97: 7月 | G97: 8月 | H97: 9月 | I97: 10月 | J97: 11月 | K97: 12月 | L97: 1月 | M97: 2月 | N97: 3月 | O97: 平均
B98: ⑨ 社保は帳簿上は発生ベースだが、実務上は未払いにすれば納付も翌月以降にズラせる（税理士相談） | C98: 1.7 | D98: 1.45 | E98: 0.85 | F98: 0.8 | G98: 1.3 | H98: 1.2 | I98: 1.15 | J98: 1.55 | K98: 0.85 | L98: 0.6 | M98: 0.55 | N98: 1 | O98: =IFERROR(AVERAGEIF(C98:N98,">0"),0) -> 1.0833333
B99: ⑩ R103-105（出資額返済）も未払いで運用可。1年目は返済ゼロが現実的 | C99: 1.25 | D99: 1.15 | E99: 0.9 | F99: 1.1 | G99: 1.4 | H99: 1.05 | I99: 1.2 | J99: 1.3 | K99: 1.5 | L99: 0.75 | M99: 0.7 | N99: 1.2 | O99: =IFERROR(AVERAGEIF(C99:N99,">0"),0) -> 1.125
B100: ⑪ 法人税試算 R183-188: 1年目赤字なら法人税ゼロ、10年繰越可 | C100: 桜まつり＋新学期 | D100: GW＋好気候 | E100: 梅雨・観光客減 | F100: 猛暑・鳥人間 | G100: お盆・花火・夏休み | H100: 5連休(2026)・行楽 | I100: 秋の行楽・修学旅行 | J100: 紅葉ライトアップ | K100: 忘年会・クリスマス | L100: 積雪・閑散期 | M100: ニッパチ・年間最低 | N100: 桜前・歓送迎会
B101: 昼カフェの根拠 | C101: 彦根城4月入場87,420人(年間最大)。桜まつり+新学期+新歓。キャッスルロード回遊ピーク | D101: GW需要。彦根城69,308人。にぎわい市(~5/6)。好気候で散策客多い | E101: 梅雨入り。彦根城37,496人(4月の43%)。テラス席利用不可。地元住民のルーチン利用のみ | F101: 猛暑(最高32℃超)。彦根城33,854人(年間最低級)。学生試験期間→勉強利用(低単価) | G101: お盆帰省+夏休み観光客。彦根城62,333人。8/22彦根花火。避暑需要でカフェ利用増 | H101: 2026年は5連休(シルバーウィーク)。彦根城43,683人。秋の行楽開始 | I101: 紅葉前の行楽。彦根城58,076人。修学旅行シーズン。学生の課外活動再開(10月新学期) | J101: 紅葉ライトアップ。彦根城74,524人(第2ピーク)。11/21-23の3連休と重なる | K101: 冬の冷え込みで昼の散策客減。彦根城44,781人。中旬以降の急激な冷え込み | L101: 積雪(月平均36cm・雪日数17.6日)。彦根城34,456人。学生試験→帰省。物理的に来店困難 | M101: ニッパチ。彦根城33,261人(年間最少)。積雪+学生春休み+観光客ゼロの三重苦 | N101: 下旬から桜まつり開始(3/28~)。彦根城57,063人。歓送迎会シーズン開始
B102: 夜カフェの根拠 | C102: 新歓・サークル需要。夜桜ライトアップで夕方以降の人出が増える | D102: GWの夜間外出。気候が良く夜カフェ日和。学生のGW集まり | E102: 梅雨でも夜は影響少なめ。ただし学生の外出意欲がやや低下 | F102: 鳥人間コンテスト(7月下旬)の宿泊客。夏の夜の外出需要。学生試験打ち上げ | G102: 8/22彦根花火→年間最大スパイク。お盆の帰省客の夜の集まり。ただし学生は夏休みで不在 | H102: 5連休の夜間レジャー。ただし学生はまだ夏休み(9月末まで) | I102: 学生の新学期(10月)→サークル・ゼミの飲み会再開。秋のイベント後の夜利用 | J102: 紅葉ライトアップ拝観後の来店。3連休の夜の観光客利用 | K102: 忘年会・クリスマス需要(夜カフェ年間最大)。年末の仕事納め後の利用 | L102: 積雪で夜間外出を極端に控える。正月三が日のみ多賀大社参拝客がわずかに来る程度 | M102: 積雪+極寒で夜間外出ほぼなし。学生不在(春休み)。年間最低 | N102: 歓送迎会の二次会・三次会需要。学生の卒業パーティー。桜まつりの夜桜ライトアップ開始
B103: 彦根城入場者数 | C103: 87420 | D103: 69308 | E103: 37496 | F103: 33854 | G103: 62333 | H103: 43683 | I103: 58076 | J103: 74524 | K103: 44781 | L103: 34456 | M103: 33261 | N103: 57063 | O103: =SUM(C99:N99) -> 13.5
B107: ※ 係数を1.0にすると季節調整なし（ベース目標がそのまま使われます）
B108: ※ データソース: 彦根城入場者統計、日本フードサービス協会、気象庁彦根平年値、滋賀大学学事暦
B115: ■ 役員報酬＋社会保険（月次発生、役員報酬・社保シートから自動連動）
B116: 営業開始月を切り替えられます。開業前（4-5月）は役員報酬なしでも可
B117: 役員報酬 開始月（1=4月, 3=6月, 5=8月など） | C117: 5 | D117: ← 数字を変えると、その月から役員報酬・社保が計上される
B118: ※ 役員報酬は毎月計上＆口座流出（定期同額給与のため）
C119: 4月 | D119: 5月 | E119: 6月 | F119: 7月 | G119: 8月 | H119: 9月 | I119: 10月 | J119: 11月 | K119: 12月 | L119: 1月 | M119: 2月 | N119: 3月 | O119: 年間合計
B120: 月番号 | C120: 1 | D120: 2 | E120: 3 | F120: 4 | G120: 5 | H120: 6 | I120: 7 | J120: 8 | K120: 9 | L120: 10 | M120: 11 | N120: 12
B121: 坂本 役員報酬 | C121: =IF(C120>=$C$117,'役員報酬・社保'!C17,0) -> 0 | D121: =IF(D120>=$C$117,'役員報酬・社保'!C17,0) -> 0 | E121: =IF(E120>=$C$117,'役員報酬・社保'!C17,0) -> 0 | F121: =IF(F120>=$C$117,'役員報酬・社保'!C17,0) -> 0 | G121: =IF(G120>=$C$117,'役員報酬・社保'!C17,0) -> 62000 | H121: =IF(H120>=$C$117,'役員報酬・社保'!C17,0) -> 62000 | I121: =IF(I120>=$C$117,'役員報酬・社保'!C17,0) -> 62000 | J121: =IF(J120>=$C$117,'役員報酬・社保'!C17,0) -> 62000 | K121: =IF(K120>=$C$117,'役員報酬・社保'!C17,0) -> 62000 | L121: =IF(L120>=$C$117,'役員報酬・社保'!C17,0) -> 62000 | M121: =IF(M120>=$C$117,'役員報酬・社保'!C17,0) -> 62000 | N121: =IF(N120>=$C$117,'役員報酬・社保'!C17,0) -> 62000 | O121: =SUM(C121:N121) -> 496000
B122: 櫻井 役員報酬 | C122: =IF(C120>=7,'役員報酬・社保'!D17,0) -> 0 | D122: =IF(D120>=7,'役員報酬・社保'!D17,0) -> 0 | E122: =IF(E120>=7,'役員報酬・社保'!D17,0) -> 0 | F122: =IF(F120>=7,'役員報酬・社保'!D17,0) -> 0 | G122: =IF(G120>=7,'役員報酬・社保'!D17,0) -> 0 | H122: =IF(H120>=7,'役員報酬・社保'!D17,0) -> 0 | I122: =IF(I120>=7,'役員報酬・社保'!D17,0) -> 62000 | J122: =IF(J120>=7,'役員報酬・社保'!D17,0) -> 62000 | K122: =IF(K120>=7,'役員報酬・社保'!D17,0) -> 62000 | L122: =IF(L120>=7,'役員報酬・社保'!D17,0) -> 62000 | M122: =IF(M120>=7,'役員報酬・社保'!D17,0) -> 62000 | N122: =IF(N120>=7,'役員報酬・社保'!D17,0) -> 62000 | O122: =SUM(C122:N122) -> 372000
B123: 町田 役員報酬 | C123: =IF(C120>=$C$117,'役員報酬・社保'!E17,0) -> 0 | D123: =IF(D120>=$C$117,'役員報酬・社保'!E17,0) -> 0 | E123: =IF(E120>=$C$117,'役員報酬・社保'!E17,0) -> 0 | F123: =IF(F120>=$C$117,'役員報酬・社保'!E17,0) -> 0 | G123: =IF(G120>=$C$117,'役員報酬・社保'!E17,0) -> 62000 | H123: =IF(H120>=$C$117,'役員報酬・社保'!E17,0) -> 62000 | I123: =IF(I120>=$C$117,'役員報酬・社保'!E17,0) -> 62000 | J123: =IF(J120>=$C$117,'役員報酬・社保'!E17,0) -> 62000 | K123: =IF(K120>=$C$117,'役員報酬・社保'!E17,0) -> 62000 | L123: =IF(L120>=$C$117,'役員報酬・社保'!E17,0) -> 62000 | M123: =IF(M120>=$C$117,'役員報酬・社保'!E17,0) -> 62000 | N123: =IF(N120>=$C$117,'役員報酬・社保'!E17,0) -> 62000 | O123: =SUM(C123:N123) -> 496000
B124: 役員報酬 合計 | C124: =SUM(C121:C123) -> 0 | D124: =SUM(D121:D123) -> 0 | E124: =SUM(E121:E123) -> 0 | F124: =SUM(F121:F123) -> 0 | G124: =SUM(G121:G123) -> 124000 | H124: =SUM(H121:H123) -> 124000 | I124: =SUM(I121:I123) -> 186000 | J124: =SUM(J121:J123) -> 186000 | ... N124: =SUM(N121:N123) -> 186000 | O124: =SUM(C124:N124) -> 1364000
B126: 社保 会社負担 合計 | C126: =IF(C120>=$C$117,'役員報酬・社保'!C71+'役員報酬・社保'!E71,0)+IF(C120>=7,'役員報酬・社保'!D71,0) -> 0 | D126: =IF(D120>=$C$117,'役員報酬・社保'!C71+'役員報酬・社保'!E71,0)+IF(D120>=7,'役員報酬・社保'!D71,0) -> 0 | E126: =IF(E120>=$C$117,'役員報酬・社保'!C71+'役員報酬・社保'!E71,0)+IF(E120>=7,'役員報酬・社保'!D71,0) -> 0 | F126: =IF(F120>=$C$117,'役員報酬・社保'!C71+'役員報酬・社保'!E71,0)+IF(F120>=7,'役員報酬・社保'!D71,0) -> 0 | G126: =IF(G120>=$C$117,'役員報酬・社保'!C71+'役員報酬・社保'!E71,0)+IF(G120>=7,'役員報酬・社保'!D71,0) -> 16895.4 | H126: =IF(H120>=$C$117,'役員報酬・社保'!C71+'役員報酬・社保'!E71,0)+IF(H120>=7,'役員報酬・社保'!D71,0) -> 16895.4 | I126: =IF(I120>=$C$117,'役員報酬・社保'!C71+'役員報酬・社保'!E71,0)+IF(I120>=7,'役員報酬・社保'!D71,0) -> 25343.1 | J126: =IF(J120>=$C$117,'役員報酬・社保'!C71+'役員報酬・社保'!E71,0)+IF(J120>=7,'役員報酬・社保'!D71,0) -> 25343.1 | K126: =IF(K120>=$C$117,'役員報酬・社保'!C71+'役員報酬・社保'!E71,0)+IF(K120>=7,'役員報酬・社保'!D71,0) -> 25343.1 | L126: =IF(L120>=$C$117,'役員報酬・社保'!C71+'役員報酬・社保'!E71,0)+IF(L120>=7,'役員報酬・社保'!D71,0) -> 25343.1 | M126: =IF(M120>=$C$117,'役員報酬・社保'!C71+'役員報酬・社保'!E71,0)+IF(M120>=7,'役員報酬・社保'!D71,0) -> 25343.1 | N126: =IF(N120>=$C$117,'役員報酬・社保'!C71+'役員報酬・社保'!E71,0)+IF(N120>=7,'役員報酬・社保'!D71,0) -> 25343.1 | O126: =SUM(C126:N126) -> 185849.4
B127: 賞与（事前確定届出給与）※3月支給想定 | C127: 0 | D127: 0 | E127: 0 | F127: 0 | G127: 0 | H127: 0 | I127: 0 | J127: 0 | K127: 0 | L127: 0 | M127: 0 | N127: ='役員報酬・社保'!C21+'役員報酬・社保'!D21+'役員報酬・社保'!E21 -> 0 | O127: =SUM(C127:N127) -> 0
B128: 賞与の社保 会社負担 | C128: 0 | D128: 0 | E128: 0 | F128: 0 | G128: 0 | H128: 0 | I128: 0 | J128: 0 | K128: 0 | L128: 0 | M128: 0 | N128: ='役員報酬・社保'!C78+'役員報酬・社保'!D78+'役員報酬・社保'!E78 -> 0 | O128: =SUM(C128:N128) -> 0
B130: 【会社負担】役員報酬＋社保＋賞与＋経費＋業務委託 | C130: =C124+C126+C127+C128+C147+C148 -> 0 | D130: =D124+D126+D127+D128+D147+D148 -> 0 | E130: =E124+E126+E127+E128+E147+E148 -> 0 | F130: =F124+F126+F127+F128+F147+F148 -> 0 | G130: =G124+G126+G127+G128+G147+G148 -> 227295.4 | H130: =H124+H126+H127+H128+H147+H148 -> 227295.4 | I130: =I124+I126+I127+I128+I147+I148 -> 297743.1 | J130: =J124+J126+J127+J128+J147+J148 -> 297743.1 | ... N130: =N124+N126+N127+N128+N147+N148 -> 297743.1 | O130: =SUM(C130:N130) -> 2241049.4
B131: 役員報酬 未払い額（今月分） | C131: =IF($C$118="未払い",C124+C126+C127+C128,0) -> 0 | D131: =IF($C$118="未払い",D124+D126+D127+D128,0) -> 0 | E131: =IF($C$118="未払い",E124+E126+E127+E128,0) -> 0 | F131: =IF($C$118="未払い",F124+F126+F127+F128,0) -> 0 | G131: =IF($C$118="未払い",G124+G126+G127+G128,0) -> 0 | H131: =IF($C$118="未払い",H124+H126+H127+H128,0) -> 0 | I131: =IF($C$118="未払い",I124+I126+I127+I128,0) -> 0 | J131: =IF($C$118="未払い",J124+J126+J127+J128,0) -> 0 | ... N131: =IF($C$118="未払い",N124+N126+N127+N128,0) -> 0 | O131: =SUM(C131:N131) -> 0
B132: 役員報酬 未払い累計 | C132: =C131 -> 0 | D132: =C132+D131 -> 0 | E132: =D132+E131 -> 0 | F132: =E132+F131 -> 0 | G132: =F132+G131 -> 0 | H132: =G132+H131 -> 0 | I132: =H132+I131 -> 0 | J132: =I132+J131 -> 0 | K132: =J132+K131 -> 0 | ... N132: =M132+N131 -> 0 | O132: =N132 -> 0
B133: ■ 法人税 ざっくり試算
...

Sheet 月次レポート
B1: ☕ 月次経営レポート（自動集計）
B2: 各月タブから自動で数値を取得。月末に確認するだけでOK
B4: ■ 売上・利益推移
B5: 項目 | C5: 4月 | D5: 5月 | E5: 6月 | F5: 7月 | G5: 8月 | H5: 9月 | I5: 10月 | J5: 11月 | K5: 12月 | L5: 1月 | M5: 2月 | N5: 3月
B6: 売上高 | C6: ='4月'!H20 -> 0 | D6: ='5月'!H20 -> 0 | E6: ='6月'!H20 -> 0 | F6: ='7月'!H20 -> 0 | G6: ='8月'!H20 -> 0 | H6: ='9月'!H20 -> 0 | I6: ='10月'!H20 -> 0 | J6: ='11月'!H20 -> 0 | K6: ='12月'!H20 -> 0 | L6: ='1月'!H20 -> 0 | M6: ='2月'!H20 -> 0 | N6: ='3月'!H20 -> 0
B7: 原価 | C7: ='4月'!C16 -> 0 | D7: ='5月'!C16 -> 0 | E7: ='6月'!C16 -> 0 | F7: ='7月'!C16 -> 0 | G7: ='8月'!C16 -> 0 | H7: ='9月'!C16 -> 0 | I7: ='10月'!C16 -> 0 | J7: ='11月'!C16 -> 0 | K7: ='12月'!C16 -> 0 | L7: ='1月'!C16 -> 0 | M7: ='2月'!C16 -> 0 | N7: ='3月'!C16 -> 0
B8: 粗利益 | C8: =C6-C7 -> 0 | D8: =D6-D7 -> 0 | E8: =E6-E7 -> 0 | F8: =F6-F7 -> 0 | G8: =G6-G7 -> 0 | H8: =H6-H7 -> 0 | I8: =I6-I7 -> 0 | J8: =J6-J7 -> 0 | ... N8: =N6-N7 -> 0
B9: 粗利率 | C9: =IF(C6=0,0,C8/C6) -> 0 | D9: =IF(D6=0,0,D8/D6) -> 0 | E9: =IF(E6=0,0,E8/E6) -> 0 | F9: =IF(F6=0,0,F8/F6) -> 0 | G9: =IF(G6=0,0,G8/G6) -> 0 | H9: =IF(H6=0,0,H8/H6) -> 0 | I9: =IF(I6=0,0,I8/I6) -> 0 | J9: =IF(J6=0,0,J8/J6) -> 0 | ... N9: =IF(N6=0,0,N8/N6) -> 0
B10: 経費（実キャッシュ） | C10: ='4月'!C30-'4月'!C29 -> 0 | D10: ='5月'!C30-'5月'!C29 -> 0 | E10: ='6月'!C30-'6月'!C29 -> 0 | F10: ='7月'!C30-'7月'!C29 -> 0 | G10: ='8月'!C30-'8月'!C29 -> 227295.4 | H10: ='9月'!C30-'9月'!C29 -> 227295.4 | I10: ='10月'!C30-'10月'!C29 -> 297743.1 | J10: ='11月'!C30-'11月'!C29 -> 297743.1 | K10: ='12月'!C30-'12月'!C29 -> 297743.1 | L10: ='1月'!C30-'1月'!C29 -> 297743.1 | M10: ='2月'!C30-'2月'!C29 -> 297743.1 | N10: ='3月'!C30-'3月'!C29 -> 297743.1
B11: 減価償却費 | C11: ='4月'!C29 -> 0 | D11: ='5月'!C29 -> 0 | E11: ='6月'!C29 -> 14433.833 | F11: ='7月'!C29 -> 14433.833 | G11: ='8月'!C29 -> 14433.833 | H11: ='9月'!C29 -> 14433.833 | I11: ='10月'!C29 -> 14433.833 | J11: ='11月'!C29 -> 14433.833 | K11: ='12月'!C29 -> 14433.833 | L11: ='1月'!C29 -> 14433.833 | M11: ='2月'!C29 -> 14433.833 | N11: ='3月'!C29 -> 14433.833
B12: 一括経費（実績） | C12: ='4月'!D54 -> 0 | D12: ='5月'!D54 -> 114000 | E12: ='6月'!D54 -> 1946388 | F12: ='7月'!D54 -> 455918 | G12: ='8月'!D54 -> 2800000 | H12: ='9月'!D54 -> 0 | I12: ='10月'!D54 -> 0 | J12: ='11月'!D54 -> 0 | K12: ='12月'!D54 -> 0 | L12: ='1月'!D54 -> 0 | M12: ='2月'!D54 -> 0 | N12: ='3月'!D54 -> 0
B13: 営業利益 | C13: ='4月'!I39 -> 0 | D13: ='5月'!I39 -> 0 | E13: ='6月'!I39 -> -14433.833 | F13: ='7月'!I39 -> -14433.833 | G13: ='8月'!I39 -> -241729.23 | H13: ='9月'!I39 -> -241729.23 | I13: ='10月'!I39 -> -312176.93 | J13: ='11月'!I39 -> -312176.93 | K13: ='12月'!I39 -> -312176.93 | L13: ='1月'!I39 -> -312176.93 | M13: ='2月'!I39 -> -312176.93 | N13: ='3月'!I39 -> -312176.93
B14: 営業利益率 | C14: =IF(C6=0,0,C13/C6) -> 0 | D14: =IF(D6=0,0,D13/D6) -> 0 | E14: =IF(E6=0,0,E13/E6) -> 0 | F14: =IF(F6=0,0,F13/F6) -> 0 | G14: =IF(G6=0,0,G13/G6) -> 0 | H14: =IF(H6=0,0,H13/H6) -> 0 | I14: =IF(I6=0,0,I13/I6) -> 0 | J14: =IF(J6=0,0,J13/J6) -> 0 | ... N14: =IF(N6=0,0,N13/N6) -> 0
B17: ■ キャッシュフロー推移
B18: 項目 | C18: 4月 | D18: 5月 | E18: 6月 | F18: 7月 | G18: 8月 | H18: 9月 | I18: 10月 | J18: 11月 | K18: 12月 | L18: 1月 | M18: 2月 | N18: 3月
B19: 営業CF | C19: ='4月'!I62 -> 0 | D19: ='5月'!I62 -> 0 | E19: ='6月'!I62 -> 0 | F19: ='7月'!I62 -> 0 | G19: ='8月'!I62 -> -227295.4 | H19: ='9月'!I62 -> -227295.4 | I19: ='10月'!I62 -> -297743.1 | J19: ='11月'!I62 -> -297743.1 | K19: ='12月'!I62 -> -297743.1 | L19: ='1月'!I62 -> -297743.1 | M19: ='2月'!I62 -> -297743.1 | N19: ='3月'!I62 -> -297743.1
B20: 投資CF | C20: ='4月'!I65 -> 0 | D20: ='5月'!I65 -> -114000 | E20: ='6月'!I65 -> -1946388 | F20: ='7月'!I65 -> -455918 | G20: ='8月'!I65 -> -2800000 | H20: ='9月'!I65 -> 0 | I20: ='10月'!I65 -> 0 | J20: ='11月'!I65 -> 0 | K20: ='12月'!I65 -> 0 | L20: ='1月'!I65 -> 0 | M20: ='2月'!I65 -> 0 | N20: ='3月'!I65 -> 0
B21: 財務CF | C21: ='4月'!I68 | D21: ='5月'!I68 | E21: ='6月'!I68 | F21: ='7月'!I68 -> 3500000 | G21: ='8月'!I68 | H21: ='9月'!I68 -> 1000000 | I21: ='10月'!I68 | J21: ='11月'!I68 | K21: ='12月'!I68 | L21: ='1月'!I68 | M21: ='2月'!I68 | N21: ='3月'!I68
B22: 期末口座残高 | C22: ='4月'!I75 -> 0 | D22: ='5月'!I75 -> 2886000 | E22: ='6月'!I75 -> 939612 | F22: ='7月'!I75 -> 3983694 | G22: ='8月'!I75 -> 956398.6 | H22: ='9月'!I75 -> 1729103.2 | I22: ='10月'!I75 -> 1431360.1 | J22: ='11月'!I75 -> 1133617 | K22: ='12月'!I75 -> 835873.9 | L22: ='1月'!I75 -> 538130.8 | M22: ='2月'!I75 -> 240387.7 | N22: ='3月'!I75 -> -57355.4
B25: ■ KPI推移
B26: 項目 | C26: 4月 | D26: 5月 | E26: 6月 | F26: 7月 | G26: 8月 | H26: 9月 | I26: 10月 | J26: 11月 | K26: 12月 | L26: 1月 | M26: 2月 | N26: 3月
B27: 来客数（人） | C27: ='4月'!H24 -> 0 | D27: ='5月'!H24 -> 0 | E27: ='6月'!H24 -> 0 | F27: ='7月'!H24 -> 0 | G27: ='8月'!H24 -> 0 | H27: ='9月'!H24 -> 0 | I27: ='10月'!H24 -> 0 | J27: ='11月'!H24 -> 0 | K27: ='12月'!H24 -> 0 | L27: ='1月'!H24 -> 0 | M27: ='2月'!H24 -> 0 | N27: ='3月'!H24 -> 0
B28: 客単価 | C28: ='4月'!H25 -> 0 | D28: ='5月'!H25 -> 0 | E28: ='6月'!H25 -> 0 | F28: ='7月'!H25 -> 0 | G28: ='8月'!H25 -> 0 | H28: ='9月'!H25 -> 0 | I28: ='10月'!H25 -> 0 | J28: ='11月'!H25 -> 0 | K28: ='12月'!H25 -> 0 | L28: ='1月'!H25 -> 0 | M28: ='2月'!H25 -> 0 | N28: ='3月'!H25 -> 0
B29: 営業日数 | C29: ='4月'!H26 -> 0 | D29: ='5月'!H26 -> 0 | E29: ='6月'!H26 -> 0 | F29: ='7月'!H26 -> 0 | G29: ='8月'!H26 -> 31 | H29: ='9月'!H26 -> 30 | I29: ='10月'!H26 -> 31 | J29: ='11月'!H26 -> 30 | K29: ='12月'!H26 -> 31 | L29: ='1月'!H26 -> 31 | M29: ='2月'!H26 -> 28 | N29: ='3月'!H26 -> 31
B30: 日商 | C30: ='4月'!H27 -> 0 | D30: ='5月'!H27 -> 0 | E30: ='6月'!H27 -> 0 | F30: ='7月'!H27 -> 0 | G30: ='8月'!H27 -> 0 | H30: ='9月'!H27 -> 0 | I30: ='10月'!H27 -> 0 | J30: ='11月'!H27 -> 0 | K30: ='12月'!H27 -> 0 | L30: ='1月'!H27 -> 0 | M30: ='2月'!H27 -> 0 | N30: ='3月'!H27 -> 0
B31: 原価率 | C31: ='4月'!H28 -> 0 | D31: ='5月'!H28 -> 0 | E31: ='6月'!H28 -> 0 | F31: ='7月'!H28 -> 0 | G31: ='8月'!H28 -> 0 | H31: ='9月'!H28 -> 0 | I31: ='10月'!H28 -> 0 | J31: ='11月'!H28 -> 0 | K31: ='12月'!H28 -> 0 | L31: ='1月'!H28 -> 0 | M31: ='2月'!H28 -> 0 | N31: ='3月'!H28 -> 0
B32: 今月出ていくお金 | C32: ='4月'!C16+SUM('4月'!C20:C28)+'4月'!D54 -> 0 | D32: ='5月'!C16+SUM('5月'!C20:C28)+'5月'!D54 -> 114000 | E32: ='6月'!C16+SUM('6月'!C20:C28)+'6月'!D54 -> 1946388 | F32: ='7月'!C16+SUM('7月'!C20:C28)+'7月'!D54 -> 455918 | G32: ='8月'!C16+SUM('8月'!C20:C28)+'8月'!D54 -> 3027295.4 | H32: ='9月'!C16+SUM('9月'!C20:C28)+'9月'!D54 -> 227295.4 | I32: ='10月'!C16+SUM('10月'!C20:C28)+'10月'!D54 -> 297743.1 | J32: ='11月'!C16+SUM('11月'!C20:C28)+'11月'!D54 -> 297743.1 | K32: ='12月'!C16+SUM('12月'!C20:C28)+'12月'!D54 -> 297743.1 | L32: ='1月'!C16+SUM('1月'!C20:C28)+'1月'!D54 -> 297743.1 | M32: ='2月'!C16+SUM('2月'!C20:C28)+'2月'!D54 -> 297743.1 | N32: ='3月'!C16+SUM('3月'!C20:C28)+'3月'!D54 -> 297743.1
B33: 人件費 | C33: ='4月'!C24 -> 0 | D33: ='5月'!C24 -> 0 | E33: ='6月'!C24 -> 0 | F33: ='7月'!C24 | G33: ='8月'!C24 -> 227295.4 | H33: ='9月'!C24 -> 227295.4 | I33: ='10月'!C24 -> 297743.1 | J33: ='11月'!C24 -> 297743.1 | K33: ='12月'!C24 -> 297743.1 | L33: ='1月'!C24 -> 297743.1 | M33: ='2月'!C24 -> 297743.1 | N33: ='3月'!C24 -> 297743.1
B34: 人件費率 | C34: =IF(C27=0,0,C33/C27) -> 0 | D34: =IF(D27=0,0,D33/D27) -> 0 | E34: =IF(E27=0,0,E33/E27) -> 0 | F34: =IF(F27=0,0,F33/F27) -> 0 | G34: =IF(G27=0,0,G33/G27) -> 0 | H34: =IF(H27=0,0,H33/H27) -> 0 | I34: =IF(I27=0,0,I33/I27) -> 0 | J34: =IF(J27=0,0,J33/J27) -> 0 | ... N34: =IF(N27=0,0,N33/N27) -> 0
B37: ■ 前月比（売上）
B38: 項目 | C38: 4月 | D38: 5月 | E38: 6月 | F38: 7月 | G38: 8月 | H38: 9月 | I38: 10月 | J38: 11月 | K38: 12月 | L38: 1月 | M38: 2月 | N38: 3月
B39: 売上 前月比 | C39: 0 | D39: =D6-C6 -> 0 | E39: =E6-D6 -> 0 | F39: =F6-E6 -> 0 | G39: =G6-F6 -> 0 | H39: =H6-G6 -> 0 | I39: =I6-H6 -> 0 | J39: =J6-I6 -> 0 | K39: =K6-J6 -> 0 | ... N39: =N6-M6 -> 0
B40: 口座残高 前月比 | C40: 0 | D40: =D22-C22 -> 2886000 | E40: =E22-D22 -> -1946388 | F40: =F22-E22 -> 3044082 | G40: =G22-F22 -> -3027295.4 | H40: =H22-G22 -> 772704.6 | I40: =I22-H22 -> -297743.1 | J40: =J22-I22 -> -297743.1 | K40: =K22-J22 -> -297743.1 | ... N40: =N22-M22 -> -297743.1

Sheet 損益分岐点
B1: ☕ 損益分岐点分析
B2: 「何杯売れば黒字か」「1日いくら売れば赤字にならないか」を計算
B4: ■ 基本情報（月次） | F4: ■ 損益分岐点（結果）
B5: 項目 | C5: 金額 | D5: 入力方法 | F5: 指標 | G5: 数値 | H5: 算出方法
B6: 客単価 | C6: =IF('売上計画'!O40=0,1175,'売上計画'!O45/'売上計画'!O40) -> 1289.3517 | D6: 手入力 or 年間サマリーから | F6: 月間 損益分岐売上 | G6: =IF(C8=0,0,C9/(1-C8)) -> 20684.851 | H6: 固定費÷（1−原価率）
B7: ドリンク比率 | C7: 0.7 | D7: 売上に占めるドリンクの割合 | F7: 日次 損益分岐売上 | G7: =IF(C10=0,0,G6/C10) -> 689.49504 | H7: 月間BEP÷営業日数
B8: 平均原価率 | C8: ='売上計画'!$C$9 -> 0.3 | D8: メニュー別原価率を参考に | F8: 日次 必要客数 | G8: =IF(C6=0,0,G7/C6) -> 0.53476104 | H8: 日次BEP÷客単価
B9: 月間固定費 | C9: =C21 -> 14479.396 | D9: 下の固定費合計を参照 | F9: 月間 必要客数 | G9: =IF(C6=0,0,G6/C6) -> 16.042831 | H9: 日次客数×営業日数
B10: 月間営業日数 | C10: ='売上計画'!$C$7 -> 30 | D10: 通常25〜28日
F11: 安全余裕率 | H11: 現在の売上がBEPからどれだけ余裕があるか
B12: ■ 月間固定費の内訳
B13: 項目 | C13: 月額 | D13: メモ | F13: ■ シミュレーション
B14: 家賃 | C14: ='8月'!C20 -> 0 | F14: 仮に月の売上がこれだけあったら…
B15: 人件費 | C15: =IF('売上計画'!$O$45=0,0,'売上計画'!$O$54/COUNTIF('売上計画'!$C$45:$N$45,">0")) -> 45.5625 | D15: 営業中月の平均値 | F15: 月間売上 | G15: 利益 | H15: 判定
B16: 水道光熱費 | C16: ='8月'!C21 -> 0 | F16: 500000 | G16: =F16*(1-$C$8)-$C$9 -> 335520.6 | H16: =IF(G16>0,"✅ 黒字","❌ 赤字") -> ✅ 黒字
B17: 通信費 | C17: ='8月'!C22 -> 0 | F17: 700000 | G17: =F17*(1-$C$8)-$C$9 -> 475520.6 | H17: =IF(G17>0,"✅ 黒字","❌ 赤字") -> ✅ 黒字
B18: 保険料 | C18: ='8月'!C23 -> 0 | F18: 900000 | G18: =F18*(1-$C$8)-$C$9 -> 615520.6 | H18: =IF(G18>0,"✅ 黒字","❌ 赤字") -> ✅ 黒字
B19: 減価償却費 | C19: ='固定資産台帳'!J26 -> 14433.833 | F19: 1000000 | G19: =F19*(1-$C$8)-$C$9 -> 685520.6 | H19: =IF(G19>0,"✅ 黒字","❌ 赤字") -> ✅ 黒字
B20: その他固定費 | C20: 0 | F20: 1200000 | G20: =F20*(1-$C$8)-$C$9 -> 825520.6 | H20: =IF(G20>0,"✅ 黒字","❌ 赤字") -> ✅ 黒字
B21: 固定費 合計 | C21: =SUM(C14:C20) -> 14479.396 | D21: → 上の「月間固定費」に転記 | F21: 1500000 | G21: =F21*(1-$C$8)-$C$9 -> 1035520.6 | H21: =IF(G21>0,"✅ 黒字","❌ 赤字") -> ✅ 黒字
F22: 2000000 | G22: =F22*(1-$C$8)-$C$9 -> 1385520.6 | H22: =IF(G22>0,"✅ 黒字","❌ 赤字") -> ✅ 黒字
F24: ■ 客単価を変えたら？
F25: 客単価 | G25: 日次必要客数 | H25: 月間必要客数
F26: 500 | G26: =IF(F26=0,0,G6/F26) -> 41.369702 | H26: =G26*$C$10 -> 1241.0911
F27: 600 | G27: =IF(F27=0,0,G6/F27) -> 34.474752 | H27: =G27*$C$10 -> 1034.2426
F28: 700 | G28: =IF(F28=0,0,G6/F28) -> 29.549787 | H28: =G28*$C$10 -> 886.49362
F29: 800 | G29: =IF(F29=0,0,G6/F29) -> 25.856064 | H29: =G29*$C$10 -> 775.68192
F30: 900 | G30: =IF(F30=0,0,G6/F30) -> 22.983168 | H30: =G30*$C$10 -> 689.49504
F31: 1000 | G31: =IF(F31=0,0,G6/F31) -> 20.684851 | H31: =G31*$C$10 -> 620.54554
F32: 1200 | G32: =IF(F32=0,0,G6/F32) -> 17.237376 | H32: =G32*$C$10 -> 517.12128
F33: 1500 | G33: =IF(F33=0,0,G6/F33) -> 13.789901 | H33: =G33*$C$10 -> 413.69702

Sheet 年間サマリー
B1: ☕ 年間サマリー（自動集計）
B3: 項目 | C3: 4月 | D3: 5月 | E3: 6月 | F3: 7月 | G3: 8月 | H3: 9月 | I3: 10月 | J3: 11月 | K3: 12月 | L3: 1月 | M3: 2月 | N3: 3月 | O3: 年間合計
B4: 期首資金 | C4: ='4月'!C7 -> 0 | D4: ='5月'!C7 -> 3000000 | E4: ='6月'!C7 -> 2886000 | F4: ='7月'!C7 -> 4439612 | G4: ='8月'!C7 -> 3983694 | H4: ='9月'!C7 -> 1956398.6 | I4: ='10月'!C7 -> 1729103.2 | J4: ='11月'!C7 -> 1431360.1 | K4: ='12月'!C7 -> 1133617 | L4: ='1月'!C7 -> 835873.9 | M4: ='2月'!C7 -> 538130.8 | N4: ='3月'!C7 -> 240387.7 | O4: =C4 -> 0
B5: 売上高 | C5: ='4月'!H20 -> 0 | D5: ='5月'!H20 -> 0 | E5: ='6月'!H20 -> 0 | F5: ='7月'!H20 -> 0 | G5: ='8月'!H20 -> 0 | H5: ='9月'!H20 -> 0 | I5: ='10月'!H20 -> 0 | J5: ='11月'!H20 -> 0 | K5: ='12月'!H20 -> 0 | L5: ='1月'!H20 -> 0 | M5: ='2月'!H20 -> 0 | N5: ='3月'!H20 -> 0 | O5: =SUM(C5:N5) -> 0
B6: 原価合計 | C6: ='4月'!C16 -> 0 | D6: ='5月'!C16 -> 0 | E6: ='6月'!C16 -> 0 | F6: ='7月'!C16 -> 0 | G6: ='8月'!C16 -> 0 | H6: ='9月'!C16 -> 0 | I6: ='10月'!C16 -> 0 | J6: ='11月'!C16 -> 0 | K6: ='12月'!C16 -> 0 | L6: ='1月'!C16 -> 0 | M6: ='2月'!C16 -> 0 | N6: ='3月'!C16 -> 0 | O6: =SUM(C6:N6) -> 0
B7: 粗利益 | C7: =C5-C6 -> 0 | D7: =D5-D6 -> 0 | E7: =E5-E6 -> 0 | F7: =F5-F6 -> 0 | G7: =G5-G6 -> 0 | H7: =H5-H6 -> 0 | I7: =I5-I6 -> 0 | J7: =J5-J6 -> 0 | ... N7: =N5-N6 -> 0 | O7: =SUM(C7:N7) -> 0
B8: 粗利率 | C8: =IF(C5=0,0,C7/C5) -> 0 | D8: =IF(D5=0,0,D7/D5) -> 0 | E8: =IF(E5=0,0,E7/E5) -> 0 | F8: =IF(F5=0,0,F7/F5) -> 0 | G8: =IF(G5=0,0,G7/G5) -> 0 | H8: =IF(H5=0,0,H7/H5) -> 0 | I8: =IF(I5=0,0,I7/I5) -> 0 | J8: =IF(J5=0,0,J7/J5) -> 0 | ... O8: =IF(O5=0,0,O7/O5) -> 0
B9: 経費合計 | C9: ='4月'!C30 -> 0 | D9: ='5月'!C30 -> 0 | E9: ='6月'!C30 -> 14433.833 | F9: ='7月'!C30 -> 14433.833 | G9: ='8月'!C30 -> 241729.23 | H9: ='9月'!C30 -> 241729.23 | I9: ='10月'!C30 -> 312176.93 | J9: ='11月'!C30 -> 312176.93 | K9: ='12月'!C30 -> 312176.93 | L9: ='1月'!C30 -> 312176.93 | M9: ='2月'!C30 -> 312176.93 | N9: ='3月'!C30 -> 312176.93 | O9: =SUM(C9:N9) -> 2385387.7
B10: 一括経費 | C10: ='4月'!C54 -> 0 | D10: ='5月'!C54 -> 114000 | E10: ='6月'!C54 -> 318888 | F10: ='7月'!C54 -> 85790 | G10: ='8月'!C54 -> 2800000 | H10: ='9月'!C54 -> 0 | I10: ='10月'!C54 -> 0 | J10: ='11月'!C54 -> 0 | K10: ='12月'!C54 -> 0 | L10: ='1月'!C54 -> 0 | M10: ='2月'!C54 -> 0 | N10: ='3月'!C54 -> 0 | O10: =SUM(C10:N10) -> 3318678
B11: 営業利益 | C11: =C7-C9-C10 -> 0 | D11: =D7-D9-D10 -> -114000 | E11: =E7-E9-E10 -> -333321.83 | F11: =F7-F9-F10 -> -100223.83 | G11: =G7-G9-G10 -> -3041729.2 | H11: =H7-H9-H10 -> -241729.23 | I11: =I7-I9-I10 -> -312176.93 | J11: =J7-J9-J10 -> -312176.93 | ... N11: =N7-N9-N10 -> -312176.93 | O11: =SUM(C11:N11) -> -5704065.7
B12: 営業利益率 | C12: =IF(C5=0,0,C11/C5) -> 0 | D12: =IF(D5=0,0,D11/D5) -> 0 | E12: =IF(E5=0,0,E11/E5) -> 0 | F12: =IF(F5=0,0,F11/F5) -> 0 | G12: =IF(G5=0,0,G11/G5) -> 0 | H12: =IF(H5=0,0,H11/H5) -> 0 | I12: =IF(I5=0,0,I11/I5) -> 0 | J12: =IF(J5=0,0,J11/J5) -> 0 | ... O12: =IF(O5=0,0,O11/O5) -> 0
B13: 期末残高 | C13: ='4月'!I75 -> 0 | D13: ='5月'!I75 -> 2886000 | E13: ='6月'!I75 -> 939612 | F13: ='7月'!I75 -> 3983694 | G13: ='8月'!I75 -> 956398.6 | H13: ='9月'!I75 -> 1729103.2 | I13: ='10月'!I75 -> 1431360.1 | J13: ='11月'!I75 -> 1133617 | K13: ='12月'!I75 -> 835873.9 | L13: ='1月'!I75 -> 538130.8 | M13: ='2月'!I75 -> 240387.7 | N13: ='3月'!I75 -> -57355.4 | O13: =N13 -> -57355.4
B15: ■ キャッシュフロー
B16: 項目 | C16: 4月 | D16: 5月 | E16: 6月 | F16: 7月 | G16: 8月 | H16: 9月 | I16: 10月 | J16: 11月 | K16: 12月 | L16: 1月 | M16: 2月 | N16: 3月 | O16: 年間合計
B17: 営業CF | C17: ='4月'!I62 -> 0 | D17: ='5月'!I62 -> 0 | E17: ='6月'!I62 -> 0 | F17: ='7月'!I62 -> 0 | G17: ='8月'!I62 -> -227295.4 | H17: ='9月'!I62 -> -227295.4 | I17: ='10月'!I62 -> -297743.1 | J17: ='11月'!I62 -> -297743.1 | K17: ='12月'!I62 -> -297743.1 | L17: ='1月'!I62 -> -297743.1 | M17: ='2月'!I62 -> -297743.1 | N17: ='3月'!I62 -> -297743.1 | O17: =SUM(C17:N17) -> -2241049.4
B18: 投資CF | C18: ='4月'!I65 -> 0 | D18: ='5月'!I65 -> -114000 | E18: ='6月'!I65 -> -1946388 | F18: ='7月'!I65 -> -455918 | G18: ='8月'!I65 -> -2800000 | H18: ='9月'!I65 -> 0 | I18: ='10月'!I65 -> 0 | J18: ='11月'!I65 -> 0 | K18: ='12月'!I65 -> 0 | L18: ='1月'!I65 -> 0 | M18: ='2月'!I65 -> 0 | N18: ='3月'!I65 -> 0 | O18: =SUM(C18:N18) -> -5316306
B19: 財務CF | C19: ='4月'!I68 | D19: ='5月'!I68 | E19: ='6月'!I68 | F19: ='7月'!I68 -> 3500000 | G19: ='8月'!I68 | H19: ='9月'!I68 -> 1000000 | I19: ='10月'!I68 | J19: ='11月'!I68 | K19: ='12月'!I68 | L19: ='1月'!I68 | M19: ='2月'!I68 | N19: ='3月'!I68 | O19: =SUM(C19:N19) -> 4500000
B20: CF合計 | C20: =C17+C18+C19 -> 0 | D20: =D17+D18+D19 -> -114000 | E20: =E17+E18+E19 -> -1946388 | F20: =F17+F18+F19 -> 3044082 | G20: =G17+G18+G19 -> -3027295.4 | H20: =H17+H18+H19 -> 772704.6 | I20: =I17+I18+I19 -> -297743.1 | J20: =J17+J18+J19 -> -297743.1 | ... N20: =N17+N18+N19 -> -297743.1 | O20: =SUM(C20:N20) -> -3057355.4
B21: 期末口座残高 | C21: ='4月'!I75 -> 0 | D21: ='5月'!I75 -> 2886000 | E21: ='6月'!I75 -> 939612 | F21: ='7月'!I75 -> 3983694 | G21: ='8月'!I75 -> 956398.6 | H21: ='9月'!I75 -> 1729103.2 | I21: ='10月'!I75 -> 1431360.1 | J21: ='11月'!I75 -> 1133617 | K21: ='12月'!I75 -> 835873.9 | L21: ='1月'!I75 -> 538130.8 | M21: ='2月'!I75 -> 240387.7 | N21: ='3月'!I75 -> -57355.4 | O21: =N20 -> -297743.1

Sheet 使い方ガイド
B2: ☕ flat. 経営管理スプレッドシート 使い方ガイド
B3: v13 (2026/4/29更新): 役員報酬・社保連動、月次⇄売上計画 連動、損益分岐点修正など
B5: ■ 1. シート構成
B6: 役員報酬・社保 | C6: 【新規】3人の月額報酬・賞与・経費枠を入力 → 社保自動計算＋実質手取り
B7: 4月〜3月（月次） | C7: 実績入力＋右側に計画値ブロック（U列以降）
B8: 〇月日次売上 | C8: 日々の売上カテゴリ別記録（C-J列）。月計が月次シートH列に自動連携
B9: 売上計画 | C9: マスタシート: 来客数→売上→人件費→利益 自動計算
B10: 予実管理 | C10: F3に対象月入力 → 売上計画から予算自動取得、月次から実績自動取得
B11: 損益分岐点 | C11: 客単価・原価率・固定費から月間BEP売上・必要客数を算出
B12: メニュー別原価率 | C12: Notion確定メニュー（10ドリンク+4スイーツ）の売価・原価・原価率
B13: 固定資産台帳 | C13: 設備の取得価額・耐用年数→月額減価償却を自動計算（月次C29に反映）
B14: 仕入先・支払管理 | C14: 仕入先別の締日・支払日・支払予定額の管理
B15: 月次レポート | C15: 月次シートの主要指標を一覧表示
B16: 年間サマリー | C16: 12ヶ月の推移を一覧表示
B18: ■ 2. 入力セルの色
B19: 🟡 黄色背景 | C19: ユーザー手入力セル（料率、報酬額、来客数目標など）
B20: ⚪ グレー背景 | C20: 自動計算セル（数式が入っているので変更不可）
B21: 🟢 薄緑背景 | C21: 計画値ブロック（売上計画から自動取得）
B22: 🟠 オレンジ背景 | C22: 合計・重要指標
B23: 🔴 赤字 | C23: 警告・注意事項
B25: ■ 3. 役員報酬・社会保険の入力（重要）
B26: STEP 1: 「役員報酬・社保」シートで料率を確認（C7-C11、滋賀県R8デフォルト）
B27: STEP 2: 3人の月額報酬を入力（C17-E17、定期同額給与なので毎月同額）
B28: STEP 3: 年齢設定（40-64歳は「はい」、介護保険対象）
B29: STEP 4: flat.で社保加入するかを選択（國仲は副業先確認後に決定）
B30: STEP 5: 賞与（事前確定届出給与）を入力（年1回想定、3月支給）
B31: STEP 6: 「売上計画」シートのR165-180で月次反映を確認
B32: - C167: 開始月（5=8月、開業時）
B33: - C168: 「未払い」or「支払う」を選択
B34: STEP 7: 法人税試算 R183-189 で税負担を確認
B36: STEP 8: 「経費枠」の労働時間を入力（C97-E97、坂本10h/國仲25h/町田70h）
B37: STEP 9: 経費上限が自動計算（労働時間×1,080円/h）→ R100に表示
... B113: ・使い方ガイド全面リライト
